Workbook
Name _03: #REF!
Name _03: #REF!
Name _03: #REF!
Name _03: #REF!
Name _03: #REF!
Name _44242: #REF!
Name fff: #REF!
Name fff: #REF!
Name fff: #REF!
Name fff: #REF!
Name fff: #REF!
Name M: #REF!
Name M: #REF!
Name M: #REF!
Name M: #REF!
Name M: #REF!
Name импорт: #REF!
Name импорт: #REF!
Name импорт: #REF!
Name импорт: #REF!
Name импорт: #REF!
Name импорт8: #REF!
Name импорт8: #REF!
Name импорт8: #REF!
Name импорт8: #REF!
Name импорт8: #REF!

Sheet ТЗВ всего
D1: Таблица затраты-выпуcк (Input output tables)
C3: Продукты Продукты | D3: Goods/ products industry 1 | E3: Goods/ products industry 2 | F3: Goods/ products industry 3 | G3: Goods/ products industry 4 | H3: Goods/ products industry 5 | I3: Goods/ products industry 6 | J3: Goods/ products industry 7 | K3: Goods/ products industry 8 | L3: Goods/ products industry 9 | M3: Goods/ products industry 10 | N3: Goods/ products industry 11 | O3: Goods/ products industry 12 | P3: Goods/ products industry 13 | Q3: Goods/ products industry 14 | R3: Goods/ products industry 15 | S3: Goods/ products industry 16 | T3: Goods/ products industry 17 | U3: Goods/ products industry 18 | V3: Goods/ products industry 19 | W3: Goods/ products industry 20 | X3: Goods/ products industry 21 | Y3: Goods/ products industry 22 | Z3: Goods/ products industry 23 | AA3: Goods/ products industry 24 | AB3: Goods/ products industry 25 | AC3: Goods/ products industry 26 | AD3: Goods/ products industry 27 | AE3: Goods/ products industry 28 | AF3: Goods/ products industry 29 | AG3: Goods/ products industry 30 | AH3: Goods/ products industry 31 | AI3: Goods/ products industry 32 | AJ3: Goods/ products industry 33 | AK3: Goods/ products industry 34 | AL3: Goods/ products industry 35 | AM3: Goods/ products industry 36 | AN3: Goods/ products industry 37 | AO3: Goods/ products industry 38 | AP3: Goods/ products industry 39 | AQ3: Goods/ products industry 40 | AR3: Goods/ products industry 41 | AS3: Goods/ products industry 42 | AT3: Goods/ products industry 43 | AU3: Goods/ products industry 44 | AV3: Goods/ products industry 45 | AW3: Goods/ products industry 46 | AX3: Goods/ products industry 47 | AY3: Goods/ products industry 48 | AZ3: Goods/ products industry 49 | BA3: Goods/ products industry 50 | BB3: Goods/ products industry 51 | BC3: Goods/ products industry 52 | BD3: Goods/ products industry 53 | BE3: Goods/ products industry 54 | BF3: Goods/ products industry 55 | BG3: Goods/ products industry 56 | BH3: Goods/ products industry 57 | BI3: Goods/ products industry 58 | BJ3: Goods/ products industry 59 | BK3: Goods/ products industry 60 | BL3: Goods/ products industry 61 | BM3: Goods/ products industry 62 | BN3: Goods/ products industry 63 | BO3: Goods/ products industry 64 | BP3: Goods/ products industry 65 | BQ3: Goods/ products industry 66 | BR3: Goods/ products industry 67 | BS3: Goods/ products industry 68 | BT3: Goods/ products industry 69 | BU3: Goods/ products industry 70 | BV3: Goods/ products industry 71 | BW3: Goods/ products industry 72 | BX3: Goods/ products industry 73 | BY3: Goods/ products industry 74 | BZ3: Goods/ products industry 75 | CA3: Goods/ products industry 76 | CB3: Goods/ products industry 77 | CC3: Goods/ products industry 78 | CD3: Goods/ products industry 79 | CE3: Goods/ products industry 80 | CF3: Goods/ products industry 81 | CG3: Goods/ products industry 82 | CH3: Goods/ products industry 83 | CI3: Goods/ products industry 84 | CJ3: Goods/ products industry 85 | CK3: Goods/ products industry 86 | CL3: Goods/ products industry 87 | CM3: Goods/ products industry 88 | CN3: Goods/ products industry 89 | CO3: Goods/ products industry 90 | CP3: Goods/ products industry 91 | CQ3: Goods/ products industry 92 | CR3: Goods/ products industry 93 | CS3: Goods/ products industry 94 | CT3: Goods/ products industry 95 | CU3: Goods/ products industry 96 | CV3: Goods/ products industry 97 | CW3: Goods/ products industry 98 | CX3: Goods/ products industry 99 | CY3: Goods/ products industry 100 | CZ3: Goods/ products industry 101 | DA3: Goods/ products industry 102 | DB3: Goods/ products industry 103 | DC3: Goods/ products industry 104 | DD3: Goods/ products industry 105 | DE3: Goods/ products industry 106 | DF3: Goods/ products industry 107 | DG3: Goods/ products industry 108 | DH3: Goods/ products industry 109 | DI3: Goods/ products industry 110 | DJ3: Goods/ products industry 111 | DK3: Goods/ products industry 112 | DL3: Goods/ products industry 113 | DM3: Goods/ products industry 114 | DN3: Goods/ products industry 115 | DO3: Goods/ products industry 116 | DP3: Goods/ products industry 117 | DQ3: Goods/ products industry 118 | DR3: Goods/ products industry 119 | DS3: Goods/ products industry 120 | DT3: Goods/ products industry 121 | DU3: Goods/ products industry 122 | DV3: Goods/ products industry 123 | DW3: Goods/ products industry 124 | DX3: Goods/ products industry 125 | DY3: Goods/ products industry 126 | DZ3: Goods/ products industry 127 | EA3: Goods/ products industry 128 | EB3: Goods/ products industry 129 | EC3: Goods/ products industry 130 | ED3: Goods/ products industry 131 | EE3: Goods/ products industry 132 | EF3: Goods/ products industry 133 | EG3: Goods/ products industry 134 | EH3: Goods/ products industry 135 | EI3: Goods/ products industry 136 | EJ3: Промежуточный спрос | EK3: Расходы на конечное потребление | EO3: Валовое накопление | EQ3: Экспорт | ER3: Конечный спрос | ES3: Всего использовано ресурсов | ET3: Импорт товаров и услуг в основных ценах | EU3: Выпуск
EK4: домашних хозяйств | EL4: государственных учреждений | EN4: некоммерческих организаций, обслужиающих домашние хозяйства | EO4: основного капитала | EP4: изменение запасов МОС
EL5: на индивидуальные товары и услуги | EM5: на коллективные услуги | ET5: импорт
B6: Коды | D6: Code 1 | E6: Code 2 | F6: Code 3 | G6: Code 4 | H6: Code 5 | I6: Code 6 | J6: Code 7 | K6: Code 8 | L6: Code 9 | M6: Code 10 | N6: Code 11 | O6: Code 12 | P6: Code 13 | Q6: Code 14 | R6: Code 15 | S6: Code 16 | T6: Code 17 | U6: Code 18 | V6: Code 19 | W6: Code 20 | X6: Code 21 | Y6: Code 22 | Z6: Code 23 | AA6: Code 24 | AB6: Code 25 | AC6: Code 26 | AD6: Code 27 | AE6: Code 28 | AF6: Code 29 | AG6: Code 30 | AH6: Code 31 | AI6: Code 32 | AJ6: Code 33 | AK6: Code 34 | AL6: Code 35 | AM6: Code 36 | AN6: Code 37 | AO6: Code 38 | AP6: Code 39 | AQ6: Code 40 | AR6: Code 41 | AS6: Code 42 | AT6: Code 43 | AU6: Code 44 | AV6: Code 45 | AW6: Code 46 | AX6: Code 47 | AY6: Code 48 | AZ6: Code 49 | BA6: Code 50 | BB6: Code 51 | BC6: Code 52 | BD6: Code 53 | BE6: Code 54 | BF6: Code 55 | BG6: Code 56 | BH6: Code 57 | BI6: Code 58 | BJ6: Code 59 | BK6: Code 60 | BL6: Code 61 | BM6: Code 62 | BN6: Code 63 | BO6: Code 64 | BP6: Code 65 | BQ6: Code 66 | BR6: Code 67 | BS6: Code 68 | BT6: Code 69 | BU6: Code 70 | BV6: Code 71 | BW6: Code 72 | BX6: Code 73 | BY6: Code 74 | BZ6: Code 75 | CA6: Code 76 | CB6: Code 77 | CC6: Code 78 | CD6: Code 79 | CE6: Code 80 | CF6: Code 81 | CG6: Code 82 | CH6: Code 83 | CI6: Code 84 | CJ6: Code 85 | CK6: Code 86 | CL6: Code 87 | CM6: Code 88 | CN6: Code 89 | CO6: Code 90 | CP6: Code 91 | CQ6: Code 92 | CR6: Code 93 | CS6: Code 94 | CT6: Code 95 | CU6: Code 96 | CV6: Code 97 | CW6: Code 98 | CX6: Code 99 | CY6: Code 100 | CZ6: Code 101 | DA6: Code 102 | DB6: Code 103 | DC6: Code 104 | DD6: Code 105 | DE6: Code 106 | DF6: Code 107 | DG6: Code 108 | DH6: Code 109 | DI6: Code 110 | DJ6: Code 111 | DK6: Code 112 | DL6: Code 113 | DM6: Code 114 | DN6: Code 115 | DO6: Code 116 | DP6: Code 117 | DQ6: Code 118 | DR6: Code 119 | DS6: Code 120 | DT6: Code 121 | DU6: Code 122 | DV6: Code 123 | DW6: Code 124 | DX6: Code 125 | DY6: Code 126 | DZ6: Code 127 | EA6: Code 128 | EB6: Code 129 | EC6: Code 130 | ED6: Code 131 | EE6: Code 132 | EF6: Code 133 | EG6: Code 134 | EH6: Code 135 | EI6: Code 136
A7: № | D7: 1 | E7: 2 | F7: 3 | G7: 4 | H7: 5 | I7: 6 | J7: 7 | K7: 8 | L7: 9 | M7: 10 | N7: 11 | O7: 12 | P7: 13 | Q7: 14 | R7: 15 | S7: 16 | T7: 17 | U7: 18 | V7: 19 | W7: 20 | X7: 21 | Y7: 22 | Z7: 23 | AA7: 24 | AB7: 25 | AC7: 26 | AD7: 27 | AE7: 28 | AF7: 29 | AG7: 30 | AH7: 31 | AI7: 32 | AJ7: 33 | AK7: 34 | AL7: 35 | AM7: 36 | AN7: 37 | AO7: 38 | AP7: 39 | AQ7: 40 | AR7: 41 | AS7: 42 | AT7: 43 | AU7: 44 | AV7: 45 | AW7: 46 | AX7: 47 | AY7: 48 | AZ7: 49 | BA7: 50 | BB7: 51 | BC7: 52 | BD7: 53 | BE7: 54 | BF7: 55 | BG7: 56 | BH7: 57 | BI7: 58 | BJ7: 59 | BK7: 60 | BL7: 61 | BM7: 62 | BN7: 63 | BO7: 64 | BP7: 65 | BQ7: 66 | BR7: 67 | BS7: 68 | BT7: 69 | BU7: 70 | BV7: 71 | BW7: 72 | BX7: 73 | BY7: 74 | BZ7: 75 | CA7: 76 | CB7: 77 | CC7: 78 | CD7: 79 | CE7: 80 | CF7: 81 | CG7: 82 | CH7: 83 | CI7: 84 | CJ7: 85 | CK7: 86 | CL7: 87 | CM7: 88 | CN7: 89 | CO7: 90 | CP7: 91 | CQ7: 92 | CR7: 93 | CS7: 94 | CT7: 95 | CU7: 96 | CV7: 97 | CW7: 98 | CX7: 99 | CY7: 100 | CZ7: 101 | DA7: 102 | DB7: 103 | DC7: 104 | DD7: 105 | DE7: 106 | DF7: 107 | DG7: 108 | DH7: 109 | DI7: 110 | DJ7: 111 | DK7: 112 | DL7: 113 | DM7: 114 | DN7: 115 | DO7: 116 | DP7: 117 | DQ7: 118 | DR7: 119 | DS7: 120 | DT7: 121 | DU7: 122 | DV7: 123 | DW7: 124 | DX7: 125 | DY7: 126 | DZ7: 127 | EA7: 128 | EB7: 129 | EC7: 130 | ED7: 131 | EE7: 132 | EF7: 133 | EG7: 134 | EH7: 135 | EI7: 136 | EJ7: 138 | EK7: 139 | EL7: 140 | EM7: 141 | EN7: 142 | EO7: 143 | EP7: 144 | EQ7: 145 | ER7: 146 | ES7: 147
A8: 1 | B8: Code 1 | C8: Goods/ products industry 1 | D8: 1497846.5 | E8: 311524.39 | F8: 375251.56 | G8: 267422.14 | H8: 1565972.7 | I8: 421314.52 | J8: 157.24953 | K8: 37721.933 | L8: 0 | M8: 0 | N8: 0 | O8: 0 | P8: 2.9306456e-06 | Q8: 220.56964 | R8: 0 | S8: 202866.68 | T8: 9086.2839 | U8: 175999.61 | V8: 580908.19 | W8: 4518.8395 | X8: 1809405.6 | Y8: 41145.774 | Z8: 7158.9517 | AA8: 697.58785 | AB8: 242859.58 | AC8: 146528.79 | AD8: 6.6281356 | AE8: 49.862502 | AF8: 7.2484308 | AG8: 2.7410632e-06 | AH8: 94.479323 | AI8: 125.47864 | AJ8: 563.11154 | AK8: 26.43076 | AL8: 112.04762 | AM8: 4.4437097e-07 | AN8: 0 | AO8: 33.886659 | AP8: 2114.2392 | AQ8: 22.253691 | AR8: 68.598513 | AS8: 72.698916 | AT8: 0 | AU8: 17297.505 | AV8: 389.25918 | AW8: 0 | AX8: 230.50314 | AY8: 0.00028423703 | AZ8: 142.90013 | BA8: 1393.7824 | BB8: 15.742698 | BC8: 19.466886 | BD8: 0.00026752603 | BE8: 2.0378886 | BF8: 263.4742 | BG8: 0.27987604 | BH8: 126.97845 | BI8: 372.89065 | BJ8: 0.0095275498 | BK8: 2.1401141 | BL8: 16.680174 | BM8: 0.0079989135 | BN8: 206.07913 | BO8: 0.0057709769 | BP8: 0 | BQ8: 2.940393 | BR8: 18.971381 | BS8: 4.5888265 | BT8: 0.21506286 | BU8: 0 | BV8: 0.0063602359 | BW8: 2.7513155e-06 | BX8: 0 | BY8: 0.036364549 | BZ8: 1182.0773 | CA8: 0.037520376 | CB8: 0.0047211152 | CC8: 0.0055770207 | CD8: 3.5002291 | CE8: 0 | CF8: 93.059542 | CG8: 6.2413595 | CH8: 38.047946 | CI8: 0 | CJ8: 3.809903 | CK8: 145.44006 | CL8: 0 | CM8: 0 | CN8: 0 | CO8: 0.0056736587 | CP8: 84.45754 | CQ8: 104.18572 | CR8: 0.00221048 | CS8: 13.910298 | CT8: 0 | CU8: 0.0019240634 | CV8: 0 | CW8: 0 | CX8: 0 | CY8: 0 | CZ8: 55.521047 | DA8: 4925.9307 | DB8: 0 | DC8: 0 | DD8: 0 | DE8: 0 | DF8: 0 | DG8: 0 | DH8: 0 | DI8: 0 | DJ8: 0 | DK8: 0 | DL8: 0 | DM8: 0.31869093 | DN8: 1.9507967 | DO8: 28.399718 | DP8: 0 | DQ8: 5867.3401 | DR8: 0.064086699 | DS8: 389.52253 | DT8: 6.1510913 | DU8: 0.0007958256 | DV8: 0 | DW8: 946.71763 | DX8: 2.9094501 | DY8: 4610.3368 | DZ8: 4783.8626 | EA8: 1176.3175 | EB8: 0 | EC8: 480.15006 | ED8: 70.900101 | EE8: 0 | EF8: 138.20222 | EG8: 19.658185 | EH8: 18.116248 | EI8: 22.482977 | EJ8: =SUM(D8:EI8) -> 7747630.6 | EK8: Information sanitized
A9: 2 | B9: Code 2 | C9: Goods/ products industry 2 | D9: 251930.57 | E9: 4431869.7 | F9: 421276.61 | G9: 209212.94 | H9: 123772.55 | I9: 839431.58 | J9: 1083.5789 | K9: 83.43782 | L9: 0 | M9: 0 | N9: 0 | O9: 0 | P9: 0 | Q9: 151.91978 | R9: 0 | S9: 582.96927 | T9: 31.867003 | U9: 150767.61 | V9: 53.189512 | W9: 433.42924 | X9: 570.26511 | Y9: 5862.8779 | Z9: 1859.4594 | AA9: 4.203668 | AB9: 727.53649 | AC9: 804.52034 | AD9: 0.51946199 | AE9: 41.538421 | AF9: 6.5302453 | AG9: 0 | AH9: 6.3975576 | AI9: 7.3006495 | AJ9: 1.157694 | AK9: 19.910055 | AL9: 97.845336 | AM9: 0 | AN9: 0 | AO9: 0.0022433638 | AP9: 0.19912059 | AQ9: 4.0250265 | AR9: 0.011555683 | AS9: 0.079191971 | AT9: 0 | AU9: 1.7042936 | AV9: 0.025752127 | AW9: 0 | AX9: 5.110417 | AY9: 0 | AZ9: 0.22904906 | BA9: 0.99755436 | BB9: 3.7944113 | BC9: 0.00041120494 | BD9: 0 | BE9: 0.34654285 | BF9: 0.34401744 | BG9: 0.047592771 | BH9: 0.011107929 | BI9: 1.4428892 | BJ9: 0.0016177988 | BK9: 0.0001316181 | BL9: 0.0011041376 | BM9: 0 | BN9: 2.0773484 | BO9: 0 | BP9: 0 | BQ9: 0.23923323 | BR9: 2.1424887 | BS9: 0.7757604 | BT9: 0 | BU9: 0 | BV9: 0 | BW9: 0 | BX9: 0 | BY9: 0 | BZ9: 0.98767794 | CA9: 0 | CB9: 0 | CC9: 0 | CD9: 0.0068594964 | CE9: 0 | CF9: 0.187013 | CG9: 1.0112139 | CH9: 25.990585 | CI9: 0 | CJ9: 0.57099858 | CK9: 3.8919075 | CL9: 0 | CM9: 0 | CN9: 0 | CO9: 0 | CP9: 0.05356604 | CQ9: 0.21482552 | CR9: 0 | CS9: 1.7342169 | CT9: 0 | CU9: 0 | CV9: 0 | CW9: 0 | CX9: 0 | CY9: 0 | CZ9: 1151.0101 | DA9: 124320.82 | DB9: 0 | DC9: 0 | DD9: 0.0083963098 | DE9: 0 | DF9: 0 | DG9: 0 | DH9: 0 | DI9: 0 | DJ9: 0 | DK9: 0 | DL9: 7.2622878 | DM9: 0 | DN9: 5.6678435 | DO9: 8.9375722 | DP9: 0 | DQ9: 13865.713 | DR9: 0.14727257 | DS9: 280.26468 | DT9: 0 | DU9: 0.0015056075 | DV9: 0 | DW9: 0 | DX9: 3.4515783 | DY9: 197791.43 | DZ9: 87224.059 | EA9: 11966.113 | EB9: 421.46779 | EC9: 7935.3075 | ED9: 861.60777 | EE9: 0 | EF9: 1353.7088 | EG9: 29.769356 | EH9: 0 | EI9: 948.79844 | EJ9: =SUM(D9:EI9) -> 6888925.8
A10: 3 | B10: Code 3 | C10: Goods/ products industry 3 | D10: 403832.48 | E10: 5973.9516 | F10: 216019.81 | G10: 0 | H10: 0 | I10: 1648.8603 | J10: 0 | K10: 0 | L10: 0 | M10: 0 | N10: 0 | O10: 0 | P10: 0 | Q10: 0.79495376 | R10: 0 | S10: 133.50644 | T10: 0 | U10: 4.7070421 | V10: 90299.264 | W10: 0.056209429 | X10: 0.6673336 | Y10: 69.692767 | Z10: 39.291104 | AA10: 0 | AB10: 0 | AC10: 1.6497753 | AD10: 0 | AE10: 4301187.8 | AF10: 122953.77 | AG10: 1975.9863 | AH10: 190461.71 | AI10: 24918.92 | AJ10: 180.12524 | AK10: 0.58739806 | AL10: 1945.1383 | AM10: 206.55105 | AN10: 0 | AO10: 0 | AP10: 35.973939 | AQ10: 0 | AR10: 7.7728113 | AS10: 0 | AT10: 30.642103 | AU10: 5.4285542 | AV10: 81.127641 | AW10: 17117.792 | AX10: 2.2645922 | AY10: 750.23378 | AZ10: 655.70243 | BA10: 3439.2044 | BB10: 10.627769 | BC10: 225.32958 | BD10: 0.06625091 | BE10: 22.610691 | BF10: 0 | BG10: 0.06625091 | BH10: 128.00659 | BI10: 27.580014 | BJ10: 0 | BK10: 4.7808596 | BL10: 0.93177368 | BM10: 0.025829734 | BN10: 0 | BO10: 0 | BP10: 3.870829 | BQ10: 23.641641 | BR10: 9.1793904 | BS10: 7.1452664 | BT10: 0.0067972985 | BU10: 0 | BV10: 0 | BW10: 0 | BX10: 0 | BY10: 0.0067972985 | BZ10: 67.995577 | CA10: 3.8743242 | CB10: 0.29445897 | CC10: 0 | CD10: 0.96606218 | CE10: 87.924027 | CF10: 0.0067972985 | CG10: 790.26433 | CH10: 33.263768 | CI10: 0.28581066 | CJ10: 114.7249 | CK10: 0.12914867 | CL10: 0 | CM10: 64.545244 | CN10: 0 | CO10: 0 | CP10: 821.97077 | CQ10: 0 | CR10: 0 | CS10: 19439.154 | CT10: 0 | CU10: 0 | CV10: 0 | CW10: 0 | CX10: 0 | CY10: 0 | CZ10: 0 | DA10: 0 | DB10: 0 | DC10: 0 | DD10: 0 | DE10: 0 | DF10: 0 | DG10: 0 | DH10: 0 | DI10: 0 | DJ10: 0 | DK10: 0 | DL10: 0 | DM10: 0 | DN10: 0 | DO10: 6.9832192 | DP10: 0 | DQ10: 0 | DR10: 0 | DS10: 0 | DT10: 0 | DU10: 0 | DV10: 0 | DW10: 0 | DX10: 0 | DY10: 0 | DZ10: 0.20993857 | EA10: 0 | EB10: 0 | EC10: 0 | ED10: 0 | EE10: 0 | EF10: 0 | EG10: 0 | EH10: 0 | EI10: 0 | EJ10: =SUM(D10:EI10) -> 5405877.9
A11: 4 | B11: Code 4 | C11: Goods/ products industry 4 | D11: 5590.6908 | E11: 77355.102 | F11: 29.063222 | G11: 112020.66 | H11: 6886.5132 | I11: 50719.889 | J11: 0 | K11: 52.189911 | L11: 0 | M11: 0 | N11: 0 | O11: 0 | P11: 0 | Q11: 92.359251 | R11: 0 | S11: 84.460756 | T11: 0 | U11: 93082.005 | V11: 1.6109434 | W11: 262.95469 | X11: 115.73215 | Y11: 177.65844 | Z11: 632.49313 | AA11: 102.77394 | AB11: 34.429475 | AC11: 649407.37 | AD11: 0.38186882 | AE11: 25.31387 | AF11: 4.0219238 | AG11: 0 | AH11: 0.022962738 | AI11: 3.8086349 | AJ11: 0.00012309814 | AK11: 12.266957 | AL11: 68.897771 | AM11: 0 | AN11: 0 | AO11: 0 | AP11: 67.407706 | AQ11: 2.3687938 | AR11: 0.00070736461 | AS11: 329.84818 | AT11: 0 | AU11: 9.0652279 | AV11: 1.7806925 | AW11: 0 | AX11: 0.0023563067 | AY11: 0 | AZ11: 568.72419 | BA11: 4181.9268 | BB11: 0 | BC11: 88.777623 | BD11: 0 | BE11: 0.0012440903 | BF11: 0.0037752557 | BG11: 0.00017085825 | BH11: 0 | BI11: 0.026958762 | BJ11: 5.8079047e-06 | BK11: 0 | BL11: 0 | BM11: 0 | BN11: 0 | BO11: 0 | BP11: 0 | BQ11: 0.00030844636 | BR11: 0.0075736232 | BS11: 0.0027849832 | BT11: 0 | BU11: 0 | BV11: 0 | BW11: 0 | BX11: 0 | BY11: 0 | BZ11: 15.148415 | CA11: 0 | CB11: 0 | CC11: 0 | CD11: 0 | CE11: 0 | CF11: 5.047304e-06 | CG11: 0.0031658365 | CH11: 11.332782 | CI11: 0 | CJ11: 0.0017525361 | CK11: 1.6380661 | CL11: 0 | CM11: 0 | CN11: 0 | CO11: 0 | CP11: 7.4270966 | CQ11: 455.58683 | CR11: 0 | CS11: 0.0062619104 | CT11: 0 | CU11: 0 | CV11: 0 | CW11: 0 | CX11: 0 | CY11: 0 | CZ11: 17.612116 | DA11: 0 | DB11: 0 | DC11: 0 | DD11: 0.020602333 | DE11: 0 | DF11: 0 | DG11: 0 | DH11: 0 | DI11: 0 | DJ11: 0 | DK11: 0 | DL11: 0 | DM11: 0 | DN11: 0 | DO11: 0.1217217 | DP11: 0 | DQ11: 5147.6641 | DR11: 0 | DS11: 280.91978 | DT11: 0 | DU11: 0.0034495706 | DV11: 0 | DW11: 0 | DX11: 0 | DY11: 23005.961 | DZ11: 1821.7965 | EA11: 137.01248 | EB11: 0 | EC11: 0 | ED11: 1.2080013 | EE11: 0 | EF11: 73.999242 | EG11: 0.45989022 | EH11: 0 | EI11: 0.96680841 | EJ11: =SUM(D11:EI11) -> 1032991.5
A12: 5 | B12: Code 5 | C12: Goods/ products industry 5 | D12: 208951.91 | E12: 166620.61 | F12: 9123.8446 | G12: 66314.215 | H12: 11362093 | I12: 406786.67 | J12: 3867.3897 | K12: 7991.8169 | L12: 0 | M12: 0 | N12: 0 | O12: 0 | P12: 0.26692161 | Q12: 308.014 | R12: 0.034863684 | S12: 983620.76 | T12: 8202.4399 | U12: 1229.9427 | V12: 252958.73 | W12: 627662.79 | X12: 2593.3434 | Y12: 20466.206 | Z12: 18723.208 | AA12: 24.825596 | AB12: 20118.054 | AC12: 8977.417 | AD12: 5.7934324 | AE12: 114615.65 | AF12: 8311.3448 | AG12: 175.13872 | AH12: 4869.5592 | AI12: 3955.6728 | AJ12: 124680.71 | AK12: 0.1519361 | AL12: 988.37892 | AM12: 2.3270761 | AN12: 0 | AO12: 14.902484 | AP12: 1861.6096 | AQ12: 114.99166 | AR12: 9.0473442 | AS12: 1.0141152 | AT12: 0.34582158 | AU12: 7678.0113 | AV12: 173.99053 | AW12: 436.21608 | AX12: 207.11296 | AY12: 39.759828 | AZ12: 49.931536 | BA12: 710.18822 | BB12: 53.784894 | BC12: 4.6699665 | BD12: 0.0063337503 | BE12: 1.3989187 | BF12: 1234.7756 | BG12: 0.15801432 | BH12: 59.150448 | BI12: 481.24851 | BJ12: 0.0061814918 | BK12: 1.2205604 | BL12: 7.388319 | BM12: 146.78291 | BN12: 26.336674 | BO12: 0.029905137 | BP12: 0.0434354 | BQ12: 12.112857 | BR12: 137.28904 | BS12: 2.6436885 | BT12: 0.001481392 | BU12: 0 | BV12: 0 | BW12: 0 | BX12: 0 | BY12: 0.00017392216 | BZ12: 16.778092 | CA12: 0.099132154 | CB12: 0.0075343081 | CC12: 0 | CD12: 17.133392 | CE12: 566.59968 | CF12: 462.07742 | CG12: 24.819857 | CH12: 94.472127 | CI12: 0.0032071425 | CJ12: 6.9465021 | CK12: 14.912118 | CL12: 0 | CM12: 1.6550755 | CN12: 0 | CO12: 0.00035792871 | CP12: 208.19111 | CQ12: 1.0443405 | CR12: 0.19072572 | CS12: 1367.1777 | CT12: 0 | CU12: 0 | CV12: 0 | CW12: 0 | CX12: 0 | CY12: 0 | CZ12: 267.06127 | DA12: 410909.89 | DB12: 0 | DC12: 0 | DD12: 0.1188045 | DE12: 0 | DF12: 0 | DG12: 0 | DH12: 0 | DI12: 0 | DJ12: 0 | DK12: 0 | DL12: 0 | DM12: 0 | DN12: 0 | DO12: 161.20744 | DP12: 0 | DQ12: 0 | DR12: 94.336738 | DS12: 44.100532 | DT12: 5.7040257 | DU12: 0 | DV12: 0 | DW12: 0 | DX12: 0 | DY12: 220211.18 | DZ12: 370008.72 | EA12: 56776.1 | EB12: 504.03043 | EC12: 1010.1278 | ED12: 3046.6391 | EE12: 241.58086 | EF12: 8133.2083 | EG12: 3.6947213 | EH12: 0 | EI12: 0 | EJ12: =SUM(D12:EI12) -> 15521906
A13: 6 | B13: Code 6 | C13: Goods/ products industry 6 | D13: 595563.55 | E13: 1767962.5 | F13: 689429.08 | G13: 699545.39 | H13: 3029674.8 | I13: 2985459 | J13: 79046.335 | K13: 8666.0449 | L13: 11.950111 | M13: 1.0235125 | N13: 6.0188344 | O13: 0 | P13: 0.012504484 | Q13: 232.89151 | R13: 0.69899179 | S13: 8974.9444 | T13: 1094.0476 | U13: 174920.46 | V13: 2845.2176 | W13: 698.45258 | X13: 8867.3281 | Y13: 10294.833 | Z13: 12924.641 | AA13: 36.61802 | AB13: 17276.355 | AC13: 99376.739 | AD13: 22306.647 | AE13: 7010.6598 | AF13: 231.18492 | AG13: 4.6172417 | AH13: 982.60563 | AI13: 255.7442 | AJ13: 420.20964 | AK13: 6341.9619 | AL13: 586.97765 | AM13: 3.5155729 | AN13: 0.00016590354 | AO13: 16.702834 | AP13: 1068.7031 | AQ13: 8379.2634 | AR13: 675.62239 | AS13: 224.74145 | AT13: 0.469149 | AU13: 1965.499 | AV13: 217.47166 | AW13: 31.902438 | AX13: 29456.701 | AY13: 3872.1617 | AZ13: 4196.745 | BA13: 839.62467 | BB13: 95.511974 | BC13: 314.06906 | BD13: 1.0286001 | BE13: 14.94881 | BF13: 5.7451895 | BG13: 2.9454396 | BH13: 0.81115454 | BI13: 16.350845 | BJ13: 0.12484103 | BK13: 3.7461701 | BL13: 4.2646453 | BM13: 14.86047 | BN13: 75.892238 | BO13: 22.829053 | BP13: 0.049658437 | BQ13: 202.29157 | BR13: 62.278341 | BS13: 16.114376 | BT13: 4.2160299 | BU13: 3.3911519 | BV13: 15.406718 | BW13: 29.385838 | BX13: 61.733775 | BY13: 7.2094517 | BZ13: 771.20429 | CA13: 16.119165 | CB13: 11.651627 | CC13: 8.2648231 | CD13: 0.25744723 | CE13: 15.96419 | CF13: 5.3622095 | CG13: 1056.7302 | CH13: 246.68117 | CI13: 545.68419 | CJ13: 69.922486 | CK13: 81.860041 | CL13: 7284.8816 | CM13: 0.3682216 | CN13: 0 | CO13: 0.00026259297 | CP13: 90.716592 | CQ13: 75.644224 | CR13: 14.165633 | CS13: 52.542146 | CT13: 3.9493202 | CU13: 9384.3644 | CV13: 73869.086 | CW13: 8974.4692 | CX13: 0 | CY13: 0 | CZ13: 517.97144 | DA13: 17413.585 | DB13: 0.0026923282 | DC13: 5.962764 | DD13: 119.43112 | DE13: 0.00076251329 | DF13: 27.603602 | DG13: 3.461289 | DH13: 47.418166 | DI13: 0 | DJ13: 36.206428 | DK13: 1023.6932 | DL13: 66.431978 | DM13: 0 | DN13: 37.878862 | DO13: 4481.335 | DP13: 14.06954 | DQ13: 22338.077 | DR13: 0.49030789 | DS13: 950.77857 | DT13: 0 | DU13: 62.94267 | DV13: 0 | DW13: 50309.444 | DX13: 2446.7931 | DY13: 295876.06 | DZ13: 65005.779 | EA13: 2445.3965 | EB13: 599.52564 | EC13: 1104.9521 | ED13: 839.46057 | EE13: 6.0028122 | EF13: 1083.9261 | EG13: 82.457165 | EH13: 327.27166 | EI13: 6600.2046 | EJ13: =SUM(D13:EI13) -> 10859428
A14: 7 | B14: Code 7 | C14: Goods/ products industry 7 | D14: 0.31572756 | E14: 14593.634 | F14: 0 | G14: 177.09034 | H14: 50790.444 | I14: 3809.5949 | J14: 577097.29 | K14: 136.39341 | L14: 5368.4814 | M14: 87.857296 | N14: 802.58687 | O14: 0 | P14: 4623.9629 | Q14: 6441.5938 | R14: 38.019192 | S14: 0.66806576 | T14: 0 | U14: 107.79441 | V14: 132.75611 | W14: 6.5781102 | X14: 41.533254 | Y14: 1874.7359 | Z14: 112.02601 | AA14: 1.0134927 | AB14: 6.3997773 | AC14: 21.728636 | AD14: 0 | AE14: 13.380419 | AF14: 2.1693272 | AG14: 0.00037307121 | AH14: 81.25283 | AI14: 15.456522 | AJ14: 83.145296 | AK14: 158859.37 | AL14: 6350.8383 | AM14: 8.4570196 | AN14: 0.002206428 | AO14: 125.0254 | AP14: 706.72351 | AQ14: 71.465028 | AR14: 1362.423 | AS14: 2.9143544 | AT14: 93614.342 | AU14: 624.64141 | AV14: 2230.4273 | AW14: 0.00049347755 | AX14: 6.2510786 | AY14: 415.16093 | AZ14: 10702.251 | BA14: 49.063607 | BB14: 526.01625 | BC14: 36.295553 | BD14: 22.410046 | BE14: 370.54569 | BF14: 114.43632 | BG14: 88.956015 | BH14: 2362.4663 | BI14: 5194.3299 | BJ14: 48.405906 | BK14: 785.41024 | BL14: 19.512546 | BM14: 6.2400054 | BN14: 65.180791 | BO14: 410.62111 | BP14: 0 | BQ14: 342.51154 | BR14: 2644.9224 | BS14: 299.3992 | BT14: 19.31124 | BU14: 0.21062003 | BV14: 66.698975 | BW14: 24.402365 | BX14: 1209.0368 | BY14: 1.7981505 | BZ14: 1040.9249 | CA14: 1.603531 | CB14: 94.501486 | CC14: 14.646853 | CD14: 1.2979207 | CE14: 75.618924 | CF14: 12807.508 | CG14: 21194.363 | CH14: 85.785951 | CI14: 184.48941 | CJ14: 55.358481 | CK14: 895.46849 | CL14: 4.7899181 | CM14: 0 | CN14: 0 | CO14: 0 | CP14: 120.55009 | CQ14: 0.11228136 | CR14: 0.0023949544 | CS14: 916.49766 | CT14: 0 | CU14: 723743.74 | CV14: 0 | CW14: 426.64789 | CX14: 0 | CY14: 0 | CZ14: 23.489921 | DA14: 324.20366 | DB14: 0 | DC14: 0 | DD14: 0 | DE14: 0 | DF14: 0 | DG14: 0 | DH14: 0 | DI14: 0 | DJ14: 0 | DK14: 10086.546 | DL14: 0 | DM14: 0 | DN14: 0 | DO14: 0 | DP14: 0 | DQ14: 10.803266 | DR14: 0 | DS14: 0 | DT14: 0 | DU14: 0 | DV14: 0 | DW14: 5109.5434 | DX14: 0 | DY14: 754.46604 | DZ14: 38.886249 | EA14: 44.352599 | EB14: 0 | EC14: 0 | ED14: 17.94241 | EE14: 0 | EF14: 0 | EG14: 0 | EH14: 0 | EI14: 0 | EJ14: =SUM(D14:EI14) -> 1734330.5
A15: 8 | B15: Code 8 | C15: Goods/ products industry 8 | D15: 700.86139 | E15: 4967.4747 | F15: 57.815041 | G15: 208.39821 | H15: 45826.869 | I15: 1235.5986 | J15: 0 | K15: 174246.96 | L15: 0 | M15: 0 | N15: 0 | O15: 0 | P15: 0 | Q15: 0.89663018 | R15: 0 | S15: 134.95409 | T15: 992.37772 | U15: 2.9242128 | V15: 0.092284997 | W15: 1.2938368 | X15: 0.45654314 | Y15: 21.902903 | Z15: 226.29691 | AA15: 0.26464091 | AB15: 10.703282 | AC15: 0.11944144 | AD15: 0 | AE15: 0.00024289747 | AF15: 0.00088083746 | AG15: 0 | AH15: 0 | AI15: 0.25111484 | AJ15: 0.37474661 | AK15: 0 | AL15: 0.16348004 | AM15: 0 | AN15: 0 | AO15: 0 | AP15: 0.012958904 | AQ15: 0.0026595138 | AR15: 0 | AS15: 0.016125305 | AT15: 0 | AU15: 0.12472592 | AV15: 0 | AW15: 0 | AX15: 1.0987091 | AY15: 0 | AZ15: 0.00023410962 | BA15: 0.18965349 | BB15: 0.8217627 | BC15: 0 | BD15: 0 | BE15: 0 | BF15: 0 | BG15: 0 | BH15: 0.00058527406 | BI15: 0.10941175 | BJ15: 0 | BK15: 0 | BL15: 0 | BM15: 0 | BN15: 0.030472785 | BO15: 0 | BP15: 0 | BQ15: 0.033203885 | BR15: 0.00098107728 | BS15: 0 | BT15: 0 | BU15: 0 | BV15: 0 | BW15: 0 | BX15: 0 | BY15: 0 | BZ15: 0.091781858 | CA15: 0 | CB15: 0 | CC15: 0 | CD15: 0.0022881983 | CE15: 0 | CF15: 0.061824005 | CG15: 0.028612761 | CH15: 2.0324421 | CI15: 0 | CJ15: 0.016089627 | CK15: 0.016980347 | CL15: 0 | CM15: 0 | CN15: 0 | CO15: 0 | CP15: 0.010408748 | CQ15: 0.0059894606 | CR15: 0 | CS15: 0 | CT15: 0 | CU15: 0 | CV15: 0 | CW15: 0 | CX15: 0 | CY15: 0 | CZ15: 182.98692 | DA15: 9563.933 | DB15: 0 | DC15: 0 | DD15: 0 | DE15: 0 | DF15: 0 | DG15: 0 | DH15: 0 | DI15: 0 | DJ15: 0 | DK15: 0 | DL15: 0 | DM15: 0 | DN15: 0 | DO15: 0 | DP15: 0 | DQ15: 0 | DR15: 0 | DS15: 10.408335 | DT15: 0 | DU15: 0 | DV15: 0 | DW15: 0 | DX15: 42.835078 | DY15: 7.7367676 | DZ15: 9664.8454 | EA15: 583.30906 | EB15: 0 | EC15: 68.449407 | ED15: 14.304797 | EE15: 0 | EF15: 253.18118 | EG15: 0.92582196 | EH15: 0 | EI15: 4.4700429 | EJ15: =SUM(D15:EI15) -> 249039.14
A16: 9 | B16: Code 9 | C16: Goods/ products industry 9 | D16: 359.67872 | E16: 373.1068 | F16: 172.86363 | G16: 0 | H16: 529.93476 | I16: 279.55288 | J16: 196.04259 | K16: 550.13437 | L16: 64.860199 | M16: 128.19567 | N16: 1207.3091 | O16: 0 | P16: 42.330027 | Q16: 607.09246 | R16: 37.171446 | S16: 0.76839425 | T16: 0 | U16: 126.53212 | V16: 292.32547 | W16: 2.0297863 | X16: 44.581921 | Y16: 147.30255 | Z16: 4.7280817 | AA16: 0.19324204 | AB16: 6.3769789 | AC16: 0.80328273 | AD16: 0 | AE16: 100.66339 | AF16: 8.8901988 | AG16: 5.3112988 | AH16: 83.259861 | AI16: 1211.575 | AJ16: 2.9829253 | AK16: 477.88916 | AL16: 19.610891 | AM16: 0.1800296 | AN16: 0 | AO16: 132.39386 | AP16: 243.25459 | AQ16: 382.94984 | AR16: 2032.3797 | AS16: 0.54733397 | AT16: 24.34049 | AU16: 8.8891182 | AV16: 23.80613 | AW16: 0.57194733 | AX16: 0.33882687 | AY16: 5.0311969 | AZ16: 164.35321 | BA16: 19.940495 | BB16: 126.23598 | BC16: 10.993295 | BD16: 15.89739 | BE16: 61.632723 | BF16: 3026.5086 | BG16: 280.70724 | BH16: 3600.408 | BI16: 305.32938 | BJ16: 131.39692 | BK16: 114.22417 | BL16: 2713.4595 | BM16: 79.316073 | BN16: 97.022152 | BO16: 1039.1728 | BP16: 19.894678 | BQ16: 1068.7134 | BR16: 355.48624 | BS16: 1.7143354 | BT16: 33.519202 | BU16: 0.059632365 | BV16: 10.949483 | BW16: 0.15847491 | BX16: 3.9475761 | BY16: 0.41554219 | BZ16: 11.862696 | CA16: 2.7124149 | CB16: 0.62648974 | CC16: 1.4890199 | CD16: 0.7176846 | CE16: 3.6250701 | CF16: 5.3466265 | CG16: 23.73398 | CH16: 44.374285 | CI16: 1.0097193 | CJ16: 6.0821963 | CK16: 306.0039 | CL16: 276587.9 | CM16: 1.2795083 | CN16: 1500.3565 | CO16: 0.064831961 | CP16: 4485.4725 | CQ16: 8.5038731 | CR16: 0.74729466 | CS16: 12.048909 | CT16: 0 | CU16: 34795.185 | CV16: 32017.423 | CW16: 13981.575 | CX16: 11585.287 | CY16: 39.881126 | CZ16: 100.77782 | DA16: 406.09632 | DB16: 0.0012377469 | DC16: 18.756651 | DD16: 0.78671948 | DE16: 0 | DF16: 52.591935 | DG16: 0 | DH16: 117.21386 | DI16: 0 | DJ16: 0 | DK16: 1486.3432 | DL16: 0 | DM16: 0 | DN16: 108.58343 | DO16: 11.374683 | DP16: 40.506822 | DQ16: 118.5069 | DR16: 5.2300588 | DS16: 39.165977 | DT16: 0 | DU16: 0 | DV16: 0 | DW16: 78.941009 | DX16: 0 | DY16: 38639.169 | DZ16: 145994.84 | EA16: 10409.68 | EB16: 465.22386 | EC16: 98.225711 | ED16: 173.62991 | EE16: 578.52724 | EF16: 878.35493 | EG16: 45.534544 | EH16: 0 | EI16: 67508.5 | EJ16: =SUM(D16:EI16) -> 666020.11
A17: 10 | B17: Code 10 | C17: Goods/ products industry 10 | D17: 0 | E17: 0 | F17: 0 | G17: 0 | H17: 0 | I17: 0 | J17: 0 | K17: 0.015564283 | L17: 0 | M17: 6133.6604 | N17: 59755.472 | O17: 0 | P17: 0 | Q17: 1724.1711 | R17: 5.3479483 | S17: 0.020994652 | T17: 0 | U17: 9.2810904 | V17: 0.14496156 | W17: 0.028331839 | X17: 0.18736141 | Y17: 4.9365009 | Z17: 0.0002449844 | AA17: 0 | AB17: 0.00013676643 | AC17: 3.3146482e-07 | AD17: 0 | AE17: 1814.7992 | AF17: 17.172213 | AG17: 0 | AH17: 52.435119 | AI17: 30.107119 | AJ17: 6.1108617 | AK17: 107.48463 | AL17: 44.1808 | AM17: 1.2301081e-05 | AN17: 46.889567 | AO17: 1706780.2 | AP17: 408.77097 | AQ17: 1.1427602 | AR17: 99089.01 | AS17: 0.00014824094 | AT17: 110.45759 | AU17: 9.3930692 | AV17: 11163.138 | AW17: 1348.371 | AX17: 0.0025077691 | AY17: 3.252607 | AZ17: 1347.3196 | BA17: 37.906384 | BB17: 49.312378 | BC17: 832.74934 | BD17: 8993.9978 | BE17: 32.57377 | BF17: 617.07614 | BG17: 183.36357 | BH17: 1187.2839 | BI17: 1286.6122 | BJ17: 22.711478 | BK17: 6815.2946 | BL17: 1.1991124 | BM17: 18.696686 | BN17: 2.6572525 | BO17: 112.07134 | BP17: 0 | BQ17: 23.05187 | BR17: 7.3641759 | BS17: 58.587199 | BT17: 3.2895527 | BU17: 9.2941937 | BV17: 0.0029923909 | BW17: 5.1234912 | BX17: 0 | BY17: 1.7078304 | BZ17: 3.4101908 | CA17: 0 | CB17: 0 | CC17: 0 | CD17: 0 | CE17: 0.60246805 | CF17: 0.13311555 | CG17: 3.5418149 | CH17: 371.39621 | CI17: 8.1769492 | CJ17: 0.037324207 | CK17: 105.98701 | CL17: 35168.804 | CM17: 1.0317125 | CN17: 0 | CO17: 0 | CP17: 497.56813 | CQ17: 16.581847 | CR17: 58.906728 | CS17: 439.39053 | CT17: 0 | CU17: 0 | CV17: 0 | CW17: 0 | CX17: 0 | CY17: 0 | CZ17: 0 | DA17: 0 | DB17: 0 | DC17: 0 | DD17: 0 | DE17: 0 | DF17: 0 | DG17: 0 | DH17: 0 | DI17: 0 | DJ17: 0 | DK17: 0 | DL17: 0 | DM17: 0 | DN17: 0 | DO17: 0 | DP17: 0 | DQ17: 0 | DR17: 0 | DS17: 0 | DT17: 0 | DU17: 0 | DV17: 0 | DW17: 0 | DX17: 0 | DY17: 0 | DZ17: 0 | EA17: 0 | EB17: 0 | EC17: 0 | ED17: 0 | EE17: 0 | EF17: 0 | EG17: 0 | EH17: 0 | EI17: 0 | EJ17: =SUM(D17:EI17) -> 1946991
A18: 11 | B18: Code 11 | C18: Goods/ products industry 11 | D18: 1937.6686 | E18: 26146.099 | F18: 682.36675 | G18: 116.96931 | H18: 30297.202 | I18: 16307.437 | J18: 3642.7111 | K18: 1482.2582 | L18: 543.17112 | M18: 148048.01 | N18: 689541.48 | O18: 0 | P18: 42114.2 | Q18: 12373.469 | R18: 3384.7807 | S18: 506.03869 | T18: 31.845308 | U18: 4785.7644 | V18: 4068.786 | W18: 2370.968 | X18: 2243.4689 | Y18: 76386.031 | Z18: 6847.3623 | AA18: 6494.9028 | AB18: 396.79326 | AC18: 2970.0757 | AD18: 414.41058 | AE18: 6887.6458 | AF18: 1929.4467 | AG18: 2410.8006 | AH18: 3403.7145 | AI18: 1870.1849 | AJ18: 589.12976 | AK18: 666.88503 | AL18: 2670.3912 | AM18: 25.880714 | AN18: 0.012186775 | AO18: 126948 | AP18: 21007.339 | AQ18: 59933.101 | AR18: 75698.219 | AS18: 258.10834 | AT18: 2786.0452 | AU18: 2280.0431 | AV18: 2289.4149 | AW18: 1163.9342 | AX18: 3819.3943 | AY18: 729.07592 | AZ18: 5892.1317 | BA18: 198.23402 | BB18: 1726.497 | BC18: 639.62026 | BD18: 9818.182 | BE18: 6399.0221 | BF18: 37858.175 | BG18: 6591.7334 | BH18: 231406.1 | BI18: 152352.68 | BJ18: 2310.3543 | BK18: 13133.823 | BL18: 9830.5155 | BM18: 1211.6479 | BN18: 1999.9945 | BO18: 456112.59 | BP18: 468.42818 | BQ18: 6571.5887 | BR18: 13778.975 | BS18: 1781.6312 | BT18: 595.81139 | BU18: 608.96765 | BV18: 7231.6309 | BW18: 887.1542 | BX18: 2792.6744 | BY18: 21.068336 | BZ18: 1283.6287 | CA18: 195.70322 | CB18: 106.15647 | CC18: 338.75353 | CD18: 18.452411 | CE18: 305.00684 | CF18: 1699.2387 | CG18: 2548.8999 | CH18: 1362.1756 | CI18: 347.75942 | CJ18: 529.66772 | CK18: 7147.224 | CL18: 1321664.6 | CM18: 9989.4403 | CN18: 231.57099 | CO18: 60243.967 | CP18: 290358.08 | CQ18: 4282.9793 | CR18: 2198.2237 | CS18: 2114.3741 | CT18: 20.610013 | CU18: 28280.21 | CV18: 449936.44 | CW18: 775824.07 | CX18: 13672.44 | CY18: 310.2378 | CZ18: 150.66509 | DA18: 5553.8975 | DB18: 283.40788 | DC18: 58.374715 | DD18: 327.42607 | DE18: 283.77497 | DF18: 227.15608 | DG18: 35.408916 | DH18: 2578.1031 | DI18: 738.55499 | DJ18: 126.16429 | DK18: 7798.1997 | DL18: 39.285833 | DM18: 17.793625 | DN18: 992.31326 | DO18: 2521.0228 | DP18: 33.594637 | DQ18: 35.550585 | DR18: 86.248216 | DS18: 16852.981 | DT18: 470.53732 | DU18: 38.590258 | DV18: 0 | DW18: 2468.547 | DX18: 190.73147 | DY18: 111018.35 | DZ18: 119518.7 | EA18: 22359.575 | EB18: 1764.6265 | EC18: 368.46043 | ED18: 492.971 | EE18: 1328.0963 | EF18: 3429.0412 | EG18: 1126.7665 | EH18: 570.69546 | EI18: 20554.846 | EJ18: =SUM(D18:EI18) -> 5673170.6
A19: 12 | B19: Code 12 | C19: Goods/ products industry 12 | D19: 0 | E19: 0 | F19: 0 | G19: 0 | H19: 0 | I19: 0 | J19: 0 | K19: 0 | L19: 0 | M19: 0 | N19: 0.0012302091 | O19: 0 | P19: 0.0089676994 | Q19: 4.2736362 | R19: 0 | S19: 8.9799989 | T19: 0 | U19: 0.0012271451 | V19: 0 | W19: 0.00034007068 | X19: 0 | Y19: 0.0024280026 | Z19: 0 | AA19: 0 | AB19: 0 | AC19: 0 | AD19: 0 | AE19: 1.364967 | AF19: 0 | AG19: 0 | AH19: 28.215092 | AI19: 0.10494888 | AJ19: 0.00033114381 | AK19: 5.0026794 | AL19: 0.019825265 | AM19: 0 | AN19: 0.039556313 | AO19: 1296.5716 | AP19: 66.683555 | AQ19: 0 | AR19: 0.1807653 | AS19: 0 | AT19: 0.00015337188 | AU19: 0 | AV19: 15.534182 | AW19: 0 | AX19: 0 | AY19: 0.079437923 | AZ19: 4.5519355 | BA19: 0.0007301451 | BB19: 5.8490332 | BC19: 0.10618054 | BD19: 0.059586134 | BE19: 0.0013770602 | BF19: 0.00092564519 | BG19: 0 | BH19: 0.77544299 | BI19: 42.414053 | BJ19: 0.92140619 | BK19: 616.11069 | BL19: 68729.762 | BM19: 1945.149 | BN19: 1205.1273 | BO19: 1916.5044 | BP19: 766.03815 | BQ19: 17655.074 | BR19: 1192.1348 | BS19: 4.2122961 | BT19: 0 | BU19: 0 | BV19: 0.12797613 | BW19: 0.0047935785 | BX19: 1.4130036 | BY19: 0 | BZ19: 4.5215993 | CA19: 0.025355818 | CB19: 0.51895908 | CC19: 0.0017892819 | CD19: 0 | CE19: 0.035017166 | CF19: 0.00026737377 | CG19: 0.066217173 | CH19: 0.72588091 | CI19: 0 | CJ19: 0.00029716056 | CK19: 8.6603491 | CL19: 0 | CM19: 0 | CN19: 0 | CO19: 0 | CP19: 0.0077609555 | CQ19: 0.020152187 | CR19: 0.044823281 | CS19: 151.87938 | CT19: 0 | CU19: 0 | CV19: 0 | CW19: 0 | CX19: 0 | CY19: 0 | CZ19: 0 | DA19: 0 | DB19: 0 | DC19: 0 | DD19: 0 | DE19: 0 | DF19: 0 | DG19: 0 | DH19: 0 | DI19: 0 | DJ19: 0 | DK19: 0 | DL19: 0 | DM19: 0 | DN19: 0 | DO19: 0 | DP19: 0 | DQ19: 0 | DR19: 0 | DS19: 0 | DT19: 0 | DU19: 0 | DV19: 0 | DW19: 0 | DX19: 0 | DY19: 0 | DZ19: 0 | EA19: 0 | EB19: 0 | EC19: 0 | ED19: 0 | EE19: 0 | EF19: 0 | EG19: 0 | EH19: 0 | EI19: 0 | EJ19: =SUM(D19:EI19) -> 95679.912
A20: 13 | B20: Code 13 | C20: Goods/ products industry 13 | D20: 0 | E20: 0 | F20: 0 | G20: 0 | H20: 0 | I20: 0 | J20: 0 | K20: 1.2001758e-05 | L20: 0 | M20: 0 | N20: 0.018286594 | O20: 51.010589 | P20: 65643.179 | Q20: 163.16188 | R20: 0.004123851 | S20: 0.030648651 | T20: 0 | U20: 0.02686908 | V20: 0.0041025469 | W20: 22.31183 | X20: 0.10101414 | Y20: 0.20558939 | Z20: 2.0963591e-05 | AA20: 0 | AB20: 0.010804756 | AC20: 0.0024986102 | AD20: 0 | AE20: 0.00034186558 | AF20: 0.12909721 | AG20: 0 | AH20: 7.0446255 | AI20: 1.4819948 | AJ20: 94.07767 | AK20: 0.60593004 | AL20: 0.34235194 | AM20: 0.065252563 | AN20: 0 | AO20: 0.0019303951 | AP20: 3192.4762 | AQ20: 0.20673455 | AR20: 3.1669018 | AS20: 0.002376158 | AT20: 0.063284163 | AU20: 0.00016227223 | AV20: 193.37501 | AW20: 0.020573546 | AX20: 0.0010525989 | AY20: 2.6984105 | AZ20: 127.49288 | BA20: 6.7126626 | BB20: 693.6913 | BC20: 2.4479434 | BD20: 1.0080202 | BE20: 24.927843 | BF20: 16.687604 | BG20: 3.2171548 | BH20: 5057.9967 | BI20: 3.9838661 | BJ20: 1.8494037 | BK20: 40.285153 | BL20: 214.69324 | BM20: 76.063043 | BN20: 1732.2364 | BO20: 3687588.4 | BP20: 530.95644 | BQ20: 5650.0563 | BR20: 433.63202 | BS20: 0.077955976 | BT20: 16.269455 | BU20: 0 | BV20: 40534.046 | BW20: 0.090723483 | BX20: 22.03754 | BY20: 0.00041742626 | BZ20: 2942.6784 | CA20: 1.2180446 | CB20: 0.32550901 | CC20: 0.57908509 | CD20: 0.17718153 | CE20: 5.5993577 | CF20: 4.8226402 | CG20: 306.51473 | CH20: 2.561977 | CI20: 0.49255853 | CJ20: 0.0050266055 | CK20: 10.113445 | CL20: 0.0074337427 | CM20: 0 | CN20: 0 | CO20: 0 | CP20: 272.20561 | CQ20: 2419.0693 | CR20: 28.288915 | CS20: 20.657414 | CT20: 0 | CU20: 0 | CV20: 0 | CW20: 0 | CX20: 0 | CY20: 0 | CZ20: 0 | DA20: 0 | DB20: 0 | DC20: 0 | DD20: 0 | DE20: 0 | DF20: 0 | DG20: 0 | DH20: 0 | DI20: 0 | DJ20: 0 | DK20: 0 | DL20: 0 | DM20: 0 | DN20: 0 | DO20: 0 | DP20: 0 | DQ20: 0 | DR20: 0 | DS20: 0 | DT20: 0 | DU20: 0 | DV20: 0 | DW20: 0 | DX20: 0 | DY20: 0 | DZ20: 0 | EA20: 0 | EB20: 0 | EC20: 0 | ED20: 0 | EE20: 0 | EF20: 0 | EG20: 0 | EH20: 0 | EI20: 0 | EJ20: =SUM(D20:EI20) -> 3818170
... A143: 136 | B143: Code 136 | C143: Goods/ products industry 136 | D143: 5.5399854 | E143: 0 | F143: 0.78328681 | G143: 0 | H143: 0 | I143: 0 | J143: 0 | K143: 0 | L143: 0 | M143: 0 | N143: 0 | O143: 0 | P143: 0.039556822 | Q143: 0.99989839 | R143: 0.015072741 | S143: 0.51725964 | T143: 0 | U143: 0.090532435 | V143: 0.61361399 | W143: 0.015077254 | X143: 0.017771648 | Y143: 0.31313221 | Z143: 0.0081299883 | AA143: 0 | AB143: 0 | AC143: 0.026470983 | AD143: 0 | AE143: 71.371594 | AF143: 53.264432 | AG143: 2.0378726 | AH143: 1291.7383 | AI143: 160.28572 | AJ143: 3.3803836 | AK143: 0.18736651 | AL143: 3.8917709 | AM143: 3.1401963 | AN143: 0 | AO143: 0.025943324 | AP143: 0.67776241 | AQ143: 0.00015277381 | AR143: 0.1540741 | AS143: 0 | AT143: 0.46387926 | AU143: 0.084064638 | AV143: 1.2286628 | AW143: 9.1299872 | AX143: 0.14273349 | AY143: 12.121448 | AZ143: 10.022052 | BA143: 1.2859787 | BB143: 1.3926634 | BC143: 5.1569842 | BD143: 0.60868751 | BE143: 0.34696616 | BF143: 0.093916309 | BG143: 0.013683802 | BH143: 0.0021827145 | BI143: 0.60673428 | BJ143: 0.20855848 | BK143: 0.072375633 | BL143: 1.7530795e-05 | BM143: 1.8480011 | BN143: 0.020097273 | BO143: 0.70384379 | BP143: 0.058599022 | BQ143: 3.8879876 | BR143: 8.8438877 | BS143: 0.26488171 | BT143: 0.069933887 | BU143: 0 | BV143: 0 | BW143: 0.041259969 | BX143: 0.029486421 | BY143: 0.53868183 | BZ143: 3.867186 | CA143: 9.9471443 | CB143: 2.5698734 | CC143: 1.3655894 | CD143: 0.0046709535 | CE143: 2716.2956 | CF143: 4.0161911 | CG143: 5.5519085 | CH143: 174.90321 | CI143: 0.0043902769 | CJ143: 5.79603 | CK143: 2.4568353 | CL143: 1529.2983 | CM143: 0 | CN143: 0 | CO143: 0.00015474459 | CP143: 18.304221 | CQ143: 0 | CR143: 0 | CS143: 0.91043894 | CT143: 0 | CU143: 0 | CV143: 6.1882227 | CW143: 0 | CX143: 0 | CY143: 0 | CZ143: 0 | DA143: 0 | DB143: 0 | DC143: 0 | DD143: 0 | DE143: 0 | DF143: 0 | DG143: 0 | DH143: 0 | DI143: 0 | DJ143: 0 | DK143: 0 | DL143: 0 | DM143: 0 | DN143: 0 | DO143: 33.357993 | DP143: 0 | DQ143: 0 | DR143: 0 | DS143: 0 | DT143: 0 | DU143: 0 | DV143: 0 | DW143: 0 | DX143: 2853.442 | DY143: 8905.4449 | DZ143: 2035.3598 | EA143: 891.10557 | EB143: 0 | EC143: 80.65188 | ED143: 83.764532 | EE143: 19.767349 | EF143: 134.18378 | EG143: 0.19547928 | EH143: 0 | EI143: 0 | EJ143: =SUM(D143:EI143) -> 21177.177
C144: Прямые покупки за рубежом, совершаемые резидентами | EJ144: =SUM(D144:EI144) -> 0
C145: Прмежуточное потребление | D145: =SUM(D8:D144) -> 4014939.8 | E145: =SUM(E8:E144) -> 7926897 | F145: =SUM(F8:F144) -> 3061342.9 | G145: =SUM(G8:G144) -> 1619400.6 | H145: =SUM(H8:H144) -> 21264394 | I145: =SUM(I8:I144) -> 6915349.8 | J145: =SUM(J8:J144) -> 802181.09 | K145: =SUM(K8:K144) -> 398353.09 | ... EJ145: =SUM(EJ8:EJ144) -> 1.9865524e+08
B146: Transferred from the next first pass tab | C146: Intermediate consumption after first iteration of primary eff | D146: ='primary effect'!EJ137 -> 12054912 | E146: ='primary effect'!EK137 -> 23798013 | F146: ='primary effect'!EL137 -> 9192745.6 | G146: ='primary effect'!EM137 -> 4861781.7 | H146: ='primary effect'!EN137 -> 63841658 | I146: ='primary effect'!EO137 -> 20765224 | J146: ='primary effect'!EP137 -> 2408918.9 | K146: ='primary effect'!EQ137 -> 1196335.3 | ... EI146: ='primary effect'!JO137 -> 2884294.2
C147: Intermediate consumption after second iteration | D147: ='secondary effect'!EJ137 -> 13466232 | E147: ='secondary effect'!EK137 -> 26274388 | F147: ='secondary effect'!EL137 -> 10356950 | G147: ='secondary effect'!EM137 -> 5382700.2 | H147: ='secondary effect'!EN137 -> 71057548 | I147: ='secondary effect'!EO137 -> 23170092 | J147: ='secondary effect'!EP137 -> 2608157 | K147: ='secondary effect'!EQ137 -> 1338955.2 | ... EI147: ='secondary effect'!JO137 -> 3187379.9
C148: Intermediate consumption after third iteration | D148: ='tertiary effect'!EJ137 -> 13722108 | E148: ='tertiary effect'!EK137 -> 26685932 | F148: ='tertiary effect'!EL137 -> 10566993 | G148: ='tertiary effect'!EM137 -> 5473445.2 | H148: ='tertiary effect'!EN137 -> 72344727 | I148: ='tertiary effect'!EO137 -> 23605446 | J148: ='tertiary effect'!EP137 -> 2637710.8 | K148: ='tertiary effect'!EQ137 -> 1365417.3 | ... EI148: ='tertiary effect'!JO137 -> 3246181.9
C149: Intermediate consumption after fourth iteration | D149: ='quadruple effect'!EJ137 -> 13769630 | E149: ='quadruple effect'!EK137 -> 26758483 | F149: ='quadruple effect'!EL137 -> 10605933 | G149: ='quadruple effect'!EM137 -> 5490016.5 | H149: ='quadruple effect'!EN137 -> 72582369 | I149: ='quadruple effect'!EO137 -> 23687740 | J149: ='quadruple effect'!EP137 -> 2642736.8 | K149: ='quadruple effect'!EQ137 -> 1370477.7 | ... EI149: ='quadruple effect'!JO137 -> 3257679.9
C150: Intermediate consumption after fifth iteration | D150: ='quintuple effect'!EJ137 -> 13778679 | E150: ='quintuple effect'!EK137 -> 26771959 | F150: ='quintuple effect'!EL137 -> 10613388 | G150: ='quintuple effect'!EM137 -> 5493159 | H150: ='quintuple effect'!EN137 -> 72627703 | I150: ='quintuple effect'!EO137 -> 23703984 | J150: ='quintuple effect'!EP137 -> 2643676 | K150: ='quintuple effect'!EQ137 -> 1371476.5 | ... EI150: ='quintuple effect'!JO137 -> 3259952.1
C151: change in intermediate consumption after first iteration | D151: =D146-D145 -> 8039971.9 | E151: =E146-E145 -> 15871116 | F151: =F146-F145 -> 6131402.7 | G151: =G146-G145 -> 3242381.1 | H151: =H146-H145 -> 42577263 | I151: =I146-I145 -> 13849875 | J151: =J146-J145 -> 1606737.8 | K151: =K146-K145 -> 797982.26 | ... EI151: =EI146-EI145 -> 1924672.3
C152: change in intermediate consumption after second iteration | D152: =D147-D146 -> 1411320.4 | E152: =E147-E146 -> 2476374.6 | F152: =F147-F146 -> 1164204.2 | G152: =G147-G146 -> 520918.46 | H152: =H147-H146 -> 7215890.4 | I152: =I147-I146 -> 2404867.2 | J152: =J147-J146 -> 199238.11 | K152: =K147-K146 -> 142619.89 | ... EI152: =EI147-EI146 -> 303085.71
C153: change in intermediate consumption after third iteration | D153: =D148-D147 -> 255875.88 | E153: =E148-E147 -> 411544.9 | F153: =F148-F147 -> 210042.65 | G153: =G148-G147 -> 90745.067 | H153: =H148-H147 -> 1287179.2 | I153: =I148-I147 -> 435354.23 | J153: =J148-J147 -> 29553.804 | K153: =K148-K147 -> 26462.113 | ... EI153: =EI148-EI147 -> 58802.082
C154: change in intermediate consumption after fourth iteration | D154: =D149-D148 -> 47521.788 | E154: =E149-E148 -> 72550.834 | F154: =F149-F148 -> 38940.696 | G154: =G149-G148 -> 16571.269 | H154: =H149-H148 -> 237641.38 | I154: =I149-I148 -> 82294.41 | J154: =J149-J148 -> 5025.9468 | K154: =K149-K148 -> 5060.3674 | ... EI154: =EI149-EI148 -> 11497.922
C155: change in intermediate consumption after fifth iteration | D155: =D150-D149 -> 9049.4629 | E155: =E150-E149 -> 13476.029 | F155: =F150-F149 -> 7454.7728 | G155: =G150-G149 -> 3142.5017 | H155: =H150-H149 -> 45334.886 | I155: =I150-I149 -> 16244.11 | J155: =J150-J149 -> 939.22142 | K155: =K150-K149 -> 998.73782 | ... EI155: =EI150-EI149 -> 2272.2712
C156: Чистые налоги на продукты | D156: 283099.6 | E156: 245163.71 | F156: 397058.56 | G156: 46952.291 | H156: 1058545 | I156: -549060.32 | J156: 43489.037 | K156: 28892.907 | L156: 38662.928 | M156: 161062.1 | N156: 821428.69 | O156: 21.871516 | P156: 296630.11 | Q156: 84481.304 | R156: 47672.149 | S156: 95323.462 | T156: 11881.088 | U156: 203597.75 | V156: 178954.99 | W156: 48565.802 | X156: 505783.37 | Y156: 222787.95 | Z156: 127953.49 | AA156: 78985.035 | AB156: 139001 | AC156: 446900.29 | AD156: 154874.02 | AE156: 787808.86 | AF156: 151963.53 | AG156: 21632.497 | AH156: 563600.59 | AI156: 387906.59 | AJ156: 90027.312 | AK156: 74615.588 | AL156: 154930.71 | AM156: 85349.564 | AN156: 25.144232 | AO156: 1089661 | AP156: 141823.76 | AQ156: 493450.37 | AR156: 440714.63 | AS156: 11763.731 | AT156: 48799.29 | AU156: 79042.914 | AV156: 44862.721 | AW156: 20615.5 | AX156: 61556.076 | AY156: 28835.492 | AZ156: 280744.28 | BA156: 148450.84 | BB156: 82649.014 | BC156: 41486.157 | BD156: 82752.508 | BE156: 16440.023 | BF156: 92313.633 | BG156: 10493.164 | BH156: 319579.96 | BI156: 315511.02 | BJ156: 10239.543 | BK156: 45035.896 | BL156: 313092.1 | BM156: 127412.68 | BN156: 72232.488 | BO156: 1867432.2 | BP156: 5329.8848 | BQ156: 263962.5 | BR156: 290357.39 | BS156: 306189.57 | BT156: 164674.82 | BU156: 8448.131 | BV156: 124680.99 | BW156: 63230.243 | BX156: 174439.06 | BY156: 44454.488 | BZ156: 172004.67 | CA156: 27594.569 | CB156: 15162.272 | CC156: 43136.69 | CD156: 859.15961 | CE156: 2749896.1 | CF156: 47539.202 | CG156: 170281.64 | CH156: 80582.276 | CI156: 8320.7397 | CJ156: 14682.573 | CK156: 97389.362 | CL156: 1305193.8 | CM156: 11095.786 | CN156: 1829.6208 | CO156: 84221.532 | CP156: 8658.0939 | CQ156: 32654.508 | CR156: 9136.4171 | CS156: 40896.668 | CT156: 64.78599 | CU156: 3430603 | CV156: 1492308.2 | CW156: 2548562 | CX156: 101830.46 | CY156: 10202.736 | CZ156: 37152.141 | DA156: 118457.08 | DB156: 9236.4535 | DC156: 3566.1583 | DD156: 25430.363 | DE156: 328298.93 | DF156: 39701.126 | DG156: 15587.788 | DH156: 207251.79 | DI156: 12879.187 | DJ156: 12221.777 | DK156: 323389.68 | DL156: 5459.8927 | DM156: 22143.64 | DN156: 76666.454 | DO156: 20149.132 | DP156: 59195.199 | DQ156: 7361.7521 | DR156: 1162.1448 | DS156: 106607.5 | DT156: 4154.6147 | DU156: -30206.449 | DV156: 18026.618 | DW156: 31981.182 | DX156: 34846.553 | DY156: -145662.29 | DZ156: -979834.31 | EA156: 183818.67 | EB156: 8311.6798 | EC156: 3522.5287 | ED156: 2667.5542 | EE156: 6225.4398 | EF156: 58128.812 | EG156: 44046.002 | EH156: 129967.06 | EI156: 130263.51 | EJ156: =SUM(D156:EI156) -> 28706209 | EK156: 15075914 | EL156: 0 | EM156: 0 | EN156: 0 | EO156: 7440489.3 | EP156: 770193.95 | EQ156: 0 | ER156: =SUM(EK156:EQ156) -> 23286597 | ES156: =EJ156+ER156 -> 51992806
C157: Прмежуточное потребление в ценах покупателей (original intermediate cdonsumption) | D157: =D145+D156 -> 4298039.4 | E157: =E145+E156 -> 8172060.7 | F157: =F145+F156 -> 3458401.5 | G157: =G145+G156 -> 1666352.9 | H157: =H145+H156 -> 22322939 | I157: =I145+I156 -> 6366289.4 | J157: =J145+J156 -> 845670.12 | K157: =K145+K156 -> 427246 | ... EI157: =EI145+EI156 -> 1089885.3 | EJ157: =SUM(D157:EI157) -> 2.2736145e+08 | EK157: =SUM(EK145:EK156) -> 15075914 | EL157: =SUM(EL145:EL156) -> 0 | EM157: =SUM(EM145:EM156) -> 0 | EN157: =SUM(EN145:EN156) -> 0 | EO157: =SUM(EO145:EO156) -> 7440489.3 | EP157: =SUM(EP145:EP156) -> 770193.95 | EQ157: =SUM(EQ145:EQ156) -> 0 | ER157: =SUM(ER145:ER156) -> 23286597 | ES157: =SUM(ES145:ES156) -> 51992806
C158: Оплата труда работников | D158: 1043801.6 | E158: 2019480.7 | F158: 815315.64 | G158: 412300.18 | H158: 5451078.2 | I158: 1697266.9 | J158: 206646.84 | K158: 127528.47 | L158: 342688.57 | M158: 626364.27 | N158: 2683838.5 | O158: 108.81919 | P158: 839722.19 | Q158: 276535.55 | R158: 246142.06 | S158: 439937.12 | T158: 15778.455 | U158: 266383.38 | V158: 377883.57 | W158: 243804.14 | X158: 628041.07 | Y158: 340563.64 | Z158: 124619.96 | AA158: 217792.37 | AB158: 154170.59 | AC158: 723082.06 | AD158: 137136.09 | AE158: 2147026.7 | AF158: 190393.1 | AG158: 28706.217 | AH158: 727658.8 | AI158: 1316759.9 | AJ158: 154921.99 | AK158: 119806.83 | AL158: 261439.79 | AM158: 278827.13 | AN158: 18.615913 | AO158: 786446.63 | AP158: 241112.39 | AQ158: 562082.53 | AR158: 511171.56 | AS158: 12576.958 | AT158: 93271.082 | AU158: 79326.497 | AV158: 64705.36 | AW158: 33665.883 | AX158: 275827.18 | AY158: 34675.241 | AZ158: 341674.89 | BA158: 145973.43 | BB158: 98700.615 | BC158: 49004.333 | BD158: 194995.05 | BE158: 38512.212 | BF158: 212681.49 | BG158: 26648.546 | BH158: 726434.88 | BI158: 746500.88 | BJ158: 41515.556 | BK158: 184248.87 | BL158: 969798.26 | BM158: 338484.78 | BN158: 210127.17 | BO158: 7406081.5 | BP158: 17114.005 | BQ158: 576890.21 | BR158: 527635.98 | BS158: 352417.33 | BT158: 205344.05 | BU158: 22133.657 | BV158: 224021.37 | BW158: 91559.38 | BX158: 251595.67 | BY158: 53386.707 | BZ158: 312849.41 | CA158: 35200.784 | CB158: 22622.904 | CC158: 83330.453 | CD158: 4373.6193 | CE158: 2039707.9 | CF158: 202162.4 | CG158: 285496.61 | CH158: 125024.18 | CI158: 13024.614 | CJ158: 29641.738 | CK158: 542045.09 | CL158: 2599986.5 | CM158: 32335.111 | CN158: 8081.6366 | CO158: 248517.26 | CP158: 1101176.3 | CQ158: 594645.31 | CR158: 176685.8 | CS158: 205440.16 | CT158: 1222.419 | CU158: 11050532 | CV158: 11585624 | CW158: 5196986 | CX158: 1663642.6 | CY158: 204170.55 | CZ158: 316437.94 | DA158: 966477.79 | DB158: 302965.01 | DC158: 58228.647 | DD158: 322167.89 | DE158: 1964673.9 | DF158: 633858.3 | DG158: 400036.24 | DH158: 6647148.7 | DI158: 605549.07 | DJ158: 199958.27 | DK158: 1085606.7 | DL158: 453735.24 | DM158: 95031.804 | DN158: 3276691.4 | DO158: 633649.65 | DP158: 171411.54 | DQ158: 139246.65 | DR158: 207250.36 | DS158: 136456.29 | DT158: 192780.58 | DU158: 78820.101 | DV158: 2981.7379 | DW158: 2290195.2 | DX158: 416216.65 | DY158: 28547130 | DZ158: 36040459 | EA158: 16045132 | EB158: 555698.51 | EC158: 337326.58 | ED158: 371588.05 | EE158: 406125.61 | EF158: 1227590.1 | EG158: 749420.55 | EH158: 198005.41 | EI158: 164216.6 | EJ158: =SUM(D158:EI158) -> 1.870367e+08 | EK158: 1.870367e+08 | EL158: =EK158-EJ158 -> -0.022736192
C159: заработная плата | D159: 910567.44 | E159: 1752913 | F159: 709983.77 | G159: 357877.32 | H159: 4731546.1 | I159: 1473508.5 | J159: 155510.43 | K159: 113507.1 | L159: 289757.14 | M159: 550868.01 | N159: 2358411.2 | O159: 98.500243 | P159: 760083.55 | Q159: 244832.18 | R159: 215822.89 | S159: 396443.56 | T159: 14218.717 | U159: 240023.75 | V159: 339338.98 | W159: 219704.51 | X159: 565814.75 | Y159: 306842.59 | Z159: 112235.18 | AA159: 196263.06 | AB159: 138891.85 | AC159: 654250.26 | AD159: 121070.77 | AE159: 1898078.5 | AF159: 168381.93 | AG159: 25510.092 | AH159: 644821.61 | AI159: 1197608.2 | AJ159: 141484.9 | AK159: 106855.45 | AL159: 232271.43 | AM159: 244108.67 | AN159: 16.076022 | AO159: 681441.82 | AP159: 210860.4 | AQ159: 487480.36 | AR159: 443405.61 | AS159: 10944.582 | AT159: 80909.119 | AU159: 69202.754 | AV159: 56357.091 | AW159: 29401.7 | AX159: 243328.42 | AY159: 30379.277 | AZ159: 299842.2 | BA159: 127609.21 | BB159: 86379.169 | BC159: 42845.857 | BD159: 170329.27 | BE159: 33650.751 | BF159: 185865.61 | BG159: 23277.546 | BH159: 636654.31 | BI159: 652226.23 | BJ159: 36355.681 | BK159: 160939.48 | BL159: 839656.48 | BM159: 293066.34 | BN159: 182680.3 | BO159: 6416386.2 | BP159: 14825.387 | BQ159: 505216.38 | BR159: 466269.72 | BS159: 297603.18 | BT159: 177948.05 | BU159: 19142.912 | BV159: 193778.27 | BW159: 78899.551 | BX159: 216318.8 | BY159: 46172.324 | BZ159: 263015.29 | CA159: 29740.559 | CB159: 19069.756 | CC159: 69801.785 | CD159: 3749.2708 | CE159: 1731602.3 | CF159: 176727.43 | CG159: 258077.38 | CH159: 114462.94 | CI159: 11810.122 | CJ159: 27162.563 | CK159: 477621.82 | CL159: 2272384.8 | CM159: 28261.008 | CN159: 7063.3416 | CO159: 217204.78 | CP159: 962459.29 | CQ159: 524386.12 | CR159: 155782.5 | CS159: 182914.44 | CT159: 1092.0179 | CU159: 10019165 | CV159: 10685081 | CW159: 4508889.2 | CX159: 1447024.3 | CY159: 183249.23 | CZ159: 295799.89 | DA159: 861975.87 | DB159: 280380.62 | DC159: 48605.525 | DD159: 278655.23 | DE159: 1681623.1 | DF159: 596476.83 | DG159: 361934.55 | DH159: 5811930.4 | DI159: 541919.25 | DJ159: 174910.17 | DK159: 896381.95 | DL159: 361666.27 | DM159: 74357.11 | DN159: 2662758.6 | DO159: 496136.05 | DP159: 151941.86 | DQ159: 126600.65 | DR159: 163520.64 | DS159: 114693.13 | DT159: 168722.61 | DU159: 71109.148 | DV159: 2259.319 | DW159: 1851740.1 | DX159: 360203.18 | DY159: 22836973 | DZ159: 28884011 | EA159: 12739254 | EB159: 438467.35 | EC159: 230288.81 | ED159: 296535.2 | EE159: 340453.25 | EF159: 1069161.6 | EG159: 661332.98 | EH159: 171487.04 | EI159: 133060.58 | EJ159: =SUM(D159:EI159) -> 1.577523e+08 | EK159: 1.577523e+08 | EL159: =EK159-EJ159 -> -0.019889295
C160: отчисления на социальное страхование 0 (social security contributions) | D160: 133234.2 | E160: 266567.69 | F160: 105331.87 | G160: 54422.855 | H160: 719532.17 | I160: 223758.4 | J160: 51136.409 | K160: 14021.374 | L160: 52931.423 | M160: 75496.256 | N160: 325427.39 | O160: 10.318944 | P160: 79638.635 | Q160: 31703.364 | R160: 30319.165 | S160: 43493.56 | T160: 1559.7375 | U160: 26359.626 | V160: 38544.589 | W160: 24099.632 | X160: 62226.318 | Y160: 33721.047 | Z160: 12384.777 | AA160: 21529.312 | AB160: 15278.74 | AC160: 68831.795 | AD160: 16065.318 | AE160: 248948.16 | AF160: 22011.175 | AG160: 3196.1251 | AH160: 82837.193 | AI160: 119151.69 | AJ160: 13437.087 | AK160: 12951.389 | AL160: 29168.358 | AM160: 34718.458 | AN160: 2.539891 | AO160: 105004.82 | AP160: 30251.992 | AQ160: 74602.167 | AR160: 67765.958 | AS160: 1632.3763 | AT160: 12361.963 | AU160: 10123.743 | AV160: 8348.2689 | AW160: 4264.1829 | AX160: 32498.762 | AY160: 4295.9642 | AZ160: 41832.696 | BA160: 18364.22 | BB160: 12321.446 | BC160: 6158.4759 | BD160: 24665.772 | BE160: 4861.4614 | BF160: 26815.874 | BG160: 3371.0005 | BH160: 89780.574 | BI160: 94274.645 | BJ160: 5159.8744 | BK160: 23309.383 | BL160: 130141.78 | BM160: 45418.431 | BN160: 27446.87 | BO160: 989695.25 | BP160: 2288.6171 | BQ160: 71673.832 | BR160: 61366.261 | BS160: 54814.15 | BT160: 27396.001 | BU160: 2990.7457 | BV160: 30243.109 | BW160: 12659.829 | BX160: 35276.877 | BY160: 7214.3825 | BZ160: 49834.129 | CA160: 5460.2255 | CB160: 3553.1487 | CC160: 13528.668 | CD160: 624.34849 | CE160: 308105.61 | CF160: 25434.977 | CG160: 27419.227 | CH160: 10561.234 | CI160: 1214.4915 | CJ160: 2479.1752 | CK160: 64423.261 | CL160: 327601.71 | CM160: 4074.103 | CN160: 1018.295 | CO160: 31312.48 | CP160: 138717.01 | CQ160: 70259.183 | CR160: 20903.301 | CS160: 22525.712 | CT160: 130.40109 | CU160: 1031367 | CV160: 900543.16 | CW160: 688096.79 | CX160: 216618.34 | CY160: 20921.316 | CZ160: 20638.05 | DA160: 104501.91 | DB160: 22584.391 | DC160: 9623.1218 | DD160: 43512.653 | DE160: 283050.78 | DF160: 37381.469 | DG160: 38101.688 | DH160: 835218.36 | DI160: 63629.815 | DJ160: 25048.101 | DK160: 189224.72 | DL160: 92068.967 | DM160: 20674.694 | DN160: 613932.85 | DO160: 137513.6 | DP160: 19469.678 | DQ160: 12646.004 | DR160: 43729.721 | DS160: 21763.161 | DT160: 24057.974 | DU160: 7710.9526 | DV160: 722.41889 | DW160: 438455.1 | DX160: 56013.467 | DY160: 5710156.9 | DZ160: 7156447.9 | EA160: 3305877.8 | EB160: 117231.16 | EC160: 107037.77 | ED160: 75052.855 | EE160: 65672.361 | EF160: 158428.47 | EG160: 88087.569 | EH160: 26518.362 | EI160: 31156.022 | EJ160: =SUM(D160:EI160) -> 29284408 | EK160: 29284408 | EL160: =EK160-EJ160 -> -0.0028468147
B161: 1.35 | C161: отчисления на социальное страхование 1 | D161: =D160*$B$161 -> 179866.16 | E161: =E160*$B$161 -> 359866.38 | F161: =F160*$B$161 -> 142198.02 | G161: =G160*$B$161 -> 73470.854 | H161: =H160*$B$161 -> 971368.43 | I161: =I160*$B$161 -> 302073.84 | J161: =J160*$B$161 -> 69034.152 | K161: =K160*$B$161 -> 18928.856 | ... EI161: =EI160*$B$161 -> 42060.63
C162: Другие налоги на производство | D162: 155183.64 | E162: 345514.9 | F162: 126741.85 | G162: 70540.835 | H162: 932630.24 | I162: 289504.63 | J162: 49700.561 | K162: 39881.552 | L162: 5876.9667 | M162: 29443.401 | N162: 131358.31 | O162: 6.9460965 | P162: 53599.16 | Q162: 14984.847 | R162: 7536.5495 | S162: 29875.374 | T162: 1071.6473 | U162: 18084.735 | V162: 26112.293 | W162: 16549.341 | X162: 42606.775 | Y162: 23008.724 | Z162: 8469.2306 | AA162: 14792.014 | AB162: 10482.735 | AC162: 51843.027 | AD162: 10646.187 | AE162: 161460.44 | AF162: 14188.463 | AG162: 1966.8089 | AH162: 52214.818 | AI162: 49713.613 | AJ162: 8260.6625 | AK162: 9081.1147 | AL162: 15573.127 | AM162: 7881.7892 | AN162: 2.171227 | AO162: 79977.964 | AP162: 17765.239 | AQ162: 43925.877 | AR162: 39808.647 | AS162: 968.56009 | AT162: 6915.3088 | AU162: 6053.6836 | AV162: 4429.2578 | AW162: 2592.8946 | AX162: 19370.592 | AY162: 2772.6626 | AZ162: 25923.924 | BA162: 12556.886 | BB162: 7819.2571 | BC162: 3919.3712 | BD162: 9564.77 | BE162: 1886.5872 | BF162: 10368.596 | BG162: 1317.755 | BH162: 36439.774 | BI162: 36585.129 | BJ162: 2054.6683 | BK162: 9035.3161 | BL162: 54600.363 | BM162: 19407.291 | BN162: 11883.396 | BO162: 412896.39 | BP162: 961.61644 | BQ162: 31330.372 | BR162: 28474.389 | BS162: 26755.358 | BT162: 13818.099 | BU162: 1569.7941 | BV162: 14537.573 | BW162: 6256.7122 | BX162: 18027.077 | BY162: 3740.0952 | BZ162: 16390.17 | CA162: 2007.4295 | CB162: 1364.7245 | CC162: 4229.3406 | CD162: 163.04911 | CE162: 162782.58 | CF162: 5270.8698 | CG162: 13136.465 | CH162: 4681.915 | CI162: 484.792 | CJ162: 1159.5535 | CK162: 11497.669 | CL162: 91252.645 | CM162: 1136.6425 | CN162: 283.5792 | CO162: 8718.5498 | CP162: 39169.516 | CQ162: 6978.3277 | CR162: 2074.0355 | CS162: 5014.1829 | CT162: 12.280053 | CU162: 442705.11 | CV162: 185593.26 | CW162: 160554.34 | CX162: 25240.838 | CY162: 2232.7904 | CZ162: 6182.4331 | DA162: 30720.173 | DB162: 4338.3091 | DC162: 880.72512 | DD162: 3614.5412 | DE162: 62033.805 | DF162: 13770.752 | DG162: 7056.105 | DH162: 93754.202 | DI162: 8981.1059 | DJ162: 2708.2487 | DK162: 1986778 | DL162: 4533.1179 | DM162: 4128.5044 | DN162: 32385.195 | DO162: 1207.5796 | DP162: 7374.455 | DQ162: 3137.6901 | DR162: 331.39293 | DS162: 9149.6673 | DT162: 1685.4263 | DU162: 1641.0766 | DV162: 6461.6542 | DW162: 3193.0839 | DX162: 9476.7426 | DY162: 213.58266 | DZ162: 54343.076 | EA162: 24504.686 | EB162: 13.901481 | EC162: 2.0908371 | ED162: 424.0602 | EE162: 324.1708 | EF162: 2597.896 | EG162: 783.66389 | EH162: 3439.2382 | EI162: 2071.9053 | EJ162: =SUM(D162:EI162) -> 7441077.7 | EK162: 7441077.7 | EL162: =EK162-EJ162 -> -0.0012614671
C163: Валовая прибыль и валовой смешанный доход (gross profit and mixed income) | D163: 12590261 | E163: 29656283 | F163: 10475555 | G163: 6054670.7 | H163: 80049647 | I163: 24832493 | J163: 4833192.7 | K163: 1181669.1 | L163: 284204.29 | M163: 3160997.8 | N163: 13527018 | O163: 694.25376 | P163: 5356437.7 | Q163: 987342.3 | R163: 247795.44 | S163: 1757613.8 | T163: 63043.371 | U163: 1063039.7 | V163: 1484977.2 | W163: 974346.62 | X163: 2507339.2 | Y163: 1352312.7 | Z163: 500343.88 | AA163: 870104.76 | AB163: 616826.16 | AC163: 2391326.6 | AD163: 877872.31 | AE163: 6912105.7 | AF163: 609649.16 | AG163: 87646.741 | AH163: 2291955.2 | AI163: 2991955.6 | AJ163: 370905.11 | AK163: 702296.12 | AL163: 604089.17 | AM163: 357817.45 | AN163: 80.355519 | AO163: 3363257 | AP163: 1191594.8 | AQ163: 2655136.8 | AR163: 2402364.3 | AS163: 59560.533 | AT163: 382394.73 | AU163: 360947.57 | AV163: 246566.62 | AW163: 140451.24 | AX163: 1414044.4 | AY163: 128424.98 | AZ163: 1236626 | BA163: 536650.06 | BB163: 364923.95 | BC163: 172062.45 | BD163: 594282.59 | BE163: 118712.43 | BF163: 649560.92 | BG163: 81679.073 | BH163: 2445445.5 | BI163: 2302234 | BJ163: 130103.95 | BK163: 575998.88 | BL163: 5145251.7 | BM163: 1764082.6 | BN163: 1037877.9 | BO163: 38516937 | BP163: 89844.098 | BQ163: 2264874.6 | BR163: 1712733.3 | BS163: 1494127.3 | BT163: 449434.19 | BU163: 45174.927 | BV163: 726785.63 | BW163: 184248.6 | BX163: 637944.08 | BY163: 106896.7 | BZ163: 619503.9 | CA163: 66411.483 | CB163: 59626.934 | CC163: 141911.56 | CD163: 5802.0959 | CE163: 3325327.3 | CF163: 211054.11 | CG163: 904587.24 | CH163: 433210.61 | CI163: 40074.151 | CJ163: 106762.57 | CK163: 528644.12 | CL163: 5314321.7 | CM163: 66168.956 | CN163: 16517.406 | CO163: 507805.58 | CP163: 2292428 | CQ163: 209133.49 | CR163: 60455.914 | CS163: 174787.38 | CT163: 229.02614 | CU163: 34064180 | CV163: 30843361 | CW163: 26980737 | CX163: 1911713.7 | CY163: 112409.06 | CZ163: 438014.92 | DA163: 2377590.1 | DB163: 253211.68 | DC163: 68835.228 | DD163: 379367.77 | DE163: 5463605.8 | DF163: 1156079.4 | DG163: 581897.26 | DH163: 11466072 | DI163: 851311.63 | DJ163: 281878.28 | DK163: 36631161 | DL163: 197036.65 | DM163: 311452.49 | DN163: 1300717.8 | DO163: 96429.974 | DP163: 567834.71 | DQ163: 337622.36 | DR163: 37617.345 | DS163: 2919112 | DT163: 27639.989 | DU163: 134511.92 | DV163: 1079121.4 | DW163: 276250.83 | DX163: 891651.71 | DY163: 2315873.3 | DZ163: 5181911.6 | EA163: 2596128.4 | EB163: 40788.791 | EC163: 26902.331 | ED163: 143646.99 | EE163: 30544.922 | EF163: 184240 | EG163: 129268.69 | EH163: 2238342.4 | EI163: 3588680.3 | EJ163: =SUM(D163:EI163) -> 4.9195466e+08 | EK163: 4.9195466e+08 | EL163: =EK163-EJ163 -> -0.069627523
A164: a= | B164: 0.25 | C164: Добавленная стоимость 0 | D164: =D158+D162+D163 -> 13789247 | E164: =E158+E162+E163 -> 32021278 | F164: =F158+F162+F163 -> 11417612 | G164: =G158+G162+G163 -> 6537511.7 | H164: =H158+H162+H163 -> 86433355 | I164: =I158+I162+I163 -> 26819265 | J164: =J158+J162+J163 -> 5089540.1 | K164: =K158+K162+K163 -> 1349079.1 | ... EJ164: =EJ158+EJ162+EJ163 -> 6.8643244e+08 | EK164: 6.8643244e+08 | EL164: =EK164-EJ164 -> -0.093625188
B165: =B164 -> 0.25 | C165: Добавленная стоимость 1 | D165: =D164+$B165*(D161-D160) -> 13800905 | E165: =E164+$B165*(E161-E160) -> 32044603 | F165: =F164+$B165*(F161-F160) -> 11426829 | G165: =G164+$B165*(G161-G160) -> 6542273.7 | H165: =H164+$B165*(H161-H160) -> 86496314 | I165: =I164+$B165*(I161-I160) -> 26838844 | J165: =J164+$B165*(J161-J160) -> 5094014.5 | K165: =K164+$B165*(K161-K160) -> 1350306 | ... EI165: =EI164+$B165*(EI161-EI160) -> 3757695
C166: Change | D166: =D165/D164-1 -> 0.00084544083 | E166: =E165/E164-1 -> 0.00072841167 | F166: =F165/F164-1 -> 0.00080722115 | G166: =G165/G164-1 -> 0.00072841167 | H166: =H165/H164-1 -> 0.00072841167 | I166: =I165/I164-1 -> 0.00073002971 | J166: =J165/J164-1 -> 0.00087914344 | K166: =K165/K164-1 -> 0.00090941313 | ... EI166: =EI165/EI164-1 -> 0.00072601188
C167: Выпуск0 (original output) | D167: =D157+D164 -> 18087286 | E167: =E157+E164 -> 40193339 | F167: =F157+F164 -> 14876014 | G167: =G157+G164 -> 8203864.6 | H167: =H157+H164 -> 1.0875629e+08 | I167: =I157+I164 -> 33185554 | J167: =J157+J164 -> 5935210.2 | K167: =K157+K164 -> 1776325.1 | ... EI167: =EI157+EI164 -> 4844854.1 | EJ167: =SUM(D167:EI167) -> 9.1379389e+08 | EK167: 1.3111044e+09 | EL167: =EK167-EJ167 -> 3.9731049e+08
C168: Выпуск 1 (Output 1- after VA shock) | D168: =D167+$B165*(D161-D160) -> 18098944 | E168: =E167+$B165*(E161-E160) -> 40216664 | F168: =F167+$B165*(F161-F160) -> 14885230 | G168: =G167+$B165*(G161-G160) -> 8208626.6 | H168: =H167+$B165*(H161-H160) -> 1.0881925e+08 | I168: =I167+$B165*(I161-I160) -> 33205133 | J168: =J167+$B165*(J161-J160) -> 5939684.7 | K168: =K167+$B165*(K161-K160) -> 1777552 | ... EI168: =EI167+$B165*(EI161-EI160) -> 4847580.3
C169: change Выпуск 1/0 (due to inflated value added initially) | D169: =D168/D167 -> 1.0006445 | E169: =E168/E167 -> 1.0005803 | F169: =F168/F167 -> 1.0006196 | G169: =G168/G167 -> 1.0005805 | H169: =H168/H167 -> 1.0005789 | I169: =I168/I167 -> 1.00059 | J169: =J168/J167 -> 1.0007539 | K169: =K168/K167 -> 1.0006907 | ... EI169: =EI168/EI167 -> 1.0005627
C170: Выпуск 2 (Output) 2 - after the first-pass Int. cons. propagation) | D170: =D168+$B164*D151 -> 20108937 | E170: =E168+$B164*E151 -> 44184443 | F170: =F168+$B164*F151 -> 16418081 | G170: =G168+$B164*G151 -> 9019221.8 | H170: =H168+$B164*H151 -> 1.1946357e+08 | I170: =I168+$B164*I151 -> 36667602 | J170: =J168+$B164*J151 -> 6341369.1 | K170: =K168+$B164*K151 -> 1977047.6 | ... EI170: =EI168+$B164*EI151 -> 5328748.4
C171: сhange Выпуск (Output) 2/1 (due to intermediate consumption inflation - first round) | D171: =D170/D168 -> 1.1110558 | E171: =E170/E168 -> 1.0986601 | F171: =F170/F168 -> 1.102978 | G171: =G170/G168 -> 1.0987492 | H171: =H170/H168 -> 1.0978165 | I171: =I170/I168 -> 1.1042751 | J171: =J170/J168 -> 1.0676272 | K171: =K170/K168 -> 1.1122305 | ... EI171: =EI170/EI168 -> 1.0992594
C172: Выпуск 3 (Output) 3 - after the second -pass Int. cons. propagation) | D172: =D170+$B165*D152 -> 20461767 | E172: =E170+$B165*E152 -> 44803536 | F172: =F170+$B165*F152 -> 16709132 | G172: =G170+$B165*G152 -> 9149451.5 | H172: =H170+$B165*H152 -> 1.2126754e+08 | I172: =I170+$B165*I152 -> 37268818 | J172: =J170+$B165*J152 -> 6391178.6 | K172: =K170+$B165*K152 -> 2012702.5 | ... EI172: =EI170+$B165*EI152 -> 5404519.8
C173: Output 3/2 | D173: =D172/D170 -> 1.0175459 | E173: =E172/E170 -> 1.0140116 | F173: =F172/F170 -> 1.0177275 | G173: =G172/G170 -> 1.0144391 | H173: =H172/H170 -> 1.0151006 | I173: =I172/I170 -> 1.0163964 | J173: =J172/J170 -> 1.0078547 | K173: =K172/K170 -> 1.0180345 | ... EI173: =EI172/EI170 -> 1.0142194
C174: Output 4 -after third iteration | D174: =D172+$B165*D153 -> 20525736 | E174: =E172+$B165*E153 -> 44906423 | F174: =F172+$B165*F153 -> 16761643 | G174: =G172+$B165*G153 -> 9172137.7 | H174: =H172+$B165*H153 -> 1.2158934e+08 | I174: =I172+$B165*I153 -> 37377657 | J174: =J172+$B165*J153 -> 6398567.1 | K174: =K172+$B165*K153 -> 2019318.1 | ... EI174: =EI172+$B165*EI153 -> 5419220.3
C175: Output 4/3 | D175: =D174/D172 -> 1.0031263 | E175: =E174/E172 -> 1.0022964 | F175: =F174/F172 -> 1.0031426 | G175: =G174/G172 -> 1.0024795 | H175: =H174/H172 -> 1.0026536 | I175: =I174/I172 -> 1.0029204 | J175: =J174/J172 -> 1.001156 | K175: =K174/K172 -> 1.0032869 | ... EI175: =EI174/EI172 -> 1.00272
C176: Output 5 -after 4th iteration | D176: =D174+$B165*D154 -> 20537616 | E176: =E174+$B165*E154 -> 44924560 | F176: =F174+$B165*F154 -> 16771378 | G176: =G174+$B165*G154 -> 9176280.5 | H176: =H174+$B165*H154 -> 1.2164875e+08 | I176: =I174+$B165*I154 -> 37398231 | J176: =J174+$B165*J154 -> 6399823.6 | K176: =K174+$B165*K154 -> 2020583.1 | ... EI176: =EI174+$B165*EI154 -> 5422094.8
C177: Output 5/4 | D177: =D176/D174 -> 1.0005788 | E177: =E176/E174 -> 1.0004039 | F177: =F176/F174 -> 1.0005808 | G177: =G176/G174 -> 1.0004517 | H177: =H176/H174 -> 1.0004886 | I177: =I176/I174 -> 1.0005504 | J177: =J176/J174 -> 1.0001964 | K177: =K176/K174 -> 1.0006265 | ... EI177: =EI176/EI174 -> 1.0005304
C178: Output 6- after fifth iteration | D178: =D176+$B165*D155 -> 20539879 | E178: =E176+$B165*E155 -> 44927929 | F178: =F176+$B165*F155 -> 16773242 | G178: =G176+$B165*G155 -> 9177066.2 | H178: =H176+$B165*H155 -> 1.2166008e+08 | I178: =I176+$B165*I155 -> 37402292 | J178: =J176+$B165*J155 -> 6400058.4 | K178: =K176+$B165*K155 -> 2020832.8 | ... EI178: =EI176+$B165*EI155 -> 5422662.9
C179: Output 6/5 | D179: =D178/D176 -> 1.0001102
B180: =AVERAGE(D180:EI180) -> 0.13936477 | C180: сhange Output 2/0 | D180: =(D170/D167)-1 -> 0.11177194 | E180: =(E170/E167)-1 -> 0.099297639 | F180: =(F170/F167)-1 -> 0.10366132 | G180: =(G170/G167)-1 -> 0.099386974 | H180: =(H170/H167)-1 -> 0.098452001 | I180: =(I170/I167)-1 -> 0.1049266 | J180: =(J170/J167)-1 -> 0.068432099 | K180: =(K170/K167)-1 -> 0.1129987 | ... EI180: =(EI170/EI167)-1 -> 0.099877978 | EJ180: =EJ170/EJ167 -> 0
B181: =AVERAGE(D181:EI181) -> 0.16689803 | C181: сhange Output 3/0 | D181: =(D172/D167)-1 -> 0.13127901 | E181: =(E172/E167)-1 -> 0.11470053 | F181: =(F172/F167)-1 -> 0.12322644 | G181: =(G172/G167)-1 -> 0.11526115 | H181: =(H172/H167)-1 -> 0.11503929 | I181: =(I172/I167)-1 -> 0.12304343 | J181: =(J172/J167)-1 -> 0.076824309 | K181: =(K172/K167)-1 -> 0.13307103 | ... EI181: =(EI172/EI167)-1 -> 0.11551755
C182: сhange Output 4/0 | D182: =D174/D167 -1 -> 0.1348157 | E182: =E174/E167 -1 -> 0.11726031 | F182: =F174/F167 -1 -> 0.12675633 | G182: =G174/G167 -1 -> 0.11802647 | H182: =H174/H167 -1 -> 0.11799816 | I182: =I174/I167 -1 -> 0.12632312 | J182: =J174/J167 -1 -> 0.07806916 | K182: =K174/K167 -1 -> 0.1367953 | ... EI182: =EI174/EI167 -1 -> 0.1185518
C183: сhange Output 5/0 | D183: =D176/D167-1 -> 0.13547254 | E183: =E176/E167-1 -> 0.11771157 | F183: =F176/F167-1 -> 0.12741075 | G183: =G176/G167-1 -> 0.11853145 | H183: =H176/H167-1 -> 0.11854443 | I183: =I176/I167-1 -> 0.12694308 | J183: =J176/J167-1 -> 0.07828086 | K183: =K176/K167-1 -> 0.1375075 | ... EI183: =EI176/EI167-1 -> 0.11914511
C184: change Output 6/0 | D184: =D178/D167-1 -> 0.13559762 | E184: =E178/E167-1 -> 0.11779539 | F184: =F178/F167-1 -> 0.12753603 | G184: =G178/G167-1 -> 0.11862721 | H184: =H178/H167-1 -> 0.11864864 | I184: =I178/I167-1 -> 0.12706545 | J184: =J178/J167-1 -> 0.078320422 | K184: =K178/K167-1 -> 0.13764806 | ... EI184: =EI178/EI167-1 -> 0.11926236
B185: =AVERAGE(D185:EI185) -> 0.84280582 | C185: ratio of second pass to first pass inflation index | D185: =D180/D181 -> 0.85140749 | E185: =E180/E181 -> 0.86571212 | F185: =F180/F181 -> 0.84122625 | G185: =G180/G181 -> 0.86227642 | H185: =H180/H181 -> 0.85581193 | I185: =I180/I181 -> 0.85276074 | J185: =J180/J181 -> 0.89076102 | K185: =K180/K181 -> 0.84916083 | ... EI185: =EI180/EI181 -> 0.86461305
B186: =AVERAGE(D186:EI186) -> 0.81772439 | C186: ratio of third pass to first pass inflation index | D186: =D180/D182 -> 0.82907213 | E186: =E180/E182 -> 0.84681369 | F186: =F180/F182 -> 0.81779993 | G186: =G180/G182 -> 0.84207361 | H186: =H180/H182 -> 0.83435203 | I186: =I180/I182 -> 0.83062072 | J186: =J180/J182 -> 0.8765574 | K186: =K180/K182 -> 0.82604227 | ... EI186: =EI180/EI182 -> 0.84248385
B187: =AVERAGE(D187:EI187) -> 0.81287749 | C187: ratio of fourth pass to first pass inflation index | D187: =D180/D183 -> 0.82505237 | E187: =E180/E183 -> 0.84356733 | F187: =F180/F183 -> 0.81359946 | G187: =G180/G183 -> 0.8384861 | H187: =H180/H183 -> 0.83050721 | I187: =I180/I183 -> 0.82656419 | J187: =J180/J183 -> 0.87418686 | K187: =K180/K183 -> 0.82176392 | ... EI187: =EI180/EI183 -> 0.83828854
B188: =AVERAGE(D$188:EI$188) -> 0.81188594 | C188: ratio of fifth pass to first pass inflation index | D188: =D180/D184 -> 0.82429131 | E188: =E180/E184 -> 0.84296707 | F188: =F180/F184 -> 0.81280024 | G188: =G180/G184 -> 0.83780922 | H188: =H180/H184 -> 0.82977776 | I188: =I180/I184 -> 0.82576815 | J188: =J180/J184 -> 0.87374529 | K188: =K180/K184 -> 0.82092476 | ... EI188: =EI180/EI184 -> 0.83746439
B189: =_xlfn.STDEV.P(D$188:EI$188) -> 0.033331017 | D189: {=TRANSPOSE(EU8:EU143)} -> 0 | E189: 0 | F189: 0 | G189: 0 | H189: 0 | I189: 0 | J189: 0 | K189: 0 | L189: 0 | M189: 0 | N189: 0 | O189: 0 | P189: 0 | Q189: 0 | R189: 0 | S189: 0 | T189: 0 | U189: 0 | V189: 0 | W189: 0 | X189: 0 | Y189: 0 | Z189: 0 | AA189: 0 | AB189: 0 | AC189: 0 | AD189: 0 | AE189: 0 | AF189: 0 | AG189: 0 | AH189: 0 | AI189: 0 | AJ189: 0 | AK189: 0 | AL189: 0 | AM189: 0 | AN189: 0 | AO189: 0 | AP189: 0 | AQ189: 0 | AR189: 0 | AS189: 0 | AT189: 0 | AU189: 0 | AV189: 0 | AW189: 0 | AX189: 0 | AY189: 0 | AZ189: 0 | BA189: 0 | BB189: 0 | BC189: 0 | BD189: 0 | BE189: 0 | BF189: 0 | BG189: 0 | BH189: 0 | BI189: 0 | BJ189: 0 | BK189: 0 | BL189: 0 | BM189: 0 | BN189: 0 | BO189: 0 | BP189: 0 | BQ189: 0 | BR189: 0 | BS189: 0 | BT189: 0 | BU189: 0 | BV189: 0 | BW189: 0 | BX189: 0 | BY189: 0 | BZ189: 0 | CA189: 0 | CB189: 0 | CC189: 0 | CD189: 0 | CE189: 0 | CF189: 0 | CG189: 0 | CH189: 0 | CI189: 0 | CJ189: 0 | CK189: 0 | CL189: 0 | CM189: 0 | CN189: 0 | CO189: 0 | CP189: 0 | CQ189: 0 | CR189: 0 | CS189: 0 | CT189: 0 | CU189: 0 | CV189: 0 | CW189: 0 | CX189: 0 | CY189: 0 | CZ189: 0 | DA189: 0 | DB189: 0 | DC189: 0 | DD189: 0 | DE189: 0 | DF189: 0 | DG189: 0 | DH189: 0 | DI189: 0 | DJ189: 0 | DK189: 0 | DL189: 0 | DM189: 0 | DN189: 0 | DO189: 0 | DP189: 0 | DQ189: 0 | DR189: 0 | DS189: 0 | DT189: 0 | DU189: 0 | DV189: 0 | DW189: 0 | DX189: 0 | DY189: 0 | DZ189: 0 | EA189: 0 | EB189: 0 | EC189: 0 | ED189: 0 | EE189: 0 | EF189: 0 | EG189: 0 | EH189: 0 | EI189: 0 | EJ189: =SUM(D189:EI189) -> 0
D190: =D189-D167 -> -18087286 | E190: =E189-E167 -> -40193339 | F190: =F189-F167 -> -14876014 | G190: =G189-G167 -> -8203864.6 | H190: =H189-H167 -> -1.0875629e+08 | I190: =I189-I167 -> -33185554 | J190: =J189-J167 -> -5935210.2 | K190: =K189-K167 -> -1776325.1 | ... EI190: =EI189-EI167 -> -4844854.1 | EJ190: =SUM(D190:EI190) -> -9.1379389e+08
B191: 0 | C191: =D165 -> 13800905 | D191: =D164 -> 13789247 | E191: =D167 -> 18087286 | F191: =D169 -> 1.0006445
B192: 1 | C192: =OFFSET($D$165,0,B192) -> 32044603 | D192: =OFFSET($D$164,0,B192) -> 32021278 | E192: =OFFSET($D$167,0,B192) -> 40193339 | F192: =OFFSET($D$169,0,B192) -> 1.0005803 | I192: 0.001
B193: 2 | C193: =OFFSET($D$165,0,B193) -> 11426829 | D193: =OFFSET($D$164,0,B193) -> 11417612 | E193: =OFFSET($D$167,0,B193) -> 14876014 | F193: =OFFSET($D$169,0,B193) -> 1.0006196 | I193: 0 | J193: =I193+$I$192 -> 0.001 | K193: =J193+$I$192 -> 0.002 | L193: =K193+$I$192 -> 0.003 | M193: =L193+$I$192 -> 0.004 | N193: =M193+$I$192 -> 0.005 | O193: =N193+$I$192 -> 0.006 | P193: =O193+$I$192 -> 0.007 | Q193: =P193+$I$192 -> 0.008 | ... AR193: =AQ193+$I$192 -> 0.035
B194: 3 | C194: =OFFSET($D$165,0,B194) -> 6542273.7 | D194: =OFFSET($D$164,0,B194) -> 6537511.7 | E194: =OFFSET($D$167,0,B194) -> 8203864.6 | F194: =OFFSET($D$169,0,B194) -> 1.0005805
B195: 4 | C195: =OFFSET($D$165,0,B195) -> 86496314 | D195: =OFFSET($D$164,0,B195) -> 86433355 | E195: =OFFSET($D$167,0,B195) -> 1.0875629e+08 | F195: =OFFSET($D$169,0,B195) -> 1.0005789
B196: 5 | C196: =OFFSET($D$165,0,B196) -> 26838844 | D196: =OFFSET($D$164,0,B196) -> 26819265 | E196: =OFFSET($D$167,0,B196) -> 33185554 | F196: =OFFSET($D$169,0,B196) -> 1.00059
B197: 6 | C197: =OFFSET($D$165,0,B197) -> 5094014.5 | D197: =OFFSET($D$164,0,B197) -> 5089540.1 | E197: =OFFSET($D$167,0,B197) -> 5935210.2 | F197: =OFFSET($D$169,0,B197) -> 1.0007539 | K197: Bin | L197: Frequency
B198: 7 | C198: =OFFSET($D$165,0,B198) -> 1350306 | D198: =OFFSET($D$164,0,B198) -> 1349079.1 | E198: =OFFSET($D$167,0,B198) -> 1776325.1 | F198: =OFFSET($D$169,0,B198) -> 1.0006907 | K198: 0 | L198: 0
B199: 8 | C199: =OFFSET($D$165,0,B199) -> 637401.32 | D199: =OFFSET($D$164,0,B199) -> 632769.82 | E199: =OFFSET($D$167,0,B199) -> 828172.56 | F199: =OFFSET($D$169,0,B199) -> 1.0055924 | K199: 0.001 | L199: 1
B200: 9 | C200: =OFFSET($D$165,0,B200) -> 3823411.3 | D200: =OFFSET($D$164,0,B200) -> 3816805.4 | E200: =OFFSET($D$167,0,B200) -> 4561264.6 | F200: =OFFSET($D$169,0,B200) -> 1.0014483 | K200: 0.002 | L200: 18
B201: 10 | C201: =OFFSET($D$165,0,B201) -> 16370689 | D201: =OFFSET($D$164,0,B201) -> 16342214 | E201: =OFFSET($D$167,0,B201) -> 19964241 | F201: =OFFSET($D$169,0,B201) -> 1.0014263 | K201: 0.003 | L201: 35
B202: 11 | C202: =OFFSET($D$165,0,B202) -> 810.92195 | D202: =OFFSET($D$164,0,B202) -> 810.01904 | E202: =OFFSET($D$167,0,B202) -> 1004.3737 | F202: =OFFSET($D$169,0,B202) -> 1.000899 | K202: 0.004 | L202: 24
B203: 12 | C203: =OFFSET($D$165,0,B203) -> 6256727.4 | D203: =OFFSET($D$164,0,B203) -> 6249759 | E203: =OFFSET($D$167,0,B203) -> 7835017.5 | F203: =OFFSET($D$169,0,B203) -> 1.0008894 | K203: 0.005 | L203: 16
B204: 13 | C204: =OFFSET($D$165,0,B204) -> 1281636.7 | D204: =OFFSET($D$164,0,B204) -> 1278862.7 | E204: =OFFSET($D$167,0,B204) -> 1886296.2 | F204: =OFFSET($D$169,0,B204) -> 1.0014706 | K204: 0.006 | L204: 7
B205: 14 | C205: =OFFSET($D$165,0,B205) -> 504126.97 | D205: =OFFSET($D$164,0,B205) -> 501474.05 | E205: =OFFSET($D$167,0,B205) -> 854558.84 | F205: =OFFSET($D$169,0,B205) -> 1.0031044 | K205: 0.007 | L205: 4
B206: 15 | C206: =OFFSET($D$165,0,B206) -> 2231232 | D206: =OFFSET($D$164,0,B206) -> 2227426.3 | E206: =OFFSET($D$167,0,B206) -> 4119531.8 | F206: =OFFSET($D$169,0,B206) -> 1.0009238 | K206: 0.008 | L206: 3
B207: 16 | C207: =OFFSET($D$165,0,B207) -> 80029.95 | D207: =OFFSET($D$164,0,B207) -> 79893.473 | E207: =OFFSET($D$167,0,B207) -> 153417.86 | F207: =OFFSET($D$169,0,B207) -> 1.0008896 | K207: 0.009 | L207: 1
B208: 17 | C208: =OFFSET($D$165,0,B208) -> 1349814.3 | D208: =OFFSET($D$164,0,B208) -> 1347507.8 | E208: =OFFSET($D$167,0,B208) -> 2589052.5 | F208: =OFFSET($D$169,0,B208) -> 1.0008909 | K208: 0.01 | L208: 4
B209: 18 | C209: =OFFSET($D$165,0,B209) -> 1892345.8 | D209: =OFFSET($D$164,0,B209) -> 1888973.1 | E209: =OFFSET($D$167,0,B209) -> 3548027.2 | F209: =OFFSET($D$169,0,B209) -> 1.0009506 | K209: 0.011 | L209: 2
... B233: 42 | C233: =OFFSET($D$165,0,B233) -> 483662.8 | D233: =OFFSET($D$164,0,B233) -> 482581.12 | E233: =OFFSET($D$167,0,B233) -> 806973.73 | F233: =OFFSET($D$169,0,B233) -> 1.0013404 | K233: 0.035 | L233: 1
B234: 43 | C234: =OFFSET($D$165,0,B234) -> 447213.57 | D234: =OFFSET($D$164,0,B234) -> 446327.75 | E234: =OFFSET($D$167,0,B234) -> 759768.94 | F234: =OFFSET($D$169,0,B234) -> 1.0011659 | K234: More | L234: 5
B235: 44 | C235: =OFFSET($D$165,0,B235) -> 316431.71 | D235: =OFFSET($D$164,0,B235) -> 315701.23 | E235: =OFFSET($D$167,0,B235) -> 531765.39 | F235: =OFFSET($D$169,0,B235) -> 1.0013737
B236: 45 | C236: =OFFSET($D$165,0,B236) -> 177083.13 | D236: =OFFSET($D$164,0,B236) -> 176710.02 | E236: =OFFSET($D$167,0,B236) -> 304392.65 | F236: =OFFSET($D$169,0,B236) -> 1.0012258
B237: 46 | C237: =OFFSET($D$165,0,B237) -> 1712085.8 | D237: =OFFSET($D$164,0,B237) -> 1709242.2 | E237: =OFFSET($D$167,0,B237) -> 2448961.1 | F237: =OFFSET($D$169,0,B237) -> 1.0011612
B238: 47 | C238: =OFFSET($D$165,0,B238) -> 166248.78 | D238: =OFFSET($D$164,0,B238) -> 165872.88 | E238: =OFFSET($D$167,0,B238) -> 313774.12 | F238: =OFFSET($D$169,0,B238) -> 1.001198
B239: 48 | C239: =OFFSET($D$165,0,B239) -> 1607885.1 | D239: =OFFSET($D$164,0,B239) -> 1604224.8 | E239: =OFFSET($D$167,0,B239) -> 2982899.9 | F239: =OFFSET($D$169,0,B239) -> 1.0012271
B240: 49 | C240: =OFFSET($D$165,0,B240) -> 696787.24 | D240: =OFFSET($D$164,0,B240) -> 695180.37 | E240: =OFFSET($D$167,0,B240) -> 1389510.2 | F240: =OFFSET($D$169,0,B240) -> 1.0011564
B241: 50 | C241: =OFFSET($D$165,0,B241) -> 472521.95 | D241: =OFFSET($D$164,0,B241) -> 471443.82 | E241: =OFFSET($D$167,0,B241) -> 887739.21 | F241: =OFFSET($D$169,0,B241) -> 1.0012145
B242: 51 | C242: =OFFSET($D$165,0,B242) -> 225525.02 | D242: =OFFSET($D$164,0,B242) -> 224986.15 | E242: =OFFSET($D$167,0,B242) -> 438751.54 | F242: =OFFSET($D$169,0,B242) -> 1.0012282
B243: 52 | C243: =OFFSET($D$165,0,B243) -> 801000.66 | D243: =OFFSET($D$164,0,B243) -> 798842.4 | E243: =OFFSET($D$167,0,B243) -> 1222830.5 | F243: =OFFSET($D$169,0,B243) -> 1.001765
B244: 53 | C244: =OFFSET($D$165,0,B244) -> 159536.6 | D244: =OFFSET($D$164,0,B244) -> 159111.23 | E244: =OFFSET($D$167,0,B244) -> 242471.15 | F244: =OFFSET($D$169,0,B244) -> 1.0017543
B245: 54 | C245: =OFFSET($D$165,0,B245) -> 874957.39 | D245: =OFFSET($D$164,0,B245) -> 872611 | E245: =OFFSET($D$167,0,B245) -> 1332950.2 | F245: =OFFSET($D$169,0,B245) -> 1.0017603
B246: 55 | C246: =OFFSET($D$165,0,B246) -> 109940.34 | D246: =OFFSET($D$164,0,B246) -> 109645.37 | E246: =OFFSET($D$167,0,B246) -> 167593.38 | F246: =OFFSET($D$169,0,B246) -> 1.00176
...

Sheet Sheet1
A1: 3

Sheet primary effect
A1: 0 | B1: ='ТЗВ всего'!D169 -> 1.0006445 | C1: 4493539.6 | D1: 934573.17 | E1: 1125754.7 | F1: 802266.41 | G1: 4697918 | H1: 1263943.6 | I1: 471.7486 | J1: 113165.8 | K1: 0 | L1: 0 | M1: 0 | N1: 0 | O1: 8.7919367e-06 | P1: 661.70893 | Q1: 0 | R1: 608600.03 | S1: 27258.852 | T1: 527998.82 | U1: 1742724.6 | V1: 13556.519 | W1: 5428216.9 | X1: 123437.32 | Y1: 21476.855 | Z1: 2092.7636 | AA1: 728578.73 | AB1: 439586.38 | AC1: 19.884407 | AD1: 149.5875 | AE1: 21.745292 | AF1: 8.2231896e-06 | AG1: 283.43797 | AH1: 376.43592 | AI1: 1689.3346 | AJ1: 79.292279 | AK1: 336.14287 | AL1: 1.3331129e-06 | AM1: 0 | AN1: 101.65998 | AO1: 6342.7176 | AP1: 66.761073 | AQ1: 205.79554 | AR1: 218.09675 | AS1: 0 | AT1: 51892.516 | AU1: 1167.7775 | AV1: 0 | AW1: 691.50941 | AX1: 0.00085271109 | AY1: 428.70039 | AZ1: 4181.3473 | BA1: 47.228094 | BB1: 58.400659 | BC1: 0.0008025781 | BD1: 6.1136658 | BE1: 790.42261 | BF1: 0.83962812 | BG1: 380.93534 | BH1: 1118.6719 | BI1: 0.02858265 | BJ1: 6.4203423 | BK1: 50.040521 | BL1: 0.023996741 | BM1: 618.2374 | BN1: 0.017312931 | BO1: 0 | BP1: 8.8211789 | BQ1: 56.914142 | BR1: 13.766479 | BS1: 0.64518858 | BT1: 0 | BU1: 0.019080708 | BV1: 8.2539464e-06 | BW1: 0 | BX1: 0.10909365 | BY1: 3546.2318 | BZ1: 0.11256113 | CA1: 0.014163346 | CB1: 0.016731062 | CC1: 10.500687 | CD1: 0 | CE1: 279.17862 | CF1: 18.724078 | CG1: 114.14384 | CH1: 0 | CI1: 11.429709 | CJ1: 436.32017 | CK1: 0 | CL1: 0 | CM1: 0 | CN1: 0.017020976 | CO1: 253.37262 | CP1: 312.55716 | CQ1: 0.00663144 | CR1: 41.730895 | CS1: 0 | CT1: 0.0057721901 | CU1: 0 | CV1: 0 | CW1: 0 | CX1: 0 | CY1: 166.56314 | CZ1: 14777.792 | DA1: 0 | DB1: 0 | DC1: 0 | DD1: 0 | DE1: 0 | DF1: 0 | DG1: 0 | DH1: 0 | DI1: 0 | DJ1: 0 | DK1: 0 | DL1: 0.95607278 | DM1: 5.8523902 | DN1: 85.199154 | DO1: 0 | DP1: 17602.02 | DQ1: 0.1922601 | DR1: 1168.5676 | DS1: 18.453274 | DT1: 0.0023874768 | DU1: 0 | DV1: 2840.1529 | DW1: 8.7283502 | DX1: 13831.01 | DY1: 14351.588 | DZ1: 3528.9524 | EA1: 0 | EB1: 1440.4502 | EC1: 212.7003 | ED1: 0 | EE1: 414.60667 | EF1: 58.974554 | EG1: 54.348744 | EH1: 67.448931 | EJ1: =C1*$B1 -> 4496435.9 | EK1: =D1*$B1 -> 935175.54 | EL1: =E1*$B1 -> 1126480.3 | EM1: =F1*$B1 -> 802783.51 | EN1: =G1*$B1 -> 4700946 | EO1: =H1*$B1 -> 1264758.2 | EP1: =I1*$B1 -> 472.05267 | EQ1: =J1*$B1 -> 113238.74 | ... JO1: =EH1*$B1 -> 67.492405
A2: 1 | B2: =OFFSET('ТЗВ всего'!$D$169,0,A2) -> 1.0005803 | C2: 755791.72 | D2: 13295609 | E2: 1263829.8 | F2: 627638.81 | G2: 371317.65 | H2: 2518294.7 | I2: 3250.7368 | J2: 250.31346 | K2: 0 | L2: 0 | M2: 0 | N2: 0 | O2: 0 | P2: 455.75935 | Q2: 0 | R2: 1748.9078 | S2: 95.60101 | T2: 452302.84 | U2: 159.56854 | V2: 1300.2877 | W2: 1710.7953 | X2: 17588.634 | Y2: 5578.3783 | Z2: 12.611004 | AA2: 2182.6095 | AB2: 2413.561 | AC2: 1.558386 | AD2: 124.61526 | AE2: 19.590736 | AF2: 0 | AG2: 19.192673 | AH2: 21.901949 | AI2: 3.4730819 | AJ2: 59.730166 | AK2: 293.53601 | AL2: 0 | AM2: 0 | AN2: 0.0067300914 | AO2: 0.59736178 | AP2: 12.07508 | AQ2: 0.034667049 | AR2: 0.23757591 | AS2: 0 | AT2: 5.1128807 | AU2: 0.07725638 | AV2: 0 | AW2: 15.331251 | AX2: 0 | AY2: 0.68714718 | AZ2: 2.9926631 | BA2: 11.383234 | BB2: 0.0012336148 | BC2: 0 | BD2: 1.0396286 | BE2: 1.0320523 | BF2: 0.14277831 | BG2: 0.033323788 | BH2: 4.3286676 | BI2: 0.0048533964 | BJ2: 0.00039485431 | BK2: 0.0033124128 | BL2: 0 | BM2: 6.2320451 | BN2: 0 | BO2: 0 | BP2: 0.71769968 | BQ2: 6.4274662 | BR2: 2.3272812 | BS2: 0 | BT2: 0 | BU2: 0 | BV2: 0 | BW2: 0 | BX2: 0 | BY2: 2.9630338 | BZ2: 0 | CA2: 0 | CB2: 0 | CC2: 0.020578489 | CD2: 0 | CE2: 0.56103901 | CF2: 3.0336417 | CG2: 77.971756 | CH2: 0 | CI2: 1.7129957 | CJ2: 11.675723 | CK2: 0 | CL2: 0 | CM2: 0 | CN2: 0 | CO2: 0.16069812 | CP2: 0.64447655 | CQ2: 0 | CR2: 5.2026507 | CS2: 0 | CT2: 0 | CU2: 0 | CV2: 0 | CW2: 0 | CX2: 0 | CY2: 3453.0302 | CZ2: 372962.45 | DA2: 0 | DB2: 0 | DC2: 0.025188929 | DD2: 0 | DE2: 0 | DF2: 0 | DG2: 0 | DH2: 0 | DI2: 0 | DJ2: 0 | DK2: 21.786864 | DL2: 0 | DM2: 17.003531 | DN2: 26.812717 | DO2: 0 | DP2: 41597.139 | DQ2: 0.4418177 | DR2: 840.79403 | DS2: 0 | DT2: 0.0045168225 | DU2: 0 | DV2: 0 | DW2: 10.354735 | DX2: 593374.28 | DY2: 261672.18 | DZ2: 35898.339 | EA2: 1264.4034 | EB2: 23805.922 | EC2: 2584.8233 | ED2: 0 | EE2: 4061.1265 | EF2: 89.308068 | EG2: 0 | EH2: 2846.3953 | EJ2: =C2*$B2 -> 756230.31 | EK2: =D2*$B2 -> 13303325 | EL2: =E2*$B2 -> 1264563.2 | EM2: =F2*$B2 -> 628003.04 | EN2: =G2*$B2 -> 371533.13 | EO2: =H2*$B2 -> 2519756.1 | EP2: =I2*$B2 -> 3252.6232 | EQ2: =J2*$B2 -> 250.45872 | ... JO2: =EH2*$B2 -> 2848.0471
A3: 2 | B3: =OFFSET('ТЗВ всего'!$D$169,0,A3) -> 1.0006196 | C3: 1211497.5 | D3: 17921.855 | E3: 648059.43 | F3: 0 | G3: 0 | H3: 4946.5809 | I3: 0 | J3: 0 | K3: 0 | L3: 0 | M3: 0 | N3: 0 | O3: 0 | P3: 2.3848613 | Q3: 0 | R3: 400.51932 | S3: 0 | T3: 14.121126 | U3: 270897.79 | V3: 0.16862829 | W3: 2.0020008 | X3: 209.0783 | Y3: 117.87331 | Z3: 0 | AA3: 0 | AB3: 4.949326 | AC3: 0 | AD3: 12903563 | AE3: 368861.3 | AF3: 5927.9588 | AG3: 571385.13 | AH3: 74756.761 | AI3: 540.37571 | AJ3: 1.7621942 | AK3: 5835.415 | AL3: 619.65314 | AM3: 0 | AN3: 0 | AO3: 107.92182 | AP3: 0 | AQ3: 23.318434 | AR3: 0 | AS3: 91.92631 | AT3: 16.285663 | AU3: 243.38292 | AV3: 51353.377 | AW3: 6.7937765 | AX3: 2250.7014 | AY3: 1967.1073 | AZ3: 10317.613 | BA3: 31.883307 | BB3: 675.98875 | BC3: 0.19875273 | BD3: 67.832072 | BE3: 0 | BF3: 0.19875273 | BG3: 384.01977 | BH3: 82.740041 | BI3: 0 | BJ3: 14.342579 | BK3: 2.795321 | BL3: 0.077489203 | BM3: 0 | BN3: 0 | BO3: 11.612487 | BP3: 70.924923 | BQ3: 27.538171 | BR3: 21.435799 | BS3: 0.020391896 | BT3: 0 | BU3: 0 | BV3: 0 | BW3: 0 | BX3: 0.020391896 | BY3: 203.98673 | BZ3: 11.622973 | CA3: 0.88337692 | CB3: 0 | CC3: 2.8981865 | CD3: 263.77208 | CE3: 0.020391896 | CF3: 2370.793 | CG3: 99.791305 | CH3: 0.85743197 | CI3: 344.17469 | CJ3: 0.38744602 | CK3: 0 | CL3: 193.63573 | CM3: 0 | CN3: 0 | CO3: 2465.9123 | CP3: 0 | CQ3: 0 | CR3: 58317.461 | CS3: 0 | CT3: 0 | CU3: 0 | CV3: 0 | CW3: 0 | CX3: 0 | CY3: 0 | CZ3: 0 | DA3: 0 | DB3: 0 | DC3: 0 | DD3: 0 | DE3: 0 | DF3: 0 | DG3: 0 | DH3: 0 | DI3: 0 | DJ3: 0 | DK3: 0 | DL3: 0 | DM3: 0 | DN3: 20.949658 | DO3: 0 | DP3: 0 | DQ3: 0 | DR3: 0 | DS3: 0 | DT3: 0 | DU3: 0 | DV3: 0 | DW3: 0 | DX3: 0 | DY3: 0.6298157 | DZ3: 0 | EA3: 0 | EB3: 0 | EC3: 0 | ED3: 0 | EE3: 0 | EF3: 0 | EG3: 0 | EH3: 0 | EJ3: =C3*$B3 -> 1212248 | EK3: =D3*$B3 -> 17932.959 | EL3: =E3*$B3 -> 648460.94 | EM3: =F3*$B3 -> 0 | EN3: =G3*$B3 -> 0 | EO3: =H3*$B3 -> 4949.6456 | EP3: =I3*$B3 -> 0 | EQ3: =J3*$B3 -> 0 | ... JO3: =EH3*$B3 -> 0
A4: 3 | B4: =OFFSET('ТЗВ всего'!$D$169,0,A4) -> 1.0005805 | C4: 16772.072 | D4: 232065.31 | E4: 87.189667 | F4: 336061.99 | G4: 20659.54 | H4: 152159.67 | I4: 0 | J4: 156.56973 | K4: 0 | L4: 0 | M4: 0 | N4: 0 | O4: 0 | P4: 277.07775 | Q4: 0 | R4: 253.38227 | S4: 0 | T4: 279246.01 | U4: 4.8328301 | V4: 788.86408 | W4: 347.19644 | X4: 532.97533 | Y4: 1897.4794 | Z4: 308.32181 | AA4: 103.28842 | AB4: 1948222.1 | AC4: 1.1456065 | AD4: 75.94161 | AE4: 12.065771 | AF4: 0 | AG4: 0.068888214 | AH4: 11.425905 | AI4: 0.00036929441 | AJ4: 36.800872 | AK4: 206.69331 | AL4: 0 | AM4: 0 | AN4: 0 | AO4: 202.22312 | AP4: 7.1063813 | AQ4: 0.0021220938 | AR4: 989.54454 | AS4: 0 | AT4: 27.195684 | AU4: 5.3420776 | AV4: 0 | AW4: 0.0070689202 | AX4: 0 | AY4: 1706.1726 | AZ4: 12545.781 | BA4: 0 | BB4: 266.33287 | BC4: 0 | BD4: 0.003732271 | BE4: 0.011325767 | BF4: 0.00051257475 | BG4: 0 | BH4: 0.080876286 | BI4: 1.7423714e-05 | BJ4: 0 | BK4: 0 | BL4: 0 | BM4: 0 | BN4: 0 | BO4: 0 | BP4: 0.00092533907 | BQ4: 0.022720869 | BR4: 0.0083549496 | BS4: 0 | BT4: 0 | BU4: 0 | BV4: 0 | BW4: 0 | BX4: 0 | BY4: 45.445246 | BZ4: 0 | CA4: 0 | CB4: 0 | CC4: 0 | CD4: 0 | CE4: 1.5141912e-05 | CF4: 0.0094975096 | CG4: 33.998345 | CH4: 0 | CI4: 0.0052576084 | CJ4: 4.9141984 | CK4: 0 | CL4: 0 | CM4: 0 | CN4: 0 | CO4: 22.28129 | CP4: 1366.7605 | CQ4: 0 | CR4: 0.018785731 | CS4: 0 | CT4: 0 | CU4: 0 | CV4: 0 | CW4: 0 | CX4: 0 | CY4: 52.836347 | CZ4: 0 | DA4: 0 | DB4: 0 | DC4: 0.061807 | DD4: 0 | DE4: 0 | DF4: 0 | DG4: 0 | DH4: 0 | DI4: 0 | DJ4: 0 | DK4: 0 | DL4: 0 | DM4: 0 | DN4: 0.3651651 | DO4: 0 | DP4: 15442.992 | DQ4: 0 | DR4: 842.75934 | DS4: 0 | DT4: 0.010348712 | DU4: 0 | DV4: 0 | DW4: 0 | DX4: 69017.882 | DY4: 5465.3895 | DZ4: 411.03745 | EA4: 0 | EB4: 0 | EC4: 3.6240038 | ED4: 0 | EE4: 221.99773 | EF4: 1.3796707 | EG4: 0 | EH4: 2.9004252 | EJ4: =C4*$B4 -> 16781.808 | EK4: =D4*$B4 -> 232200.01 | EL4: =E4*$B4 -> 87.240277 | EM4: =F4*$B4 -> 336257.06 | EN4: =G4*$B4 -> 20671.532 | EO4: =H4*$B4 -> 152247.99 | EP4: =I4*$B4 -> 0 | EQ4: =J4*$B4 -> 156.66062 | ... JO4: =EH4*$B4 -> 2.9021088
A5: 4 | B5: =OFFSET('ТЗВ всего'!$D$169,0,A5) -> 1.0005789 | C5: 626855.74 | D5: 499861.84 | E5: 27371.534 | F5: 198942.65 | G5: 34086279 | H5: 1220360 | I5: 11602.169 | J5: 23975.451 | K5: 0 | L5: 0 | M5: 0 | N5: 0 | O5: 0.80076482 | P5: 924.04201 | Q5: 0.10459105 | R5: 2950862.3 | S5: 24607.32 | T5: 3689.8282 | U5: 758876.19 | V5: 1882988.4 | W5: 7780.0303 | X5: 61398.619 | Y5: 56169.625 | Z5: 74.476788 | AA5: 60354.161 | AB5: 26932.251 | AC5: 17.380297 | AD5: 343846.94 | AE5: 24934.035 | AF5: 525.41615 | AG5: 14608.678 | AH5: 11867.018 | AI5: 374042.12 | AJ5: 0.45580829 | AK5: 2965.1367 | AL5: 6.9812283 | AM5: 0 | AN5: 44.707453 | AO5: 5584.8288 | AP5: 344.97497 | AQ5: 27.142033 | AR5: 3.0423457 | AS5: 1.0374647 | AT5: 23034.034 | AU5: 521.97159 | AV5: 1308.6482 | AW5: 621.33888 | AX5: 119.27948 | AY5: 149.79461 | AZ5: 2130.5647 | BA5: 161.35468 | BB5: 14.0099 | BC5: 0.019001251 | BD5: 4.1967562 | BE5: 3704.3267 | BF5: 0.47404295 | BG5: 177.45134 | BH5: 1443.7455 | BI5: 0.018544476 | BJ5: 3.6616812 | BK5: 22.164957 | BL5: 440.34873 | BM5: 79.010023 | BN5: 0.089715411 | BO5: 0.1303062 | BP5: 36.338572 | BQ5: 411.86711 | BR5: 7.9310654 | BS5: 0.004444176 | BT5: 0 | BU5: 0 | BV5: 0 | BW5: 0 | BX5: 0.00052176649 | BY5: 50.334277 | BZ5: 0.29739646 | CA5: 0.022602924 | CB5: 0 | CC5: 51.400176 | CD5: 1699.799 | CE5: 1386.2322 | CF5: 74.45957 | CG5: 283.41638 | CH5: 0.0096214275 | CI5: 20.839506 | CJ5: 44.736354 | CK5: 0 | CL5: 4.9652264 | CM5: 0 | CN5: 0.0010737861 | CO5: 624.57334 | CP5: 3.1330214 | CQ5: 0.57217715 | CR5: 4101.5331 | CS5: 0 | CT5: 0 | CU5: 0 | CV5: 0 | CW5: 0 | CX5: 0 | CY5: 801.18382 | CZ5: 1232729.7 | DA5: 0 | DB5: 0 | DC5: 0.35641349 | DD5: 0 | DE5: 0 | DF5: 0 | DG5: 0 | DH5: 0 | DI5: 0 | DJ5: 0 | DK5: 0 | DL5: 0 | DM5: 0 | DN5: 483.62231 | DO5: 0 | DP5: 0 | DQ5: 283.01021 | DR5: 132.3016 | DS5: 17.112077 | DT5: 0 | DU5: 0 | DV5: 0 | DW5: 0 | DX5: 660633.54 | DY5: 1110026.2 | DZ5: 170328.3 | EA5: 1512.0913 | EB5: 3030.3833 | EC5: 9139.9173 | ED5: 724.74257 | EE5: 24399.625 | EF5: 11.084164 | EG5: 0 | EH5: 0 | EJ5: =C5*$B5 -> 627218.63 | EK5: =D5*$B5 -> 500151.21 | EL5: =E5*$B5 -> 27387.379 | EM5: =F5*$B5 -> 199057.81 | EN5: =G5*$B5 -> 34106012 | EO5: =H5*$B5 -> 1221066.5 | EP5: =I5*$B5 -> 11608.885 | EQ5: =J5*$B5 -> 23989.33 | ... JO5: =EH5*$B5 -> 0
A6: 5 | B6: =OFFSET('ТЗВ всего'!$D$169,0,A6) -> 1.00059 | C6: 1786690.6 | D6: 5303887.5 | E6: 2068287.2 | F6: 2098636.2 | G6: 9089024.3 | H6: 8956377.1 | I6: 237139.01 | J6: 25998.135 | K6: 35.850332 | L6: 3.0705375 | M6: 18.056503 | N6: 0 | O6: 0.037513452 | P6: 698.67454 | Q6: 2.0969754 | R6: 26924.833 | S6: 3282.1428 | T6: 524761.38 | U6: 8535.6528 | V6: 2095.3577 | W6: 26601.984 | X6: 30884.498 | Y6: 38773.923 | Z6: 109.85406 | AA6: 51829.066 | AB6: 298130.22 | AC6: 66919.94 | AD6: 21031.98 | AE6: 693.55477 | AF6: 13.851725 | AG6: 2947.8169 | AH6: 767.23261 | AI6: 1260.6289 | AJ6: 19025.886 | AK6: 1760.933 | AL6: 10.546719 | AM6: 0.00049771063 | AN6: 50.108502 | AO6: 3206.1093 | AP6: 25137.79 | AQ6: 2026.8672 | AR6: 674.22436 | AS6: 1.407447 | AT6: 5896.4969 | AU6: 652.41498 | AV6: 95.707314 | AW6: 88370.104 | AX6: 11616.485 | AY6: 12590.235 | AZ6: 2518.874 | BA6: 286.53592 | BB6: 942.20717 | BC6: 3.0858004 | BD6: 44.846429 | BE6: 17.235569 | BF6: 8.8363189 | BG6: 2.4334636 | BH6: 49.052534 | BI6: 0.37452309 | BJ6: 11.23851 | BK6: 12.793936 | BL6: 44.58141 | BM6: 227.67671 | BN6: 68.48716 | BO6: 0.14897531 | BP6: 606.87472 | BQ6: 186.83502 | BR6: 48.343128 | BS6: 12.64809 | BT6: 10.173456 | BU6: 46.220153 | BV6: 88.157513 | BW6: 185.20133 | BX6: 21.628355 | BY6: 2313.6129 | BZ6: 48.357495 | CA6: 34.954882 | CB6: 24.794469 | CC6: 0.77234169 | CD6: 47.89257 | CE6: 16.086628 | CF6: 3170.1907 | CG6: 740.0435 | CH6: 1637.0526 | CI6: 209.76746 | CJ6: 245.58012 | CK6: 21854.645 | CL6: 1.1046648 | CM6: 0 | CN6: 0.00078777892 | CO6: 272.14977 | CP6: 226.93267 | CQ6: 42.4969 | CR6: 157.62644 | CS6: 11.847961 | CT6: 28153.093 | CU6: 221607.26 | CV6: 26923.407 | CW6: 0 | CX6: 0 | CY6: 1553.9143 | CZ6: 52240.756 | DA6: 0.0080769847 | DB6: 17.888292 | DC6: 358.29336 | DD6: 0.0022875399 | DE6: 82.810806 | DF6: 10.383867 | DG6: 142.2545 | DH6: 0 | DI6: 108.61929 | DJ6: 3071.0795 | DK6: 199.29593 | DL6: 0 | DM6: 113.63659 | DN6: 13444.005 | DO6: 42.208621 | DP6: 67014.232 | DQ6: 1.4709237 | DR6: 2852.3357 | DS6: 0 | DT6: 188.82801 | DU6: 0 | DV6: 150928.33 | DW6: 7340.3792 | DX6: 887628.19 | DY6: 195017.34 | DZ6: 7336.1896 | EA6: 1798.5769 | EB6: 3314.8562 | EC6: 2518.3817 | ED6: 18.008437 | EE6: 3251.7782 | EF6: 247.3715 | EG6: 981.81499 | EH6: 19800.614 | EJ6: =C6*$B6 -> 1787744.8 | EK6: =D6*$B6 -> 5307016.7 | EL6: =E6*$B6 -> 2069507.5 | EM6: =F6*$B6 -> 2099874.3 | EN6: =G6*$B6 -> 9094386.7 | EO6: =H6*$B6 -> 8961661.2 | EP6: =I6*$B6 -> 237278.91 | EQ6: =J6*$B6 -> 26013.473 | ... JO6: =EH6*$B6 -> 19812.296
A7: 6 | B7: =OFFSET('ТЗВ всего'!$D$169,0,A7) -> 1.0007539 | C7: 0.94718269 | D7: 43780.901 | E7: 0 | F7: 531.27103 | G7: 152371.33 | H7: 11428.785 | I7: 1731291.9 | J7: 409.18023 | K7: 16105.444 | L7: 263.57189 | M7: 2407.7606 | N7: 0 | O7: 13871.889 | P7: 19324.781 | Q7: 114.05758 | R7: 2.0041973 | S7: 0 | T7: 323.38324 | U7: 398.26832 | V7: 19.734331 | W7: 124.59976 | X7: 5624.2076 | Y7: 336.07804 | Z7: 3.0404782 | AA7: 19.199332 | AB7: 65.185909 | AC7: 0 | AD7: 40.141258 | AE7: 6.5079816 | AF7: 0.0011192136 | AG7: 243.75849 | AH7: 46.369566 | AI7: 249.43589 | AJ7: 476578.11 | AK7: 19052.515 | AL7: 25.371059 | AM7: 0.0066192839 | AN7: 375.07619 | AO7: 2120.1705 | AP7: 214.39509 | AQ7: 4087.2689 | AR7: 8.7430632 | AS7: 280843.03 | AT7: 1873.9242 | AU7: 6691.2818 | AV7: 0.0014804326 | AW7: 18.753236 | AX7: 1245.4828 | AY7: 32106.752 | AZ7: 147.19082 | BA7: 1578.0488 | BB7: 108.88666 | BC7: 67.230137 | BD7: 1111.6371 | BE7: 343.30895 | BF7: 266.86804 | BG7: 7087.399 | BH7: 15582.99 | BI7: 145.21772 | BJ7: 2356.2307 | BK7: 58.537638 | BL7: 18.720016 | BM7: 195.54237 | BN7: 1231.8633 | BO7: 0 | BP7: 1027.5346 | BQ7: 7934.7672 | BR7: 898.1976 | BS7: 57.933721 | BT7: 0.63186009 | BU7: 200.09692 | BV7: 73.207094 | BW7: 3627.1105 | BX7: 5.3944516 | BY7: 3122.7748 | BZ7: 4.810593 | CA7: 283.50446 | CB7: 43.940558 | CC7: 3.893762 | CD7: 226.85677 | CE7: 38422.523 | CF7: 63583.088 | CG7: 257.35785 | CH7: 553.46823 | CI7: 166.07544 | CJ7: 2686.4055 | CK7: 14.369754 | CL7: 0 | CM7: 0 | CN7: 0 | CO7: 361.65027 | CP7: 0.33684408 | CQ7: 0.0071848631 | CR7: 2749.493 | CS7: 0 | CT7: 2171231.2 | CU7: 0 | CV7: 1279.9437 | CW7: 0 | CX7: 0 | CY7: 70.469764 | CZ7: 972.61098 | DA7: 0 | DB7: 0 | DC7: 0 | DD7: 0 | DE7: 0 | DF7: 0 | DG7: 0 | DH7: 0 | DI7: 0 | DJ7: 30259.638 | DK7: 0 | DL7: 0 | DM7: 0 | DN7: 0 | DO7: 0 | DP7: 32.409798 | DQ7: 0 | DR7: 0 | DS7: 0 | DT7: 0 | DU7: 0 | DV7: 15328.63 | DW7: 0 | DX7: 2263.3981 | DY7: 116.65875 | DZ7: 133.0578 | EA7: 0 | EB7: 0 | EC7: 53.827231 | ED7: 0 | EE7: 0 | EF7: 0 | EG7: 0 | EH7: 0 | EJ7: =C7*$B7 -> 0.94789675 | EK7: =D7*$B7 -> 43813.906 | EL7: =E7*$B7 -> 0 | EM7: =F7*$B7 -> 531.67155 | EN7: =G7*$B7 -> 152486.2 | EO7: =H7*$B7 -> 11437.401 | EP7: =I7*$B7 -> 1732597.1 | EQ7: =J7*$B7 -> 409.4887 | ... JO7: =EH7*$B7 -> 0
A8: 7 | B8: =OFFSET('ТЗВ всего'!$D$169,0,A8) -> 1.0006907 | C8: 2102.5842 | D8: 14902.424 | E8: 173.44512 | F8: 625.19464 | G8: 137480.61 | H8: 3706.7959 | I8: 0 | J8: 522740.88 | K8: 0 | L8: 0 | M8: 0 | N8: 0 | O8: 0 | P8: 2.6898905 | Q8: 0 | R8: 404.86228 | S8: 2977.1332 | T8: 8.7726385 | U8: 0.27685499 | V8: 3.8815104 | W8: 1.3696294 | X8: 65.708709 | Y8: 678.89072 | Z8: 0.79392274 | AA8: 32.109845 | AB8: 0.35832433 | AC8: 0 | AD8: 0.00072869242 | AE8: 0.0026425124 | AF8: 0 | AG8: 0 | AH8: 0.75334452 | AI8: 1.1242398 | AJ8: 0 | AK8: 0.49044011 | AL8: 0 | AM8: 0 | AN8: 0 | AO8: 0.038876712 | AP8: 0.0079785414 | AQ8: 0 | AR8: 0.048375916 | AS8: 0 | AT8: 0.37417776 | AU8: 0 | AV8: 0 | AW8: 3.2961274 | AX8: 0 | AY8: 0.00070232887 | AZ8: 0.56896048 | BA8: 2.4652881 | BB8: 0 | BC8: 0 | BD8: 0 | BE8: 0 | BF8: 0 | BG8: 0.0017558222 | BH8: 0.32823525 | BI8: 0 | BJ8: 0 | BK8: 0 | BL8: 0 | BM8: 0.091418354 | BN8: 0 | BO8: 0 | BP8: 0.099611654 | BQ8: 0.0029432318 | BR8: 0 | BS8: 0 | BT8: 0 | BU8: 0 | BV8: 0 | BW8: 0 | BX8: 0 | BY8: 0.27534557 | BZ8: 0 | CA8: 0 | CB8: 0 | CC8: 0.0068645949 | CD8: 0 | CE8: 0.18547202 | CF8: 0.085838283 | CG8: 6.0973262 | CH8: 0 | CI8: 0.048268882 | CJ8: 0.05094104 | CK8: 0 | CL8: 0 | CM8: 0 | CN8: 0 | CO8: 0.031226244 | CP8: 0.017968382 | CQ8: 0 | CR8: 0 | CS8: 0 | CT8: 0 | CU8: 0 | CV8: 0 | CW8: 0 | CX8: 0 | CY8: 548.96076 | CZ8: 28691.799 | DA8: 0 | DB8: 0 | DC8: 0 | DD8: 0 | DE8: 0 | DF8: 0 | DG8: 0 | DH8: 0 | DI8: 0 | DJ8: 0 | DK8: 0 | DL8: 0 | DM8: 0 | DN8: 0 | DO8: 0 | DP8: 0 | DQ8: 0 | DR8: 31.225004 | DS8: 0 | DT8: 0 | DU8: 0 | DV8: 0 | DW8: 128.50523 | DX8: 23.210303 | DY8: 28994.536 | DZ8: 1749.9272 | EA8: 0 | EB8: 205.34822 | EC8: 42.914391 | ED8: 0 | EE8: 759.54353 | EF8: 2.7774659 | EG8: 0 | EH8: 13.410129 | EJ8: =C8*$B8 -> 2104.0364 | EK8: =D8*$B8 -> 14912.717 | EL8: =E8*$B8 -> 173.56492 | EM8: =F8*$B8 -> 625.62645 | EN8: =G8*$B8 -> 137575.56 | EO8: =H8*$B8 -> 3709.3561 | EP8: =I8*$B8 -> 0 | EQ8: =J8*$B8 -> 523101.92 | ... JO8: =EH8*$B8 -> 13.419391
A9: 8 | B9: =OFFSET('ТЗВ всего'!$D$169,0,A9) -> 1.0055924 | C9: 1079.0362 | D9: 1119.3204 | E9: 518.59089 | F9: 0 | G9: 1589.8043 | H9: 838.65864 | I9: 588.12778 | J9: 1650.4031 | K9: 194.5806 | L9: 384.58702 | M9: 3621.9272 | N9: 0 | O9: 126.99008 | P9: 1821.2774 | Q9: 111.51434 | R9: 2.3051828 | S9: 0 | T9: 379.59635 | U9: 876.97641 | V9: 6.0893588 | W9: 133.74576 | X9: 441.90765 | Y9: 14.184245 | Z9: 0.57972612 | AA9: 19.130937 | AB9: 2.4098482 | AC9: 0 | AD9: 301.99018 | AE9: 26.670596 | AF9: 15.933896 | AG9: 249.77958 | AH9: 3634.7251 | AI9: 8.9487758 | AJ9: 1433.6675 | AK9: 58.832672 | AL9: 0.54008879 | AM9: 0 | AN9: 397.18157 | AO9: 729.76376 | AP9: 1148.8495 | AQ9: 6097.1391 | AR9: 1.6420019 | AS9: 73.02147 | AT9: 26.667355 | AU9: 71.41839 | AV9: 1.715842 | AW9: 1.0164806 | AX9: 15.093591 | AY9: 493.05963 | AZ9: 59.821485 | BA9: 378.70794 | BB9: 32.979886 | BC9: 47.692169 | BD9: 184.89817 | BE9: 9079.5259 | BF9: 842.12171 | BG9: 10801.224 | BH9: 915.98815 | BI9: 394.19075 | BJ9: 342.67252 | BK9: 8140.3784 | BL9: 237.94822 | BM9: 291.06645 | BN9: 3117.5184 | BO9: 59.684034 | BP9: 3206.1402 | BQ9: 1066.4587 | BR9: 5.1430062 | BS9: 100.5576 | BT9: 0.17889709 | BU9: 32.848448 | BV9: 0.47542472 | BW9: 11.842728 | BX9: 1.2466266 | BY9: 35.588089 | BZ9: 8.1372446 | CA9: 1.8794692 | CB9: 4.4670596 | CC9: 2.1530538 | CD9: 10.87521 | CE9: 16.03988 | CF9: 71.201939 | CG9: 133.12286 | CH9: 3.0291579 | CI9: 18.246589 | CJ9: 918.01169 | CK9: 829763.7 | CL9: 3.838525 | CM9: 4501.0695 | CN9: 0.19449588 | CO9: 13456.418 | CP9: 25.511619 | CQ9: 2.241884 | CR9: 36.146726 | CS9: 0 | CT9: 104385.56 | CU9: 96052.269 | CV9: 41944.726 | CW9: 34755.861 | CX9: 119.64338 | CY9: 302.33347 | CZ9: 1218.289 | DA9: 0.0037132408 | DB9: 56.269953 | DC9: 2.3601584 | DD9: 0 | DE9: 157.77581 | DF9: 0 | DG9: 351.64159 | DH9: 0 | DI9: 0 | DJ9: 4459.0297 | DK9: 0 | DL9: 0 | DM9: 325.75029 | DN9: 34.12405 | DO9: 121.52047 | DP9: 355.52069 | DQ9: 15.690176 | DR9: 117.49793 | DS9: 0 | DT9: 0 | DU9: 0 | DV9: 236.82303 | DW9: 0 | DX9: 115917.51 | DY9: 437984.52 | DZ9: 31229.041 | EA9: 1395.6716 | EB9: 294.67713 | EC9: 520.88974 | ED9: 1735.5817 | EE9: 2635.0648 | EF9: 136.60363 | EG9: 0 | EH9: 202525.5 | EJ9: =C9*$B9 -> 1085.0706 | EK9: =D9*$B9 -> 1125.5801 | EL9: =E9*$B9 -> 521.49108 | EM9: =F9*$B9 -> 0 | EN9: =G9*$B9 -> 1598.6952 | EO9: =H9*$B9 -> 843.34878 | EP9: =I9*$B9 -> 591.41685 | EQ9: =J9*$B9 -> 1659.6329 | ... JO9: =EH9*$B9 -> 203658.11
A10: 9 | B10: =OFFSET('ТЗВ всего'!$D$169,0,A10) -> 1.0014483 | C10: 0 | D10: 0 | E10: 0 | F10: 0 | G10: 0 | H10: 0 | I10: 0 | J10: 0.046692849 | K10: 0 | L10: 18400.981 | M10: 179266.42 | N10: 0 | O10: 0 | P10: 5172.5133 | Q10: 16.043845 | R10: 0.062983955 | S10: 0 | T10: 27.843271 | U10: 0.43488469 | V10: 0.084995518 | W10: 0.56208423 | X10: 14.809503 | Y10: 0.0007349532 | Z10: 0 | AA10: 0.00041029929 | AB10: 9.9439446e-07 | AC10: 0 | AD10: 5444.3976 | AE10: 51.51664 | AF10: 0 | AG10: 157.30536 | AH10: 90.321357 | AI10: 18.332585 | AJ10: 322.45389 | AK10: 132.5424 | AL10: 3.6903244e-05 | AM10: 140.6687 | AN10: 5120340.6 | AO10: 1226.3129 | AP10: 3.4282807 | AQ10: 297267.03 | AR10: 0.00044472281 | AS10: 331.37277 | AT10: 28.179208 | AU10: 33489.413 | AV10: 4045.1129 | AW10: 0.0075233074 | AX10: 9.7578211 | AY10: 4041.9588 | AZ10: 113.71915 | BA10: 147.93713 | BB10: 2498.248 | BC10: 26981.993 | BD10: 97.721311 | BE10: 1851.2284 | BF10: 550.09071 | BG10: 3561.8518 | BH10: 3859.8365 | BI10: 68.134434 | BJ10: 20445.884 | BK10: 3.5973372 | BL10: 56.090058 | BM10: 7.9717575 | BN10: 336.21403 | BO10: 0 | BP10: 69.155609 | BQ10: 22.092528 | BR10: 175.7616 | BS10: 9.868658 | BT10: 27.882581 | BU10: 0.0089771728 | BV10: 15.370474 | BW10: 0 | BX10: 5.1234912 | BY10: 10.230572 | BZ10: 0 | CA10: 0 | CB10: 0 | CC10: 0 | CD10: 1.8074041 | CE10: 0.39934664 | CF10: 10.625445 | CG10: 1114.1886 | CH10: 24.530848 | CI10: 0.11197262 | CJ10: 317.96102 | CK10: 105506.41 | CL10: 3.0951376 | CM10: 0 | CN10: 0 | CO10: 1492.7044 | CP10: 49.745542 | CQ10: 176.72018 | CR10: 1318.1716 | CS10: 0 | CT10: 0 | CU10: 0 | CV10: 0 | CW10: 0 | CX10: 0 | CY10: 0 | CZ10: 0 | DA10: 0 | DB10: 0 | DC10: 0 | DD10: 0 | DE10: 0 | DF10: 0 | DG10: 0 | DH10: 0 | DI10: 0 | DJ10: 0 | DK10: 0 | DL10: 0 | DM10: 0 | DN10: 0 | DO10: 0 | DP10: 0 | DQ10: 0 | DR10: 0 | DS10: 0 | DT10: 0 | DU10: 0 | DV10: 0 | DW10: 0 | DX10: 0 | DY10: 0 | DZ10: 0 | EA10: 0 | EB10: 0 | EC10: 0 | ED10: 0 | EE10: 0 | EF10: 0 | EG10: 0 | EH10: 0 | EJ10: =C10*$B10 -> 0 | EK10: =D10*$B10 -> 0 | EL10: =E10*$B10 -> 0 | EM10: =F10*$B10 -> 0 | EN10: =G10*$B10 -> 0 | EO10: =H10*$B10 -> 0 | EP10: =I10*$B10 -> 0 | EQ10: =J10*$B10 -> 0.046760473 | ... JO10: =EH10*$B10 -> 0
A11: 10 | B11: =OFFSET('ТЗВ всего'!$D$169,0,A11) -> 1.0014263 | C11: 5813.0059 | D11: 78438.298 | E11: 2047.1003 | F11: 350.90793 | G11: 90891.605 | H11: 48922.312 | I11: 10928.133 | J11: 4446.7747 | K11: 1629.5134 | L11: 444144.04 | M11: 2068624.4 | N11: 0 | O11: 126342.6 | P11: 37120.407 | Q11: 10154.342 | R11: 1518.1161 | S11: 95.535925 | T11: 14357.293 | U11: 12206.358 | V11: 7112.904 | W11: 6730.4068 | X11: 229158.09 | Y11: 20542.087 | Z11: 19484.708 | AA11: 1190.3798 | AB11: 8910.2272 | AC11: 1243.2317 | AD11: 20662.937 | AE11: 5788.3402 | AF11: 7232.4019 | AG11: 10211.143 | AH11: 5610.5548 | AI11: 1767.3893 | AJ11: 2000.6551 | AK11: 8011.1735 | AL11: 77.642142 | AM11: 0.036560325 | AN11: 380843.99 | AO11: 63022.017 | AP11: 179799.3 | AQ11: 227094.66 | AR11: 774.32503 | AS11: 8358.1355 | AT11: 6840.1292 | AU11: 6868.2446 | AV11: 3491.8026 | AW11: 11458.183 | AX11: 2187.2278 | AY11: 17676.395 | AZ11: 594.70206 | BA11: 5179.4911 | BB11: 1918.8608 | BC11: 29454.546 | BD11: 19197.066 | BE11: 113574.53 | BF11: 19775.2 | BG11: 694218.29 | BH11: 457058.05 | BI11: 6931.0629 | BJ11: 39401.47 | BK11: 29491.547 | BL11: 3634.9438 | BM11: 5999.9834 | BN11: 1368337.8 | BO11: 1405.2845 | BP11: 19714.766 | BQ11: 41336.925 | BR11: 5344.8935 | BS11: 1787.4342 | BT11: 1826.903 | BU11: 21694.893 | BV11: 2661.4626 | BW11: 8378.0233 | BX11: 63.205007 | BY11: 3850.8862 | BZ11: 587.10966 | CA11: 318.46941 | CB11: 1016.2606 | CC11: 55.357234 | CD11: 915.02051 | CE11: 5097.7161 | CF11: 7646.6997 | CG11: 4086.5269 | CH11: 1043.2783 | CI11: 1589.0032 | CJ11: 21441.672 | CK11: 3964993.7 | CL11: 29968.321 | CM11: 694.71296 | CN11: 180731.9 | CO11: 871074.23 | CP11: 12848.938 | CQ11: 6594.6712 | CR11: 6343.1223 | CS11: 61.83004 | CT11: 84840.63 | CU11: 1349809.3 | CV11: 2327472.2 | CW11: 41017.32 | CX11: 930.71341 | CY11: 451.99527 | CZ11: 16661.692 | DA11: 850.22363 | DB11: 175.12414 | DC11: 982.2782 | DD11: 851.3249 | DE11: 681.46824 | DF11: 106.22675 | DG11: 7734.3094 | DH11: 2215.665 | DI11: 378.49287 | DJ11: 23394.599 | DK11: 117.8575 | DL11: 53.380874 | DM11: 2976.9398 | DN11: 7563.0684 | DO11: 100.78391 | DP11: 106.65176 | DQ11: 258.74465 | DR11: 50558.944 | DS11: 1411.612 | DT11: 115.77077 | DU11: 0 | DV11: 7405.6409 | DW11: 572.19441 | DX11: 333055.04 | DY11: 358556.11 | DZ11: 67078.725 | EA11: 5293.8795 | EB11: 1105.3813 | EC11: 1478.913 | ED11: 3984.289 | EE11: 10287.124 | EF11: 3380.2995 | EG11: 1712.0864 | EH11: 61664.537 | EJ11: =C11*$B11 -> 5821.2969 | EK11: =D11*$B11 -> 78550.174 | EL11: =E11*$B11 -> 2050.02 | EM11: =F11*$B11 -> 351.40842 | EN11: =G11*$B11 -> 91021.243 | EO11: =H11*$B11 -> 48992.09 | EP11: =I11*$B11 -> 10943.72 | EQ11: =J11*$B11 -> 4453.1171 | ... JO11: =EH11*$B11 -> 61752.488
A12: 11 | B12: =OFFSET('ТЗВ всего'!$D$169,0,A12) -> 1.000899 | C12: 0 | D12: 0 | E12: 0 | F12: 0 | G12: 0 | H12: 0 | I12: 0 | J12: 0 | K12: 0 | L12: 0 | M12: 0.0036906273 | N12: 0 | O12: 0.026903098 | P12: 12.820909 | Q12: 0 | R12: 26.939997 | S12: 0 | T12: 0.0036814352 | U12: 0 | V12: 0.001020212 | W12: 0 | X12: 0.0072840079 | Y12: 0 | Z12: 0 | AA12: 0 | AB12: 0 | AC12: 0 | AD12: 4.094901 | AE12: 0 | AF12: 0 | AG12: 84.645275 | AH12: 0.31484665 | AI12: 0.00099343142 | AJ12: 15.008038 | AK12: 0.059475794 | AL12: 0 | AM12: 0.11866894 | AN12: 3889.7149 | AO12: 200.05066 | AP12: 0 | AQ12: 0.5422959 | AR12: 0 | AS12: 0.00046011563 | AT12: 0 | AU12: 46.602546 | AV12: 0 | AW12: 0 | AX12: 0.23831377 | AY12: 13.655807 | AZ12: 0.0021904353 | BA12: 17.5471 | BB12: 0.31854162 | BC12: 0.1787584 | BD12: 0.0041311807 | BE12: 0.0027769356 | BF12: 0 | BG12: 2.326329 | BH12: 127.24216 | BI12: 2.7642186 | BJ12: 1848.3321 | BK12: 206189.29 | BL12: 5835.447 | BM12: 3615.3819 | BN12: 5749.5132 | BO12: 2298.1145 | BP12: 52965.222 | BQ12: 3576.4044 | BR12: 12.636888 | BS12: 0 | BT12: 0 | BU12: 0.3839284 | BV12: 0.014380736 | BW12: 4.2390108 | BX12: 0 | BY12: 13.564798 | BZ12: 0.076067454 | CA12: 1.5568772 | CB12: 0.0053678457 | CC12: 0 | CD12: 0.1050515 | CE12: 0.00080212132 | CF12: 0.19865152 | CG12: 2.1776427 | CH12: 0 | CI12: 0.00089148169 | CJ12: 25.981047 | CK12: 0 | CL12: 0 | CM12: 0 | CN12: 0 | CO12: 0.023282867 | CP12: 0.060456562 | CQ12: 0.13446984 | CR12: 455.63813 | CS12: 0 | CT12: 0 | CU12: 0 | CV12: 0 | CW12: 0 | CX12: 0 | CY12: 0 | CZ12: 0 | DA12: 0 | DB12: 0 | DC12: 0 | DD12: 0 | DE12: 0 | DF12: 0 | DG12: 0 | DH12: 0 | DI12: 0 | DJ12: 0 | DK12: 0 | DL12: 0 | DM12: 0 | DN12: 0 | DO12: 0 | DP12: 0 | DQ12: 0 | DR12: 0 | DS12: 0 | DT12: 0 | DU12: 0 | DV12: 0 | DW12: 0 | DX12: 0 | DY12: 0 | DZ12: 0 | EA12: 0 | EB12: 0 | EC12: 0 | ED12: 0 | EE12: 0 | EF12: 0 | EG12: 0 | EH12: 0 | EJ12: =C12*$B12 -> 0 | EK12: =D12*$B12 -> 0 | EL12: =E12*$B12 -> 0 | EM12: =F12*$B12 -> 0 | EN12: =G12*$B12 -> 0 | EO12: =H12*$B12 -> 0 | EP12: =I12*$B12 -> 0 | EQ12: =J12*$B12 -> 0 | ... JO12: =EH12*$B12 -> 0
A13: 12 | B13: =OFFSET('ТЗВ всего'!$D$169,0,A13) -> 1.0008894 | C13: 0 | D13: 0 | E13: 0 | F13: 0 | G13: 0 | H13: 0 | I13: 0 | J13: 3.6005275e-05 | K13: 0 | L13: 0 | M13: 0.054859783 | N13: 153.03177 | O13: 196929.54 | P13: 489.48563 | Q13: 0.012371553 | R13: 0.091945953 | S13: 0 | T13: 0.080607241 | U13: 0.012307641 | V13: 66.935491 | W13: 0.30304243 | X13: 0.61676816 | Y13: 6.2890773e-05 | Z13: 0 | AA13: 0.032414268 | AB13: 0.0074958306 | AC13: 0 | AD13: 0.0010255967 | AE13: 0.38729164 | AF13: 0 | AG13: 21.133876 | AH13: 4.4459845 | AI13: 282.23301 | AJ13: 1.8177901 | AK13: 1.0270558 | AL13: 0.19575769 | AM13: 0 | AN13: 0.0057911853 | AO13: 9577.4287 | AP13: 0.62020365 | AQ13: 9.5007053 | AR13: 0.007128474 | AS13: 0.18985249 | AT13: 0.00048681669 | AU13: 580.12503 | AV13: 0.061720638 | AW13: 0.0031577967 | AX13: 8.0952314 | AY13: 382.47863 | AZ13: 20.137988 | BA13: 2081.0739 | BB13: 7.3438301 | BC13: 3.0240605 | BD13: 74.783528 | BE13: 50.062812 | BF13: 9.6514643 | BG13: 15173.99 | BH13: 11.951598 | BI13: 5.5482111 | BJ13: 120.85546 | BK13: 644.07972 | BL13: 228.18913 | BM13: 5196.7092 | BN13: 11062765 | BO13: 1592.8693 | BP13: 16950.169 | BQ13: 1300.8961 | BR13: 0.23386793 | BS13: 48.808365 | BT13: 0 | BU13: 121602.14 | BV13: 0.27217045 | BW13: 66.112621 | BX13: 0.0012522788 | BY13: 8828.0353 | BZ13: 3.6541338 | CA13: 0.97652704 | CB13: 1.7372553 | CC13: 0.53154459 | CD13: 16.798073 | CE13: 14.46792 | CF13: 919.54418 | CG13: 7.6859311 | CH13: 1.4776756 | CI13: 0.015079816 | CJ13: 30.340334 | CK13: 0.022301228 | CL13: 0 | CM13: 0 | CN13: 0 | CO13: 816.61683 | CP13: 7257.208 | CQ13: 84.866744 | CR13: 61.972243 | CS13: 0 | CT13: 0 | CU13: 0 | CV13: 0 | CW13: 0 | CX13: 0 | CY13: 0 | CZ13: 0 | DA13: 0 | DB13: 0 | DC13: 0 | DD13: 0 | DE13: 0 | DF13: 0 | DG13: 0 | DH13: 0 | DI13: 0 | DJ13: 0 | DK13: 0 | DL13: 0 | DM13: 0 | DN13: 0 | DO13: 0 | DP13: 0 | DQ13: 0 | DR13: 0 | DS13: 0 | DT13: 0 | DU13: 0 | DV13: 0 | DW13: 0 | DX13: 0 | DY13: 0 | DZ13: 0 | EA13: 0 | EB13: 0 | EC13: 0 | ED13: 0 | EE13: 0 | EF13: 0 | EG13: 0 | EH13: 0 | EJ13: =C13*$B13 -> 0 | EK13: =D13*$B13 -> 0 | EL13: =E13*$B13 -> 0 | EM13: =F13*$B13 -> 0 | EN13: =G13*$B13 -> 0 | EO13: =H13*$B13 -> 0 | EP13: =I13*$B13 -> 0 | EQ13: =J13*$B13 -> 3.6037298e-05 | ... JO13: =EH13*$B13 -> 0
... A136: 135 | B136: =OFFSET('ТЗВ всего'!$D$169,0,A136) -> 1.0005627 | C136: 16.619956 | D136: 0 | E136: 2.3498604 | F136: 0 | G136: 0 | H136: 0 | I136: 0 | J136: 0 | K136: 0 | L136: 0 | M136: 0 | N136: 0 | O136: 0.11867047 | P136: 2.9996952 | Q136: 0.045218222 | R136: 1.5517789 | S136: 0 | T136: 0.27159731 | U136: 1.840842 | V136: 0.045231761 | W136: 0.053314945 | X136: 0.93939663 | Y136: 0.024389965 | Z136: 0 | AA136: 0 | AB136: 0.079412948 | AC136: 0 | AD136: 214.11478 | AE136: 159.7933 | AF136: 6.1136179 | AG136: 3875.2148 | AH136: 480.85715 | AI136: 10.141151 | AJ136: 0.56209953 | AK136: 11.675313 | AL136: 9.4205889 | AM136: 0 | AN136: 0.077829973 | AO136: 2.0332872 | AP136: 0.00045832144 | AQ136: 0.46222231 | AR136: 0 | AS136: 1.3916378 | AT136: 0.25219391 | AU136: 3.6859885 | AV136: 27.389962 | AW136: 0.42820046 | AX136: 36.364344 | AY136: 30.066157 | AZ136: 3.8579361 | BA136: 4.1779903 | BB136: 15.470953 | BC136: 1.8260625 | BD136: 1.0408985 | BE136: 0.28174893 | BF136: 0.041051407 | BG136: 0.0065481436 | BH136: 1.8202029 | BI136: 0.62567543 | BJ136: 0.2171269 | BK136: 5.2592385e-05 | BL136: 5.5440034 | BM136: 0.060291818 | BN136: 2.1115314 | BO136: 0.17579707 | BP136: 11.663963 | BQ136: 26.531663 | BR136: 0.79464512 | BS136: 0.20980166 | BT136: 0 | BU136: 0 | BV136: 0.12377991 | BW136: 0.088459262 | BX136: 1.6160455 | BY136: 11.601558 | BZ136: 29.841433 | CA136: 7.7096203 | CB136: 4.0967681 | CC136: 0.014012861 | CD136: 8148.8867 | CE136: 12.048573 | CF136: 16.655726 | CG136: 524.70962 | CH136: 0.013170831 | CI136: 17.38809 | CJ136: 7.3705059 | CK136: 4587.8948 | CL136: 0 | CM136: 0 | CN136: 0.00046423378 | CO136: 54.912662 | CP136: 0 | CQ136: 0 | CR136: 2.7313168 | CS136: 0 | CT136: 0 | CU136: 18.564668 | CV136: 0 | CW136: 0 | CX136: 0 | CY136: 0 | CZ136: 0 | DA136: 0 | DB136: 0 | DC136: 0 | DD136: 0 | DE136: 0 | DF136: 0 | DG136: 0 | DH136: 0 | DI136: 0 | DJ136: 0 | DK136: 0 | DL136: 0 | DM136: 0 | DN136: 100.07398 | DO136: 0 | DP136: 0 | DQ136: 0 | DR136: 0 | DS136: 0 | DT136: 0 | DU136: 0 | DV136: 0 | DW136: 8560.3261 | DX136: 26716.335 | DY136: 6106.0793 | DZ136: 2673.3167 | EA136: 0 | EB136: 241.95564 | EC136: 251.2936 | ED136: 59.302046 | EE136: 402.55135 | EF136: 0.58643784 | EG136: 0 | EH136: 0 | EJ136: =C136*$B136 -> 16.629308 | EK136: =D136*$B136 -> 0 | EL136: =E136*$B136 -> 2.3511827 | EM136: =F136*$B136 -> 0 | EN136: =G136*$B136 -> 0 | EO136: =H136*$B136 -> 0 | EP136: =I136*$B136 -> 0 | EQ136: =J136*$B136 -> 0 | ... JO136: =EH136*$B136 -> 0
EJ137: =SUM(EJ1:EJ136) -> 12054912 | EK137: =SUM(EK1:EK136) -> 23798013 | EL137: =SUM(EL1:EL136) -> 9192745.6 | EM137: =SUM(EM1:EM136) -> 4861781.7 | EN137: =SUM(EN1:EN136) -> 63841658 | EO137: =SUM(EO1:EO136) -> 20765224 | EP137: =SUM(EP1:EP136) -> 2408918.9 | EQ137: =SUM(EQ1:EQ136) -> 1196335.3 | ... JO137: =SUM(JO1:JO136) -> 2884294.2

Sheet secondary effect
A1: 0 | B1: ='ТЗВ всего'!D171 -> 1.1110558 | C1: ='primary effect'!EJ1 -> 4496435.9 | D1: ='primary effect'!EK1 -> 935175.54 | E1: ='primary effect'!EL1 -> 1126480.3 | F1: ='primary effect'!EM1 -> 802783.51 | G1: ='primary effect'!EN1 -> 4700946 | H1: ='primary effect'!EO1 -> 1264758.2 | I1: ='primary effect'!EP1 -> 472.05267 | J1: ='primary effect'!EQ1 -> 113238.74 | ... EH1: ='primary effect'!JO1 -> 67.492405 | EJ1: =$B1*C1 -> 4995791.2 | EK1: =$B1*D1 -> 1039032.2 | EL1: =$B1*E1 -> 1251582.4 | EM1: =$B1*F1 -> 891937.28 | EN1: =$B1*G1 -> 5223013.4 | EO1: =$B1*H1 -> 1405217 | EP1: =$B1*I1 -> 524.47686 | EQ1: =$B1*J1 -> 125814.56 | ... JO1: =$B1*EH1 -> 74.987829
A2: 1 | B2: =OFFSET('ТЗВ всего'!$D$171,0,'secondary effect'!A2) -> 1.0986601 | C2: ='primary effect'!EJ2 -> 756230.31 | D2: ='primary effect'!EK2 -> 13303325 | E2: ='primary effect'!EL2 -> 1264563.2 | F2: ='primary effect'!EM2 -> 628003.04 | G2: ='primary effect'!EN2 -> 371533.13 | H2: ='primary effect'!EO2 -> 2519756.1 | I2: ='primary effect'!EP2 -> 3252.6232 | J2: ='primary effect'!EQ2 -> 250.45872 | ... EH2: ='primary effect'!JO2 -> 2848.0471 | EJ2: =$B2*C2 -> 830840.05 | EK2: =$B2*D2 -> 14615832 | EL2: =$B2*E2 -> 1389325.2 | EM2: =$B2*F2 -> 689961.87 | EN2: =$B2*G2 -> 408188.61 | EO2: =$B2*H2 -> 2768355.4 | EP2: =$B2*I2 -> 3573.5272 | EQ2: =$B2*J2 -> 275.16899 | ... JO2: =$B2*EH2 -> 3129.0357
A3: 2 | B3: =OFFSET('ТЗВ всего'!$D$171,0,'secondary effect'!A3) -> 1.102978 | C3: ='primary effect'!EJ3 -> 1212248 | D3: ='primary effect'!EK3 -> 17932.959 | E3: ='primary effect'!EL3 -> 648460.94 | F3: ='primary effect'!EM3 -> 0 | G3: ='primary effect'!EN3 -> 0 | H3: ='primary effect'!EO3 -> 4949.6456 | I3: ='primary effect'!EP3 -> 0 | J3: ='primary effect'!EQ3 -> 0 | ... EH3: ='primary effect'!JO3 -> 0 | EJ3: =$B3*C3 -> 1337082.9 | EK3: =$B3*D3 -> 19779.658 | EL3: =$B3*E3 -> 715238.13 | EM3: =$B3*F3 -> 0 | EN3: =$B3*G3 -> 0 | EO3: =$B3*H3 -> 5459.35 | EP3: =$B3*I3 -> 0 | EQ3: =$B3*J3 -> 0 | ... JO3: =$B3*EH3 -> 0
A4: 3 | B4: =OFFSET('ТЗВ всего'!$D$171,0,'secondary effect'!A4) -> 1.0987492 | C4: ='primary effect'!EJ4 -> 16781.808 | D4: ='primary effect'!EK4 -> 232200.01 | E4: ='primary effect'!EL4 -> 87.240277 | F4: ='primary effect'!EM4 -> 336257.06 | G4: ='primary effect'!EN4 -> 20671.532 | H4: ='primary effect'!EO4 -> 152247.99 | I4: ='primary effect'!EP4 -> 0 | J4: ='primary effect'!EQ4 -> 156.66062 | ... EH4: ='primary effect'!JO4 -> 2.9021088 | EJ4: =$B4*C4 -> 18438.998 | EK4: =$B4*D4 -> 255129.57 | EL4: =$B4*E4 -> 95.855184 | EM4: =$B4*F4 -> 369462.17 | EN4: =$B4*G4 -> 22712.829 | EO4: =$B4*H4 -> 167282.36 | EP4: =$B4*I4 -> 0 | EQ4: =$B4*J4 -> 172.13073 | ... JO4: =$B4*EH4 -> 3.1886897
A5: 4 | B5: =OFFSET('ТЗВ всего'!$D$171,0,'secondary effect'!A5) -> 1.0978165 | C5: ='primary effect'!EJ5 -> 627218.63 | D5: ='primary effect'!EK5 -> 500151.21 | E5: ='primary effect'!EL5 -> 27387.379 | F5: ='primary effect'!EM5 -> 199057.81 | G5: ='primary effect'!EN5 -> 34106012 | H5: ='primary effect'!EO5 -> 1221066.5 | I5: ='primary effect'!EP5 -> 11608.885 | J5: ='primary effect'!EQ5 -> 23989.33 | ... EH5: ='primary effect'!JO5 -> 0 | EJ5: =$B5*C5 -> 688570.95 | EK5: =$B5*D5 -> 549074.24 | EL5: =$B5*E5 -> 30066.316 | EM5: =$B5*F5 -> 218528.95 | EN5: =$B5*G5 -> 37442142 | EO5: =$B5*H5 -> 1340506.9 | EP5: =$B5*I5 -> 12744.426 | EQ5: =$B5*J5 -> 26335.882 | ... JO5: =$B5*EH5 -> 0
A6: 5 | B6: =OFFSET('ТЗВ всего'!$D$171,0,'secondary effect'!A6) -> 1.1042751 | C6: ='primary effect'!EJ6 -> 1787744.8 | D6: ='primary effect'!EK6 -> 5307016.7 | E6: ='primary effect'!EL6 -> 2069507.5 | F6: ='primary effect'!EM6 -> 2099874.3 | G6: ='primary effect'!EN6 -> 9094386.7 | H6: ='primary effect'!EO6 -> 8961661.2 | I6: ='primary effect'!EP6 -> 237278.91 | J6: ='primary effect'!EQ6 -> 26013.473 | ... EH6: ='primary effect'!JO6 -> 19812.296 | EJ6: =$B6*C6 -> 1974162 | EK6: =$B6*D6 -> 5860406.4 | EL6: =$B6*E6 -> 2285305.6 | EM6: =$B6*F6 -> 2318838.9 | EN6: =$B6*G6 -> 10042705 | EO6: =$B6*H6 -> 9896139.4 | EP6: =$B6*I6 -> 262021.2 | EQ6: =$B6*J6 -> 28726.031 | ... JO6: =$B6*EH6 -> 21878.225
A7: 6 | B7: =OFFSET('ТЗВ всего'!$D$171,0,'secondary effect'!A7) -> 1.0676272 | C7: ='primary effect'!EJ7 -> 0.94789675 | D7: ='primary effect'!EK7 -> 43813.906 | E7: ='primary effect'!EL7 -> 0 | F7: ='primary effect'!EM7 -> 531.67155 | G7: ='primary effect'!EN7 -> 152486.2 | H7: ='primary effect'!EO7 -> 11437.401 | I7: ='primary effect'!EP7 -> 1732597.1 | J7: ='primary effect'!EQ7 -> 409.4887 | ... EH7: ='primary effect'!JO7 -> 0 | EJ7: =$B7*C7 -> 1.0120004 | EK7: =$B7*D7 -> 46776.92 | EL7: =$B7*E7 -> 0 | EM7: =$B7*F7 -> 567.62702 | EN7: =$B7*G7 -> 162798.42 | EO7: =$B7*H7 -> 12210.881 | EP7: =$B7*I7 -> 1849767.8 | EQ7: =$B7*J7 -> 437.18129 | ... JO7: =$B7*EH7 -> 0
A8: 7 | B8: =OFFSET('ТЗВ всего'!$D$171,0,'secondary effect'!A8) -> 1.1122305 | C8: ='primary effect'!EJ8 -> 2104.0364 | D8: ='primary effect'!EK8 -> 14912.717 | E8: ='primary effect'!EL8 -> 173.56492 | F8: ='primary effect'!EM8 -> 625.62645 | G8: ='primary effect'!EN8 -> 137575.56 | H8: ='primary effect'!EO8 -> 3709.3561 | I8: ='primary effect'!EP8 -> 0 | J8: ='primary effect'!EQ8 -> 523101.92 | ... EH8: ='primary effect'!JO8 -> 13.419391 | EJ8: =$B8*C8 -> 2340.1735 | EK8: =$B8*D8 -> 16586.379 | EL8: =$B8*E8 -> 193.0442 | EM8: =$B8*F8 -> 695.84082 | EN8: =$B8*G8 -> 153015.74 | EO8: =$B8*H8 -> 4125.6591 | EP8: =$B8*I8 -> 0 | EQ8: =$B8*J8 -> 581809.92 | ... JO8: =$B8*EH8 -> 14.925456
A9: 8 | B9: =OFFSET('ТЗВ всего'!$D$171,0,'secondary effect'!A9) -> 1.0943772 | C9: ='primary effect'!EJ9 -> 1085.0706 | D9: ='primary effect'!EK9 -> 1125.5801 | E9: ='primary effect'!EL9 -> 521.49108 | F9: ='primary effect'!EM9 -> 0 | G9: ='primary effect'!EN9 -> 1598.6952 | H9: ='primary effect'!EO9 -> 843.34878 | I9: ='primary effect'!EP9 -> 591.41685 | J9: ='primary effect'!EQ9 -> 1659.6329 | ... EH9: ='primary effect'!JO9 -> 203658.11 | EJ9: =$B9*C9 -> 1187.4766 | EK9: =$B9*D9 -> 1231.8093 | EL9: =$B9*E9 -> 570.70797 | EM9: =$B9*F9 -> 0 | EN9: =$B9*G9 -> 1749.5756 | EO9: =$B9*H9 -> 922.94172 | EP9: =$B9*I9 -> 647.23314 | EQ9: =$B9*J9 -> 1816.2645 | ... JO9: =$B9*EH9 -> 222878.8
A10: 9 | B10: =OFFSET('ТЗВ всего'!$D$171,0,'secondary effect'!A10) -> 1.0640698 | C10: ='primary effect'!EJ10 -> 0 | D10: ='primary effect'!EK10 -> 0 | E10: ='primary effect'!EL10 -> 0 | F10: ='primary effect'!EM10 -> 0 | G10: ='primary effect'!EN10 -> 0 | H10: ='primary effect'!EO10 -> 0 | I10: ='primary effect'!EP10 -> 0 | J10: ='primary effect'!EQ10 -> 0.046760473 | ... EH10: ='primary effect'!JO10 -> 0 | EJ10: =$B10*C10 -> 0 | EK10: =$B10*D10 -> 0 | EL10: =$B10*E10 -> 0 | EM10: =$B10*F10 -> 0 | EN10: =$B10*G10 -> 0 | EO10: =$B10*H10 -> 0 | EP10: =$B10*I10 -> 0 | EQ10: =$B10*J10 -> 0.049756407 | ... JO10: =$B10*EH10 -> 0
A11: 10 | B11: =OFFSET('ТЗВ всего'!$D$171,0,'secondary effect'!A11) -> 1.070252 | C11: ='primary effect'!EJ11 -> 5821.2969 | D11: ='primary effect'!EK11 -> 78550.174 | E11: ='primary effect'!EL11 -> 2050.02 | F11: ='primary effect'!EM11 -> 351.40842 | G11: ='primary effect'!EN11 -> 91021.243 | H11: ='primary effect'!EO11 -> 48992.09 | I11: ='primary effect'!EP11 -> 10943.72 | J11: ='primary effect'!EQ11 -> 4453.1171 | ... EH11: ='primary effect'!JO11 -> 61752.488 | EJ11: =$B11*C11 -> 6230.2544 | EK11: =$B11*D11 -> 84068.477 | EL11: =$B11*E11 -> 2194.0379 | EM11: =$B11*F11 -> 376.09555 | EN11: =$B11*G11 -> 97415.663 | EO11: =$B11*H11 -> 52433.88 | EP11: =$B11*I11 -> 11712.538 | EQ11: =$B11*J11 -> 4765.9573 | ... JO11: =$B11*EH11 -> 66090.721
A12: 11 | B12: =OFFSET('ТЗВ всего'!$D$171,0,'secondary effect'!A12) -> 1.0860069 | C12: ='primary effect'!EJ12 -> 0 | D12: ='primary effect'!EK12 -> 0 | E12: ='primary effect'!EL12 -> 0 | F12: ='primary effect'!EM12 -> 0 | G12: ='primary effect'!EN12 -> 0 | H12: ='primary effect'!EO12 -> 0 | I12: ='primary effect'!EP12 -> 0 | J12: ='primary effect'!EQ12 -> 0 | ... EH12: ='primary effect'!JO12 -> 0 | EJ12: =$B12*C12 -> 0 | EK12: =$B12*D12 -> 0 | EL12: =$B12*E12 -> 0 | EM12: =$B12*F12 -> 0 | EN12: =$B12*G12 -> 0 | EO12: =$B12*H12 -> 0 | EP12: =$B12*I12 -> 0 | EQ12: =$B12*J12 -> 0 | ... JO12: =$B12*EH12 -> 0
A13: 12 | B13: =OFFSET('ТЗВ всего'!$D$171,0,'secondary effect'!A13) -> 1.0823829 | C13: ='primary effect'!EJ13 -> 0 | D13: ='primary effect'!EK13 -> 0 | E13: ='primary effect'!EL13 -> 0 | F13: ='primary effect'!EM13 -> 0 | G13: ='primary effect'!EN13 -> 0 | H13: ='primary effect'!EO13 -> 0 | I13: ='primary effect'!EP13 -> 0 | J13: ='primary effect'!EQ13 -> 3.6037298e-05 | ... EH13: ='primary effect'!JO13 -> 0 | EJ13: =$B13*C13 -> 0 | EK13: =$B13*D13 -> 0 | EL13: =$B13*E13 -> 0 | EM13: =$B13*F13 -> 0 | EN13: =$B13*G13 -> 0 | EO13: =$B13*H13 -> 0 | EP13: =$B13*I13 -> 0 | EQ13: =$B13*J13 -> 3.9006156e-05 | ... JO13: =$B13*EH13 -> 0
... A136: 135 | B136: =OFFSET('ТЗВ всего'!$D$171,0,'secondary effect'!A136) -> 1.0992594 | C136: ='primary effect'!EJ136 -> 16.629308 | D136: ='primary effect'!EK136 -> 0 | E136: ='primary effect'!EL136 -> 2.3511827 | F136: ='primary effect'!EM136 -> 0 | G136: ='primary effect'!EN136 -> 0 | H136: ='primary effect'!EO136 -> 0 | I136: ='primary effect'!EP136 -> 0 | J136: ='primary effect'!EQ136 -> 0 | ... EH136: ='primary effect'!JO136 -> 0 | EJ136: =$B136*C136 -> 18.279924 | EK136: =$B136*D136 -> 0 | EL136: =$B136*E136 -> 2.5845597 | EM136: =$B136*F136 -> 0 | EN136: =$B136*G136 -> 0 | EO136: =$B136*H136 -> 0 | EP136: =$B136*I136 -> 0 | EQ136: =$B136*J136 -> 0 | ... JO136: =$B136*EH136 -> 0
EJ137: =SUM(EJ1:EJ136) -> 13466232 | EK137: =SUM(EK1:EK136) -> 26274388 | EL137: =SUM(EL1:EL136) -> 10356950 | EM137: =SUM(EM1:EM136) -> 5382700.2 | EN137: =SUM(EN1:EN136) -> 71057548 | EO137: =SUM(EO1:EO136) -> 23170092 | EP137: =SUM(EP1:EP136) -> 2608157 | EQ137: =SUM(EQ1:EQ136) -> 1338955.2 | ... JO137: =SUM(JO1:JO136) -> 3187379.9

Sheet tertiary effect
A1: 0 | B1: ='ТЗВ всего'!D173 -> 1.0175459 | C1: ='secondary effect'!EJ1 -> 4995791.2 | D1: ='secondary effect'!EK1 -> 1039032.2 | E1: ='secondary effect'!EL1 -> 1251582.4 | F1: ='secondary effect'!EM1 -> 891937.28 | G1: ='secondary effect'!EN1 -> 5223013.4 | H1: ='secondary effect'!EO1 -> 1405217 | I1: ='secondary effect'!EP1 -> 524.47686 | J1: ='secondary effect'!EQ1 -> 125814.56 | ... EH1: ='secondary effect'!JO1 -> 74.987829 | EJ1: =$B1*C1 -> 5083447 | EK1: =$B1*D1 -> 1057263 | EL1: =$B1*E1 -> 1273542.6 | EM1: =$B1*F1 -> 907587.16 | EN1: =$B1*G1 -> 5314656 | EO1: =$B1*H1 -> 1429872.8 | EP1: =$B1*I1 -> 533.6793 | EQ1: =$B1*J1 -> 128022.09 | ... JO1: =$B1*EH1 -> 76.30356
A2: 1 | B2: =OFFSET('ТЗВ всего'!$D$173,0,'tertiary effect'!A2) -> 1.0140116 | C2: ='secondary effect'!EJ2 -> 830840.05 | D2: ='secondary effect'!EK2 -> 14615832 | E2: ='secondary effect'!EL2 -> 1389325.2 | F2: ='secondary effect'!EM2 -> 689961.87 | G2: ='secondary effect'!EN2 -> 408188.61 | H2: ='secondary effect'!EO2 -> 2768355.4 | I2: ='secondary effect'!EP2 -> 3573.5272 | J2: ='secondary effect'!EQ2 -> 275.16899 | ... EH2: ='secondary effect'!JO2 -> 3129.0357 | EJ2: =$B2*C2 -> 842481.43 | EK2: =$B2*D2 -> 14820622 | EL2: =$B2*E2 -> 1408791.8 | EM2: =$B2*F2 -> 699629.32 | EN2: =$B2*G2 -> 413907.98 | EO2: =$B2*H2 -> 2807144.5 | EP2: =$B2*I2 -> 3623.598 | EQ2: =$B2*J2 -> 279.02455 | ... JO2: =$B2*EH2 -> 3172.8784
A3: 2 | B3: =OFFSET('ТЗВ всего'!$D$173,0,'tertiary effect'!A3) -> 1.0177275 | C3: ='secondary effect'!EJ3 -> 1337082.9 | D3: ='secondary effect'!EK3 -> 19779.658 | E3: ='secondary effect'!EL3 -> 715238.13 | F3: ='secondary effect'!EM3 -> 0 | G3: ='secondary effect'!EN3 -> 0 | H3: ='secondary effect'!EO3 -> 5459.35 | I3: ='secondary effect'!EP3 -> 0 | J3: ='secondary effect'!EQ3 -> 0 | ... EH3: ='secondary effect'!JO3 -> 0 | EJ3: =$B3*C3 -> 1360786 | EK3: =$B3*D3 -> 20130.301 | EL3: =$B3*E3 -> 727917.49 | EM3: =$B3*F3 -> 0 | EN3: =$B3*G3 -> 0 | EO3: =$B3*H3 -> 5556.1304 | EP3: =$B3*I3 -> 0 | EQ3: =$B3*J3 -> 0 | ... JO3: =$B3*EH3 -> 0
A4: 3 | B4: =OFFSET('ТЗВ всего'!$D$173,0,'tertiary effect'!A4) -> 1.0144391 | C4: ='secondary effect'!EJ4 -> 18438.998 | D4: ='secondary effect'!EK4 -> 255129.57 | E4: ='secondary effect'!EL4 -> 95.855184 | F4: ='secondary effect'!EM4 -> 369462.17 | G4: ='secondary effect'!EN4 -> 22712.829 | H4: ='secondary effect'!EO4 -> 167282.36 | I4: ='secondary effect'!EP4 -> 0 | J4: ='secondary effect'!EQ4 -> 172.13073 | ... EH4: ='secondary effect'!JO4 -> 3.1886897 | EJ4: =$B4*C4 -> 18705.241 | EK4: =$B4*D4 -> 258813.42 | EL4: =$B4*E4 -> 97.239249 | EM4: =$B4*F4 -> 374796.88 | EN4: =$B4*G4 -> 23040.782 | EO4: =$B4*H4 -> 169697.77 | EP4: =$B4*I4 -> 0 | EQ4: =$B4*J4 -> 174.61614 | ... JO4: =$B4*EH4 -> 3.2347316
A5: 4 | B5: =OFFSET('ТЗВ всего'!$D$173,0,'tertiary effect'!A5) -> 1.0151006 | C5: ='secondary effect'!EJ5 -> 688570.95 | D5: ='secondary effect'!EK5 -> 549074.24 | E5: ='secondary effect'!EL5 -> 30066.316 | F5: ='secondary effect'!EM5 -> 218528.95 | G5: ='secondary effect'!EN5 -> 37442142 | H5: ='secondary effect'!EO5 -> 1340506.9 | I5: ='secondary effect'!EP5 -> 12744.426 | J5: ='secondary effect'!EQ5 -> 26335.882 | ... EH5: ='secondary effect'!JO5 -> 0 | EJ5: =$B5*C5 -> 698968.79 | EK5: =$B5*D5 -> 557365.59 | EL5: =$B5*E5 -> 30520.336 | EM5: =$B5*F5 -> 221828.87 | EN5: =$B5*G5 -> 38007541 | EO5: =$B5*H5 -> 1360749.4 | EP5: =$B5*I5 -> 12936.874 | EQ5: =$B5*J5 -> 26733.57 | ... JO5: =$B5*EH5 -> 0
A6: 5 | B6: =OFFSET('ТЗВ всего'!$D$173,0,'tertiary effect'!A6) -> 1.0163964 | C6: ='secondary effect'!EJ6 -> 1974162 | D6: ='secondary effect'!EK6 -> 5860406.4 | E6: ='secondary effect'!EL6 -> 2285305.6 | F6: ='secondary effect'!EM6 -> 2318838.9 | G6: ='secondary effect'!EN6 -> 10042705 | H6: ='secondary effect'!EO6 -> 9896139.4 | I6: ='secondary effect'!EP6 -> 262021.2 | J6: ='secondary effect'!EQ6 -> 28726.031 | ... EH6: ='secondary effect'!JO6 -> 21878.225 | EJ6: =$B6*C6 -> 2006531.2 | EK6: =$B6*D6 -> 5956496 | EL6: =$B6*E6 -> 2322776.4 | EM6: =$B6*F6 -> 2356859.6 | EN6: =$B6*G6 -> 10207369 | EO6: =$B6*H6 -> 10058400 | EP6: =$B6*I6 -> 266317.4 | EQ6: =$B6*J6 -> 29197.034 | ... JO6: =$B6*EH6 -> 22236.949
A7: 6 | B7: =OFFSET('ТЗВ всего'!$D$173,0,'tertiary effect'!A7) -> 1.0078547 | C7: ='secondary effect'!EJ7 -> 1.0120004 | D7: ='secondary effect'!EK7 -> 46776.92 | E7: ='secondary effect'!EL7 -> 0 | F7: ='secondary effect'!EM7 -> 567.62702 | G7: ='secondary effect'!EN7 -> 162798.42 | H7: ='secondary effect'!EO7 -> 12210.881 | I7: ='secondary effect'!EP7 -> 1849767.8 | J7: ='secondary effect'!EQ7 -> 437.18129 | ... EH7: ='secondary effect'!JO7 -> 0 | EJ7: =$B7*C7 -> 1.0199493 | EK7: =$B7*D7 -> 47144.338 | EL7: =$B7*E7 -> 0 | EM7: =$B7*F7 -> 572.08556 | EN7: =$B7*G7 -> 164077.15 | EO7: =$B7*H7 -> 12306.793 | EP7: =$B7*I7 -> 1864297.2 | EQ7: =$B7*J7 -> 440.61522 | ... JO7: =$B7*EH7 -> 0
A8: 7 | B8: =OFFSET('ТЗВ всего'!$D$173,0,'tertiary effect'!A8) -> 1.0180345 | C8: ='secondary effect'!EJ8 -> 2340.1735 | D8: ='secondary effect'!EK8 -> 16586.379 | E8: ='secondary effect'!EL8 -> 193.0442 | F8: ='secondary effect'!EM8 -> 695.84082 | G8: ='secondary effect'!EN8 -> 153015.74 | H8: ='secondary effect'!EO8 -> 4125.6591 | I8: ='secondary effect'!EP8 -> 0 | J8: ='secondary effect'!EQ8 -> 581809.92 | ... EH8: ='secondary effect'!JO8 -> 14.925456 | EJ8: =$B8*C8 -> 2382.3772 | EK8: =$B8*D8 -> 16885.505 | EL8: =$B8*E8 -> 196.52564 | EM8: =$B8*F8 -> 708.38993 | EN8: =$B8*G8 -> 155775.29 | EO8: =$B8*H8 -> 4200.0631 | EP8: =$B8*I8 -> 0 | EQ8: =$B8*J8 -> 592302.54 | ... JO8: =$B8*EH8 -> 15.194628
A9: 8 | B9: =OFFSET('ТЗВ всего'!$D$173,0,'tertiary effect'!A9) -> 1.0179254 | C9: ='secondary effect'!EJ9 -> 1187.4766 | D9: ='secondary effect'!EK9 -> 1231.8093 | E9: ='secondary effect'!EL9 -> 570.70797 | F9: ='secondary effect'!EM9 -> 0 | G9: ='secondary effect'!EN9 -> 1749.5756 | H9: ='secondary effect'!EO9 -> 922.94172 | I9: ='secondary effect'!EP9 -> 647.23314 | J9: ='secondary effect'!EQ9 -> 1816.2645 | ... EH9: ='secondary effect'!JO9 -> 222878.8 | EJ9: =$B9*C9 -> 1208.7626 | EK9: =$B9*D9 -> 1253.8899 | EL9: =$B9*E9 -> 580.93813 | EM9: =$B9*F9 -> 0 | EN9: =$B9*G9 -> 1780.9374 | EO9: =$B9*H9 -> 939.48581 | EP9: =$B9*I9 -> 658.83505 | EQ9: =$B9*J9 -> 1848.8217 | ... JO9: =$B9*EH9 -> 226873.99
A10: 9 | B10: =OFFSET('ТЗВ всего'!$D$173,0,'tertiary effect'!A10) -> 1.0102159 | C10: ='secondary effect'!EJ10 -> 0 | D10: ='secondary effect'!EK10 -> 0 | E10: ='secondary effect'!EL10 -> 0 | F10: ='secondary effect'!EM10 -> 0 | G10: ='secondary effect'!EN10 -> 0 | H10: ='secondary effect'!EO10 -> 0 | I10: ='secondary effect'!EP10 -> 0 | J10: ='secondary effect'!EQ10 -> 0.049756407 | ... EH10: ='secondary effect'!JO10 -> 0 | EJ10: =$B10*C10 -> 0 | EK10: =$B10*D10 -> 0 | EL10: =$B10*E10 -> 0 | EM10: =$B10*F10 -> 0 | EN10: =$B10*G10 -> 0 | EO10: =$B10*H10 -> 0 | EP10: =$B10*I10 -> 0 | EQ10: =$B10*J10 -> 0.050264713 | ... JO10: =$B10*EH10 -> 0
A11: 10 | B11: =OFFSET('ТЗВ всего'!$D$173,0,'tertiary effect'!A11) -> 1.0109839 | C11: ='secondary effect'!EJ11 -> 6230.2544 | D11: ='secondary effect'!EK11 -> 84068.477 | E11: ='secondary effect'!EL11 -> 2194.0379 | F11: ='secondary effect'!EM11 -> 376.09555 | G11: ='secondary effect'!EN11 -> 97415.663 | H11: ='secondary effect'!EO11 -> 52433.88 | I11: ='secondary effect'!EP11 -> 11712.538 | J11: ='secondary effect'!EQ11 -> 4765.9573 | ... EH11: ='secondary effect'!JO11 -> 66090.721 | EJ11: =$B11*C11 -> 6298.6868 | EK11: =$B11*D11 -> 84991.875 | EL11: =$B11*E11 -> 2218.137 | EM11: =$B11*F11 -> 380.22654 | EN11: =$B11*G11 -> 98485.665 | EO11: =$B11*H11 -> 53009.808 | EP11: =$B11*I11 -> 11841.187 | EQ11: =$B11*J11 -> 4818.306 | ... JO11: =$B11*EH11 -> 66816.654
A12: 11 | B12: =OFFSET('ТЗВ всего'!$D$173,0,'tertiary effect'!A12) -> 1.0149796 | C12: ='secondary effect'!EJ12 -> 0 | D12: ='secondary effect'!EK12 -> 0 | E12: ='secondary effect'!EL12 -> 0 | F12: ='secondary effect'!EM12 -> 0 | G12: ='secondary effect'!EN12 -> 0 | H12: ='secondary effect'!EO12 -> 0 | I12: ='secondary effect'!EP12 -> 0 | J12: ='secondary effect'!EQ12 -> 0 | ... EH12: ='secondary effect'!JO12 -> 0 | EJ12: =$B12*C12 -> 0 | EK12: =$B12*D12 -> 0 | EL12: =$B12*E12 -> 0 | EM12: =$B12*F12 -> 0 | EN12: =$B12*G12 -> 0 | EO12: =$B12*H12 -> 0 | EP12: =$B12*I12 -> 0 | EQ12: =$B12*J12 -> 0 | ... JO12: =$B12*EH12 -> 0
A13: 12 | B13: =OFFSET('ТЗВ всего'!$D$173,0,'tertiary effect'!A13) -> 1.0156355 | C13: ='secondary effect'!EJ13 -> 0 | D13: ='secondary effect'!EK13 -> 0 | E13: ='secondary effect'!EL13 -> 0 | F13: ='secondary effect'!EM13 -> 0 | G13: ='secondary effect'!EN13 -> 0 | H13: ='secondary effect'!EO13 -> 0 | I13: ='secondary effect'!EP13 -> 0 | J13: ='secondary effect'!EQ13 -> 3.9006156e-05 | ... EH13: ='secondary effect'!JO13 -> 0 | EJ13: =$B13*C13 -> 0 | EK13: =$B13*D13 -> 0 | EL13: =$B13*E13 -> 0 | EM13: =$B13*F13 -> 0 | EN13: =$B13*G13 -> 0 | EO13: =$B13*H13 -> 0 | EP13: =$B13*I13 -> 0 | EQ13: =$B13*J13 -> 3.9616036e-05 | ... JO13: =$B13*EH13 -> 0
... A136: 135 | B136: =OFFSET('ТЗВ всего'!$D$173,0,'tertiary effect'!A136) -> 1.0142194 | C136: ='secondary effect'!EJ136 -> 18.279924 | D136: ='secondary effect'!EK136 -> 0 | E136: ='secondary effect'!EL136 -> 2.5845597 | F136: ='secondary effect'!EM136 -> 0 | G136: ='secondary effect'!EN136 -> 0 | H136: ='secondary effect'!EO136 -> 0 | I136: ='secondary effect'!EP136 -> 0 | J136: ='secondary effect'!EQ136 -> 0 | ... EH136: ='secondary effect'!JO136 -> 0 | EJ136: =$B136*C136 -> 18.539853 | EK136: =$B136*D136 -> 0 | EL136: =$B136*E136 -> 2.6213105 | EM136: =$B136*F136 -> 0 | EN136: =$B136*G136 -> 0 | EO136: =$B136*H136 -> 0 | EP136: =$B136*I136 -> 0 | EQ136: =$B136*J136 -> 0 | ... JO136: =$B136*EH136 -> 0
EJ137: =SUM(EJ1:EJ136) -> 13722108 | EK137: =SUM(EK1:EK136) -> 26685932 | EL137: =SUM(EL1:EL136) -> 10566993 | EM137: =SUM(EM1:EM136) -> 5473445.2 | EN137: =SUM(EN1:EN136) -> 72344727 | EO137: =SUM(EO1:EO136) -> 23605446 | EP137: =SUM(EP1:EP136) -> 2637710.8 | EQ137: =SUM(EQ1:EQ136) -> 1365417.3 | ... JO137: =SUM(JO1:JO136) -> 3246181.9

Sheet quadruple effect
A1: 0 | B1: ='ТЗВ всего'!D175 -> 1.0031263 | C1: ='tertiary effect'!EJ1 -> 5083447 | D1: ='tertiary effect'!EK1 -> 1057263 | E1: ='tertiary effect'!EL1 -> 1273542.6 | F1: ='tertiary effect'!EM1 -> 907587.16 | G1: ='tertiary effect'!EN1 -> 5314656 | H1: ='tertiary effect'!EO1 -> 1429872.8 | I1: ='tertiary effect'!EP1 -> 533.6793 | J1: ='tertiary effect'!EQ1 -> 128022.09 | ... EH1: ='tertiary effect'!JO1 -> 76.30356 | EJ1: =$B1*C1 -> 5099339.3 | EK1: =$B1*D1 -> 1060568.3 | EL1: =$B1*E1 -> 1277524.1 | EM1: =$B1*F1 -> 910424.52 | EN1: =$B1*G1 -> 5331271 | EO1: =$B1*H1 -> 1434343 | EP1: =$B1*I1 -> 535.34772 | EQ1: =$B1*J1 -> 128422.32 | ... JO1: =$B1*EH1 -> 76.542106
A2: 1 | B2: =OFFSET('ТЗВ всего'!$D$175,0,'quadruple effect'!A2) -> 1.0022964 | C2: ='tertiary effect'!EJ2 -> 842481.43 | D2: ='tertiary effect'!EK2 -> 14820622 | E2: ='tertiary effect'!EL2 -> 1408791.8 | F2: ='tertiary effect'!EM2 -> 699629.32 | G2: ='tertiary effect'!EN2 -> 413907.98 | H2: ='tertiary effect'!EO2 -> 2807144.5 | I2: ='tertiary effect'!EP2 -> 3623.598 | J2: ='tertiary effect'!EQ2 -> 279.02455 | ... EH2: ='tertiary effect'!JO2 -> 3172.8784 | EJ2: =$B2*C2 -> 844416.09 | EK2: =$B2*D2 -> 14854656 | EL2: =$B2*E2 -> 1412026.9 | EM2: =$B2*F2 -> 701235.94 | EN2: =$B2*G2 -> 414858.47 | EO2: =$B2*H2 -> 2813590.8 | EP2: =$B2*I2 -> 3631.9192 | EQ2: =$B2*J2 -> 279.66529 | ... JO2: =$B2*EH2 -> 3180.1645
A3: 2 | B3: =OFFSET('ТЗВ всего'!$D$175,0,'quadruple effect'!A3) -> 1.0031426 | C3: ='tertiary effect'!EJ3 -> 1360786 | D3: ='tertiary effect'!EK3 -> 20130.301 | E3: ='tertiary effect'!EL3 -> 727917.49 | F3: ='tertiary effect'!EM3 -> 0 | G3: ='tertiary effect'!EN3 -> 0 | H3: ='tertiary effect'!EO3 -> 5556.1304 | I3: ='tertiary effect'!EP3 -> 0 | J3: ='tertiary effect'!EQ3 -> 0 | ... EH3: ='tertiary effect'!JO3 -> 0 | EJ3: =$B3*C3 -> 1365062.4 | EK3: =$B3*D3 -> 20193.563 | EL3: =$B3*E3 -> 730205.07 | EM3: =$B3*F3 -> 0 | EN3: =$B3*G3 -> 0 | EO3: =$B3*H3 -> 5573.5913 | EP3: =$B3*I3 -> 0 | EQ3: =$B3*J3 -> 0 | ... JO3: =$B3*EH3 -> 0
A4: 3 | B4: =OFFSET('ТЗВ всего'!$D$175,0,'quadruple effect'!A4) -> 1.0024795 | C4: ='tertiary effect'!EJ4 -> 18705.241 | D4: ='tertiary effect'!EK4 -> 258813.42 | E4: ='tertiary effect'!EL4 -> 97.239249 | F4: ='tertiary effect'!EM4 -> 374796.88 | G4: ='tertiary effect'!EN4 -> 23040.782 | H4: ='tertiary effect'!EO4 -> 169697.77 | I4: ='tertiary effect'!EP4 -> 0 | J4: ='tertiary effect'!EQ4 -> 174.61614 | ... EH4: ='tertiary effect'!JO4 -> 3.2347316 | EJ4: =$B4*C4 -> 18751.621 | EK4: =$B4*D4 -> 259455.15 | EL4: =$B4*E4 -> 97.480356 | EM4: =$B4*F4 -> 375726.19 | EN4: =$B4*G4 -> 23097.912 | EO4: =$B4*H4 -> 170118.53 | EP4: =$B4*I4 -> 0 | EQ4: =$B4*J4 -> 175.04911 | ... JO4: =$B4*EH4 -> 3.2427522
A5: 4 | B5: =OFFSET('ТЗВ всего'!$D$175,0,'quadruple effect'!A5) -> 1.0026536 | C5: ='tertiary effect'!EJ5 -> 698968.79 | D5: ='tertiary effect'!EK5 -> 557365.59 | E5: ='tertiary effect'!EL5 -> 30520.336 | F5: ='tertiary effect'!EM5 -> 221828.87 | G5: ='tertiary effect'!EN5 -> 38007541 | H5: ='tertiary effect'!EO5 -> 1360749.4 | I5: ='tertiary effect'!EP5 -> 12936.874 | J5: ='tertiary effect'!EQ5 -> 26733.57 | ... EH5: ='tertiary effect'!JO5 -> 0 | EJ5: =$B5*C5 -> 700823.57 | EK5: =$B5*D5 -> 558844.61 | EL5: =$B5*E5 -> 30601.324 | EM5: =$B5*F5 -> 222417.51 | EN5: =$B5*G5 -> 38108397 | EO5: =$B5*H5 -> 1364360.3 | EP5: =$B5*I5 -> 12971.204 | EQ5: =$B5*J5 -> 26804.51 | ... JO5: =$B5*EH5 -> 0
A6: 5 | B6: =OFFSET('ТЗВ всего'!$D$175,0,'quadruple effect'!A6) -> 1.0029204 | C6: ='tertiary effect'!EJ6 -> 2006531.2 | D6: ='tertiary effect'!EK6 -> 5956496 | E6: ='tertiary effect'!EL6 -> 2322776.4 | F6: ='tertiary effect'!EM6 -> 2356859.6 | G6: ='tertiary effect'!EN6 -> 10207369 | H6: ='tertiary effect'!EO6 -> 10058400 | I6: ='tertiary effect'!EP6 -> 266317.4 | J6: ='tertiary effect'!EQ6 -> 29197.034 | ... EH6: ='tertiary effect'!JO6 -> 22236.949 | EJ6: =$B6*C6 -> 2012391 | EK6: =$B6*D6 -> 5973891.1 | EL6: =$B6*E6 -> 2329559.8 | EM6: =$B6*F6 -> 2363742.4 | EN6: =$B6*G6 -> 10237178 | EO6: =$B6*H6 -> 10087775 | EP6: =$B6*I6 -> 267095.15 | EQ6: =$B6*J6 -> 29282.3 | ... JO6: =$B6*EH6 -> 22301.889
A7: 6 | B7: =OFFSET('ТЗВ всего'!$D$175,0,'quadruple effect'!A7) -> 1.001156 | C7: ='tertiary effect'!EJ7 -> 1.0199493 | D7: ='tertiary effect'!EK7 -> 47144.338 | E7: ='tertiary effect'!EL7 -> 0 | F7: ='tertiary effect'!EM7 -> 572.08556 | G7: ='tertiary effect'!EN7 -> 164077.15 | H7: ='tertiary effect'!EO7 -> 12306.793 | I7: ='tertiary effect'!EP7 -> 1864297.2 | J7: ='tertiary effect'!EQ7 -> 440.61522 | ... EH7: ='tertiary effect'!JO7 -> 0 | EJ7: =$B7*C7 -> 1.0211284 | EK7: =$B7*D7 -> 47198.839 | EL7: =$B7*E7 -> 0 | EM7: =$B7*F7 -> 572.74692 | EN7: =$B7*G7 -> 164266.83 | EO7: =$B7*H7 -> 12321.02 | EP7: =$B7*I7 -> 1866452.4 | EQ7: =$B7*J7 -> 441.12458 | ... JO7: =$B7*EH7 -> 0
A8: 7 | B8: =OFFSET('ТЗВ всего'!$D$175,0,'quadruple effect'!A8) -> 1.0032869 | C8: ='tertiary effect'!EJ8 -> 2382.3772 | D8: ='tertiary effect'!EK8 -> 16885.505 | E8: ='tertiary effect'!EL8 -> 196.52564 | F8: ='tertiary effect'!EM8 -> 708.38993 | G8: ='tertiary effect'!EN8 -> 155775.29 | H8: ='tertiary effect'!EO8 -> 4200.0631 | I8: ='tertiary effect'!EP8 -> 0 | J8: ='tertiary effect'!EQ8 -> 592302.54 | ... EH8: ='tertiary effect'!JO8 -> 15.194628 | EJ8: =$B8*C8 -> 2390.2078 | EK8: =$B8*D8 -> 16941.006 | EL8: =$B8*E8 -> 197.1716 | EM8: =$B8*F8 -> 710.71833 | EN8: =$B8*G8 -> 156287.31 | EO8: =$B8*H8 -> 4213.8682 | EP8: =$B8*I8 -> 0 | EQ8: =$B8*J8 -> 594249.37 | ... JO8: =$B8*EH8 -> 15.244571
A9: 8 | B9: =OFFSET('ТЗВ всего'!$D$175,0,'quadruple effect'!A9) -> 1.0032277 | C9: ='tertiary effect'!EJ9 -> 1208.7626 | D9: ='tertiary effect'!EK9 -> 1253.8899 | E9: ='tertiary effect'!EL9 -> 580.93813 | F9: ='tertiary effect'!EM9 -> 0 | G9: ='tertiary effect'!EN9 -> 1780.9374 | H9: ='tertiary effect'!EO9 -> 939.48581 | I9: ='tertiary effect'!EP9 -> 658.83505 | J9: ='tertiary effect'!EQ9 -> 1848.8217 | ... EH9: ='tertiary effect'!JO9 -> 226873.99 | EJ9: =$B9*C9 -> 1212.6641 | EK9: =$B9*D9 -> 1257.9372 | EL9: =$B9*E9 -> 582.81325 | EM9: =$B9*F9 -> 0 | EN9: =$B9*G9 -> 1786.6858 | EO9: =$B9*H9 -> 942.51822 | EP9: =$B9*I9 -> 660.96159 | EQ9: =$B9*J9 -> 1854.7892 | ... JO9: =$B9*EH9 -> 227606.28
A10: 9 | B10: =OFFSET('ТЗВ всего'!$D$175,0,'quadruple effect'!A10) -> 1.0019406 | C10: ='tertiary effect'!EJ10 -> 0 | D10: ='tertiary effect'!EK10 -> 0 | E10: ='tertiary effect'!EL10 -> 0 | F10: ='tertiary effect'!EM10 -> 0 | G10: ='tertiary effect'!EN10 -> 0 | H10: ='tertiary effect'!EO10 -> 0 | I10: ='tertiary effect'!EP10 -> 0 | J10: ='tertiary effect'!EQ10 -> 0.050264713 | ... EH10: ='tertiary effect'!JO10 -> 0 | EJ10: =$B10*C10 -> 0 | EK10: =$B10*D10 -> 0 | EL10: =$B10*E10 -> 0 | EM10: =$B10*F10 -> 0 | EN10: =$B10*G10 -> 0 | EO10: =$B10*H10 -> 0 | EP10: =$B10*I10 -> 0 | EQ10: =$B10*J10 -> 0.050362255 | ... JO10: =$B10*EH10 -> 0
A11: 10 | B11: =OFFSET('ТЗВ всего'!$D$175,0,'quadruple effect'!A11) -> 1.0020652 | C11: ='tertiary effect'!EJ11 -> 6298.6868 | D11: ='tertiary effect'!EK11 -> 84991.875 | E11: ='tertiary effect'!EL11 -> 2218.137 | F11: ='tertiary effect'!EM11 -> 380.22654 | G11: ='tertiary effect'!EN11 -> 98485.665 | H11: ='tertiary effect'!EO11 -> 53009.808 | I11: ='tertiary effect'!EP11 -> 11841.187 | J11: ='tertiary effect'!EQ11 -> 4818.306 | ... EH11: ='tertiary effect'!JO11 -> 66816.654 | EJ11: =$B11*C11 -> 6311.6949 | EK11: =$B11*D11 -> 85167.401 | EL11: =$B11*E11 -> 2222.7179 | EM11: =$B11*F11 -> 381.01179 | EN11: =$B11*G11 -> 98689.058 | EO11: =$B11*H11 -> 53119.284 | EP11: =$B11*I11 -> 11865.641 | EQ11: =$B11*J11 -> 4828.2568 | ... JO11: =$B11*EH11 -> 66954.644
A12: 11 | B12: =OFFSET('ТЗВ всего'!$D$175,0,'quadruple effect'!A12) -> 1.002945 | C12: ='tertiary effect'!EJ12 -> 0 | D12: ='tertiary effect'!EK12 -> 0 | E12: ='tertiary effect'!EL12 -> 0 | F12: ='tertiary effect'!EM12 -> 0 | G12: ='tertiary effect'!EN12 -> 0 | H12: ='tertiary effect'!EO12 -> 0 | I12: ='tertiary effect'!EP12 -> 0 | J12: ='tertiary effect'!EQ12 -> 0 | ... EH12: ='tertiary effect'!JO12 -> 0 | EJ12: =$B12*C12 -> 0 | EK12: =$B12*D12 -> 0 | EL12: =$B12*E12 -> 0 | EM12: =$B12*F12 -> 0 | EN12: =$B12*G12 -> 0 | EO12: =$B12*H12 -> 0 | EP12: =$B12*I12 -> 0 | EQ12: =$B12*J12 -> 0 | ... JO12: =$B12*EH12 -> 0
A13: 12 | B13: =OFFSET('ТЗВ всего'!$D$175,0,'quadruple effect'!A13) -> 1.0029163 | C13: ='tertiary effect'!EJ13 -> 0 | D13: ='tertiary effect'!EK13 -> 0 | E13: ='tertiary effect'!EL13 -> 0 | F13: ='tertiary effect'!EM13 -> 0 | G13: ='tertiary effect'!EN13 -> 0 | H13: ='tertiary effect'!EO13 -> 0 | I13: ='tertiary effect'!EP13 -> 0 | J13: ='tertiary effect'!EQ13 -> 3.9616036e-05 | ... EH13: ='tertiary effect'!JO13 -> 0 | EJ13: =$B13*C13 -> 0 | EK13: =$B13*D13 -> 0 | EL13: =$B13*E13 -> 0 | EM13: =$B13*F13 -> 0 | EN13: =$B13*G13 -> 0 | EO13: =$B13*H13 -> 0 | EP13: =$B13*I13 -> 0 | EQ13: =$B13*J13 -> 3.9731566e-05 | ... JO13: =$B13*EH13 -> 0
... A136: 135 | B136: =OFFSET('ТЗВ всего'!$D$175,0,'quadruple effect'!A136) -> 1.00272 | C136: ='tertiary effect'!EJ136 -> 18.539853 | D136: ='tertiary effect'!EK136 -> 0 | E136: ='tertiary effect'!EL136 -> 2.6213105 | F136: ='tertiary effect'!EM136 -> 0 | G136: ='tertiary effect'!EN136 -> 0 | H136: ='tertiary effect'!EO136 -> 0 | I136: ='tertiary effect'!EP136 -> 0 | J136: ='tertiary effect'!EQ136 -> 0 | ... EH136: ='tertiary effect'!JO136 -> 0 | EJ136: =$B136*C136 -> 18.590282 | EK136: =$B136*D136 -> 0 | EL136: =$B136*E136 -> 2.6284406 | EM136: =$B136*F136 -> 0 | EN136: =$B136*G136 -> 0 | EO136: =$B136*H136 -> 0 | EP136: =$B136*I136 -> 0 | EQ136: =$B136*J136 -> 0 | ... JO136: =$B136*EH136 -> 0
EJ137: =SUM(EJ1:EJ136) -> 13769630 | EK137: =SUM(EK1:EK136) -> 26758483 | EL137: =SUM(EL1:EL136) -> 10605933 | EM137: =SUM(EM1:EM136) -> 5490016.5 | EN137: =SUM(EN1:EN136) -> 72582369 | EO137: =SUM(EO1:EO136) -> 23687740 | EP137: =SUM(EP1:EP136) -> 2642736.8 | EQ137: =SUM(EQ1:EQ136) -> 1370477.7 | ... JO137: =SUM(JO1:JO136) -> 3257679.9

Sheet quintuple effect
A1: 0 | B1: ='ТЗВ всего'!D177 -> 1.0005788 | C1: ='quadruple effect'!EJ1 -> 5099339.3 | D1: ='quadruple effect'!EK1 -> 1060568.3 | E1: ='quadruple effect'!EL1 -> 1277524.1 | F1: ='quadruple effect'!EM1 -> 910424.52 | G1: ='quadruple effect'!EN1 -> 5331271 | H1: ='quadruple effect'!EO1 -> 1434343 | I1: ='quadruple effect'!EP1 -> 535.34772 | J1: ='quadruple effect'!EQ1 -> 128422.32 | ... EH1: ='quadruple effect'!JO1 -> 76.542106 | EJ1: =$B1*C1 -> 5102290.8 | EK1: =$B1*D1 -> 1061182.2 | EL1: =$B1*E1 -> 1278263.5 | EM1: =$B1*F1 -> 910951.48 | EN1: =$B1*G1 -> 5334356.8 | EO1: =$B1*H1 -> 1435173.2 | EP1: =$B1*I1 -> 535.65758 | EQ1: =$B1*J1 -> 128496.66 | ... JO1: =$B1*EH1 -> 76.586409
A2: 1 | B2: =OFFSET('ТЗВ всего'!$D$177,0,'quintuple effect'!A2) -> 1.0004039 | C2: ='quadruple effect'!EJ2 -> 844416.09 | D2: ='quadruple effect'!EK2 -> 14854656 | E2: ='quadruple effect'!EL2 -> 1412026.9 | F2: ='quadruple effect'!EM2 -> 701235.94 | G2: ='quadruple effect'!EN2 -> 414858.47 | H2: ='quadruple effect'!EO2 -> 2813590.8 | I2: ='quadruple effect'!EP2 -> 3631.9192 | J2: ='quadruple effect'!EQ2 -> 279.66529 | ... EH2: ='quadruple effect'!JO2 -> 3180.1645 | EJ2: =$B2*C2 -> 844757.15 | EK2: =$B2*D2 -> 14860656 | EL2: =$B2*E2 -> 1412597.2 | EM2: =$B2*F2 -> 701519.17 | EN2: =$B2*G2 -> 415026.03 | EO2: =$B2*H2 -> 2814727.2 | EP2: =$B2*I2 -> 3633.3861 | EQ2: =$B2*J2 -> 279.77825 | ... JO2: =$B2*EH2 -> 3181.449
A3: 2 | B3: =OFFSET('ТЗВ всего'!$D$177,0,'quintuple effect'!A3) -> 1.0005808 | C3: ='quadruple effect'!EJ3 -> 1365062.4 | D3: ='quadruple effect'!EK3 -> 20193.563 | E3: ='quadruple effect'!EL3 -> 730205.07 | F3: ='quadruple effect'!EM3 -> 0 | G3: ='quadruple effect'!EN3 -> 0 | H3: ='quadruple effect'!EO3 -> 5573.5913 | I3: ='quadruple effect'!EP3 -> 0 | J3: ='quadruple effect'!EQ3 -> 0 | ... EH3: ='quadruple effect'!JO3 -> 0 | EJ3: =$B3*C3 -> 1365855.3 | EK3: =$B3*D3 -> 20205.292 | EL3: =$B3*E3 -> 730629.17 | EM3: =$B3*F3 -> 0 | EN3: =$B3*G3 -> 0 | EO3: =$B3*H3 -> 5576.8284 | EP3: =$B3*I3 -> 0 | EQ3: =$B3*J3 -> 0 | ... JO3: =$B3*EH3 -> 0
A4: 3 | B4: =OFFSET('ТЗВ всего'!$D$177,0,'quintuple effect'!A4) -> 1.0004517 | C4: ='quadruple effect'!EJ4 -> 18751.621 | D4: ='quadruple effect'!EK4 -> 259455.15 | E4: ='quadruple effect'!EL4 -> 97.480356 | F4: ='quadruple effect'!EM4 -> 375726.19 | G4: ='quadruple effect'!EN4 -> 23097.912 | H4: ='quadruple effect'!EO4 -> 170118.53 | I4: ='quadruple effect'!EP4 -> 0 | J4: ='quadruple effect'!EQ4 -> 175.04911 | ... EH4: ='quadruple effect'!JO4 -> 3.2427522 | EJ4: =$B4*C4 -> 18760.09 | EK4: =$B4*D4 -> 259572.34 | EL4: =$B4*E4 -> 97.524385 | EM4: =$B4*F4 -> 375895.9 | EN4: =$B4*G4 -> 23108.345 | EO4: =$B4*H4 -> 170195.37 | EP4: =$B4*I4 -> 0 | EQ4: =$B4*J4 -> 175.12817 | ... JO4: =$B4*EH4 -> 3.2442168
A5: 4 | B5: =OFFSET('ТЗВ всего'!$D$177,0,'quintuple effect'!A5) -> 1.0004886 | C5: ='quadruple effect'!EJ5 -> 700823.57 | D5: ='quadruple effect'!EK5 -> 558844.61 | E5: ='quadruple effect'!EL5 -> 30601.324 | F5: ='quadruple effect'!EM5 -> 222417.51 | G5: ='quadruple effect'!EN5 -> 38108397 | H5: ='quadruple effect'!EO5 -> 1364360.3 | I5: ='quadruple effect'!EP5 -> 12971.204 | J5: ='quadruple effect'!EQ5 -> 26804.51 | ... EH5: ='quadruple effect'!JO5 -> 0 | EJ5: =$B5*C5 -> 701166 | EK5: =$B5*D5 -> 559117.67 | EL5: =$B5*E5 -> 30616.276 | EM5: =$B5*F5 -> 222526.19 | EN5: =$B5*G5 -> 38127018 | EO5: =$B5*H5 -> 1365026.9 | EP5: =$B5*I5 -> 12977.541 | EQ5: =$B5*J5 -> 26817.607 | ... JO5: =$B5*EH5 -> 0
A6: 5 | B6: =OFFSET('ТЗВ всего'!$D$177,0,'quintuple effect'!A6) -> 1.0005504 | C6: ='quadruple effect'!EJ6 -> 2012391 | D6: ='quadruple effect'!EK6 -> 5973891.1 | E6: ='quadruple effect'!EL6 -> 2329559.8 | F6: ='quadruple effect'!EM6 -> 2363742.4 | G6: ='quadruple effect'!EN6 -> 10237178 | H6: ='quadruple effect'!EO6 -> 10087775 | I6: ='quadruple effect'!EP6 -> 267095.15 | J6: ='quadruple effect'!EQ6 -> 29282.3 | ... EH6: ='quadruple effect'!JO6 -> 22301.889 | EJ6: =$B6*C6 -> 2013498.7 | EK6: =$B6*D6 -> 5977179.3 | EL6: =$B6*E6 -> 2330842 | EM6: =$B6*F6 -> 2365043.5 | EN6: =$B6*G6 -> 10242813 | EO6: =$B6*H6 -> 10093327 | EP6: =$B6*I6 -> 267242.16 | EQ6: =$B6*J6 -> 29298.418 | ... JO6: =$B6*EH6 -> 22314.165
A7: 6 | B7: =OFFSET('ТЗВ всего'!$D$177,0,'quintuple effect'!A7) -> 1.0001964 | C7: ='quadruple effect'!EJ7 -> 1.0211284 | D7: ='quadruple effect'!EK7 -> 47198.839 | E7: ='quadruple effect'!EL7 -> 0 | F7: ='quadruple effect'!EM7 -> 572.74692 | G7: ='quadruple effect'!EN7 -> 164266.83 | H7: ='quadruple effect'!EO7 -> 12321.02 | I7: ='quadruple effect'!EP7 -> 1866452.4 | J7: ='quadruple effect'!EQ7 -> 441.12458 | ... EH7: ='quadruple effect'!JO7 -> 0 | EJ7: =$B7*C7 -> 1.021329 | EK7: =$B7*D7 -> 47208.108 | EL7: =$B7*E7 -> 0 | EM7: =$B7*F7 -> 572.85939 | EN7: =$B7*G7 -> 164299.09 | EO7: =$B7*H7 -> 12323.44 | EP7: =$B7*I7 -> 1866818.9 | EQ7: =$B7*J7 -> 441.21121 | ... JO7: =$B7*EH7 -> 0
A8: 7 | B8: =OFFSET('ТЗВ всего'!$D$177,0,'quintuple effect'!A8) -> 1.0006265 | C8: ='quadruple effect'!EJ8 -> 2390.2078 | D8: ='quadruple effect'!EK8 -> 16941.006 | E8: ='quadruple effect'!EL8 -> 197.1716 | F8: ='quadruple effect'!EM8 -> 710.71833 | G8: ='quadruple effect'!EN8 -> 156287.31 | H8: ='quadruple effect'!EO8 -> 4213.8682 | I8: ='quadruple effect'!EP8 -> 0 | J8: ='quadruple effect'!EQ8 -> 594249.37 | ... EH8: ='quadruple effect'!JO8 -> 15.244571 | EJ8: =$B8*C8 -> 2391.7053 | EK8: =$B8*D8 -> 16951.619 | EL8: =$B8*E8 -> 197.29513 | EM8: =$B8*F8 -> 711.16359 | EN8: =$B8*G8 -> 156385.22 | EO8: =$B8*H8 -> 4216.5082 | EP8: =$B8*I8 -> 0 | EQ8: =$B8*J8 -> 594621.67 | ... JO8: =$B8*EH8 -> 15.254122
A9: 8 | B9: =OFFSET('ТЗВ всего'!$D$177,0,'quintuple effect'!A9) -> 1.0006118 | C9: ='quadruple effect'!EJ9 -> 1212.6641 | D9: ='quadruple effect'!EK9 -> 1257.9372 | E9: ='quadruple effect'!EL9 -> 582.81325 | F9: ='quadruple effect'!EM9 -> 0 | G9: ='quadruple effect'!EN9 -> 1786.6858 | H9: ='quadruple effect'!EO9 -> 942.51822 | I9: ='quadruple effect'!EP9 -> 660.96159 | J9: ='quadruple effect'!EQ9 -> 1854.7892 | ... EH9: ='quadruple effect'!JO9 -> 227606.28 | EJ9: =$B9*C9 -> 1213.406 | EK9: =$B9*D9 -> 1258.7067 | EL9: =$B9*E9 -> 583.16979 | EM9: =$B9*F9 -> 0 | EN9: =$B9*G9 -> 1787.7788 | EO9: =$B9*H9 -> 943.09481 | EP9: =$B9*I9 -> 661.36594 | EQ9: =$B9*J9 -> 1855.9239 | ... JO9: =$B9*EH9 -> 227745.52
A10: 9 | B10: =OFFSET('ТЗВ всего'!$D$177,0,'quintuple effect'!A10) -> 1.0003831 | C10: ='quadruple effect'!EJ10 -> 0 | D10: ='quadruple effect'!EK10 -> 0 | E10: ='quadruple effect'!EL10 -> 0 | F10: ='quadruple effect'!EM10 -> 0 | G10: ='quadruple effect'!EN10 -> 0 | H10: ='quadruple effect'!EO10 -> 0 | I10: ='quadruple effect'!EP10 -> 0 | J10: ='quadruple effect'!EQ10 -> 0.050362255 | ... EH10: ='quadruple effect'!JO10 -> 0 | EJ10: =$B10*C10 -> 0 | EK10: =$B10*D10 -> 0 | EL10: =$B10*E10 -> 0 | EM10: =$B10*F10 -> 0 | EN10: =$B10*G10 -> 0 | EO10: =$B10*H10 -> 0 | EP10: =$B10*I10 -> 0 | EQ10: =$B10*J10 -> 0.050381548 | ... JO10: =$B10*EH10 -> 0
A11: 10 | B11: =OFFSET('ТЗВ всего'!$D$177,0,'quintuple effect'!A11) -> 1.0004049 | C11: ='quadruple effect'!EJ11 -> 6311.6949 | D11: ='quadruple effect'!EK11 -> 85167.401 | E11: ='quadruple effect'!EL11 -> 2222.7179 | F11: ='quadruple effect'!EM11 -> 381.01179 | G11: ='quadruple effect'!EN11 -> 98689.058 | H11: ='quadruple effect'!EO11 -> 53119.284 | I11: ='quadruple effect'!EP11 -> 11865.641 | J11: ='quadruple effect'!EQ11 -> 4828.2568 | ... EH11: ='quadruple effect'!JO11 -> 66954.644 | EJ11: =$B11*C11 -> 6314.2506 | EK11: =$B11*D11 -> 85201.887 | EL11: =$B11*E11 -> 2223.6179 | EM11: =$B11*F11 -> 381.16607 | EN11: =$B11*G11 -> 98729.019 | EO11: =$B11*H11 -> 53140.793 | EP11: =$B11*I11 -> 11870.446 | EQ11: =$B11*J11 -> 4830.2119 | ... JO11: =$B11*EH11 -> 66981.755
A12: 11 | B12: =OFFSET('ТЗВ всего'!$D$177,0,'quintuple effect'!A12) -> 1.0006032 | C12: ='quadruple effect'!EJ12 -> 0 | D12: ='quadruple effect'!EK12 -> 0 | E12: ='quadruple effect'!EL12 -> 0 | F12: ='quadruple effect'!EM12 -> 0 | G12: ='quadruple effect'!EN12 -> 0 | H12: ='quadruple effect'!EO12 -> 0 | I12: ='quadruple effect'!EP12 -> 0 | J12: ='quadruple effect'!EQ12 -> 0 | ... EH12: ='quadruple effect'!JO12 -> 0 | EJ12: =$B12*C12 -> 0 | EK12: =$B12*D12 -> 0 | EL12: =$B12*E12 -> 0 | EM12: =$B12*F12 -> 0 | EN12: =$B12*G12 -> 0 | EO12: =$B12*H12 -> 0 | EP12: =$B12*I12 -> 0 | EQ12: =$B12*J12 -> 0 | ... JO12: =$B12*EH12 -> 0
A13: 12 | B13: =OFFSET('ТЗВ всего'!$D$177,0,'quintuple effect'!A13) -> 1.0005571 | C13: ='quadruple effect'!EJ13 -> 0 | D13: ='quadruple effect'!EK13 -> 0 | E13: ='quadruple effect'!EL13 -> 0 | F13: ='quadruple effect'!EM13 -> 0 | G13: ='quadruple effect'!EN13 -> 0 | H13: ='quadruple effect'!EO13 -> 0 | I13: ='quadruple effect'!EP13 -> 0 | J13: ='quadruple effect'!EQ13 -> 3.9731566e-05 | ... EH13: ='quadruple effect'!JO13 -> 0 | EJ13: =$B13*C13 -> 0 | EK13: =$B13*D13 -> 0 | EL13: =$B13*E13 -> 0 | EM13: =$B13*F13 -> 0 | EN13: =$B13*G13 -> 0 | EO13: =$B13*H13 -> 0 | EP13: =$B13*I13 -> 0 | EQ13: =$B13*J13 -> 3.97537e-05 | ... JO13: =$B13*EH13 -> 0
... A136: 135 | B136: =OFFSET('ТЗВ всего'!$D$177,0,'quintuple effect'!A136) -> 1.0005304 | C136: ='quadruple effect'!EJ136 -> 18.590282 | D136: ='quadruple effect'!EK136 -> 0 | E136: ='quadruple effect'!EL136 -> 2.6284406 | F136: ='quadruple effect'!EM136 -> 0 | G136: ='quadruple effect'!EN136 -> 0 | H136: ='quadruple effect'!EO136 -> 0 | I136: ='quadruple effect'!EP136 -> 0 | J136: ='quadruple effect'!EQ136 -> 0 | ... EH136: ='quadruple effect'!JO136 -> 0 | EJ136: =$B136*C136 -> 18.600143 | EK136: =$B136*D136 -> 0 | EL136: =$B136*E136 -> 2.6298348 | EM136: =$B136*F136 -> 0 | EN136: =$B136*G136 -> 0 | EO136: =$B136*H136 -> 0 | EP136: =$B136*I136 -> 0 | EQ136: =$B136*J136 -> 0 | ... JO136: =$B136*EH136 -> 0
DM137: ='quadruple effect'!IT137 -> 3095247.8 | DN137: ='quadruple effect'!IU137 -> 420774.47 | DO137: ='quadruple effect'!IV137 -> 726529.97 | DP137: ='quadruple effect'!IW137 -> 345452.63 | DQ137: ='quadruple effect'!IX137 -> 88124.641 | DR137: ='quadruple effect'!IY137 -> 2580713.1 | DS137: ='quadruple effect'!IZ137 -> 141540.33 | DT137: ='quadruple effect'!JA137 -> 255971.98 | ... EH137: ='quadruple effect'!JO137 -> 3257679.9 | EJ137: =SUM(EJ1:EJ136) -> 13778679 | EK137: =SUM(EK1:EK136) -> 26771959 | EL137: =SUM(EL1:EL136) -> 10613388 | EM137: =SUM(EM1:EM136) -> 5493159 | EN137: =SUM(EN1:EN136) -> 72627703 | EO137: =SUM(EO1:EO136) -> 23703984 | EP137: =SUM(EP1:EP136) -> 2643676 | EQ137: =SUM(EQ1:EQ136) -> 1371476.5 | ... JO137: =SUM(JO1:JO136) -> 3259952.1

Sheet Int cons analysis
C1: сhange in intermediate consumption | D1: ='ТЗВ всего'!D151 -> 8039971.9 | E1: ='ТЗВ всего'!E151 -> 15871116 | F1: ='ТЗВ всего'!F151 -> 6131402.7 | G1: ='ТЗВ всего'!G151 -> 3242381.1 | H1: ='ТЗВ всего'!H151 -> 42577263 | I1: ='ТЗВ всего'!I151 -> 13849875 | J1: ='ТЗВ всего'!J151 -> 1606737.8 | K1: ='ТЗВ всего'!K151 -> 797982.26 | ... EI1: ='ТЗВ всего'!EI151 -> 1924672.3
D2: ='ТЗВ всего'!D152 -> 1411320.4 | E2: ='ТЗВ всего'!E152 -> 2476374.6 | F2: ='ТЗВ всего'!F152 -> 1164204.2 | G2: ='ТЗВ всего'!G152 -> 520918.46 | H2: ='ТЗВ всего'!H152 -> 7215890.4 | I2: ='ТЗВ всего'!I152 -> 2404867.2 | J2: ='ТЗВ всего'!J152 -> 199238.11 | K2: ='ТЗВ всего'!K152 -> 142619.89 | ... EI2: ='ТЗВ всего'!EI152 -> 303085.71
D3: ='ТЗВ всего'!D153 -> 255875.88 | E3: ='ТЗВ всего'!E153 -> 411544.9 | F3: ='ТЗВ всего'!F153 -> 210042.65 | G3: ='ТЗВ всего'!G153 -> 90745.067 | H3: ='ТЗВ всего'!H153 -> 1287179.2 | I3: ='ТЗВ всего'!I153 -> 435354.23 | J3: ='ТЗВ всего'!J153 -> 29553.804 | K3: ='ТЗВ всего'!K153 -> 26462.113 | ... EI3: ='ТЗВ всего'!EI153 -> 58802.082
D4: ='ТЗВ всего'!D154 -> 47521.788 | E4: ='ТЗВ всего'!E154 -> 72550.834 | F4: ='ТЗВ всего'!F154 -> 38940.696 | G4: ='ТЗВ всего'!G154 -> 16571.269 | H4: ='ТЗВ всего'!H154 -> 237641.38 | I4: ='ТЗВ всего'!I154 -> 82294.41 | J4: ='ТЗВ всего'!J154 -> 5025.9468 | K4: ='ТЗВ всего'!K154 -> 5060.3674 | ... EI4: ='ТЗВ всего'!EI154 -> 11497.922
D5: ='ТЗВ всего'!D155 -> 9049.4629 | E5: ='ТЗВ всего'!E155 -> 13476.029 | F5: ='ТЗВ всего'!F155 -> 7454.7728 | G5: ='ТЗВ всего'!G155 -> 3142.5017 | H5: ='ТЗВ всего'!H155 -> 45334.886 | I5: ='ТЗВ всего'!I155 -> 16244.11 | J5: ='ТЗВ всего'!J155 -> 939.22142 | K5: ='ТЗВ всего'!K155 -> 998.73782 | ... EI5: ='ТЗВ всего'!EI155 -> 2272.2712
A6: iteration | B6: ratios of successive changes in industry-specific intermediate consumption to previous ones (standard deviation) | C6: ratios of successive abs. changes in industry-specific intermediate consuption to previous ones (unweighted mean across the industries)
A7: 2 | B7: =_xlfn.STDEV.P(D7:EI7) -> 0.035041256 | C7: =AVERAGE(D7:EI7) -> 0.19301179 | D7: =D2/D1 -> 0.17553797 | E7: =E2/E1 -> 0.15603027 | F7: =F2/F1 -> 0.18987568 | G7: =G2/G1 -> 0.16065923 | H7: =H2/H1 -> 0.16947755 | I7: =I2/I1 -> 0.17363819 | J7: =J2/J1 -> 0.12400163 | K7: =K2/K1 -> 0.17872564 | ... EI7: =EI2/EI1 -> 0.15747393
A8: 3 | B8: =_xlfn.STDEV.P(D8:EI8) -> 0.021148646 | C8: =AVERAGE(D8:EI8) -> 0.19446967 | D8: =D3/D2 -> 0.18130248 | E8: =E3/E2 -> 0.16618847 | F8: =F3/F2 -> 0.18041736 | G8: =G3/G2 -> 0.17420206 | H8: =H3/H2 -> 0.1783812 | I8: =I3/I2 -> 0.18103047 | J8: =J3/J2 -> 0.14833409 | K8: =K3/K2 -> 0.18554294 | ... EI8: =EI3/EI2 -> 0.1940114
A9: 4 | B9: =_xlfn.STDEV.P(D9:EI9) -> 0.016667546 | C9: =AVERAGE(D9:EI9) -> 0.1981457 | D9: =D4/D3 -> 0.18572203 | E9: =E4/E3 -> 0.17628899 | F9: =F4/F3 -> 0.18539423 | G9: =G4/G3 -> 0.18261345 | H9: =H4/H3 -> 0.18462183 | I9: =I4/I3 -> 0.18902862 | J9: =J4/J3 -> 0.17006091 | K9: =K4/K3 -> 0.19123066 | ... EI9: =EI4/EI3 -> 0.19553597
A10: 5 | B10: =_xlfn.STDEV.P(D10:EI10) -> 0.014687487 | C10: =AVERAGE(D10:EI10) -> 0.20256761 | D10: =D5/D4 -> 0.19042766 | E10: =E5/E4 -> 0.18574603 | F10: =F5/F4 -> 0.19143912 | G10: =G5/G4 -> 0.18963555 | H10: =H5/H4 -> 0.19077016 | I10: =I5/I4 -> 0.1973902 | J10: =J5/J4 -> 0.18687452 | K10: =K5/K4 -> 0.19736469 | ... EI10: =EI5/EI4 -> 0.1976245
